Workbook

Sheet เริ่มที่นี่
A1: แม่แบบโครงการ TCRoof (ทุกกรณี), เริ่มที่นี่
A2: เลือกบทบาทของคุณด้านล่าง ทำแค่ 3 อย่างต่อสัปดาห์, ที่เหลือคำนวณเอง
A4: วันที่ข้อมูล | C4: COD ทั้งเฟส (คาดการณ์) | E4: ติดตั้งแล้ว | F4: COD แล้ว | G4: Milestone ทำได้ตามที่ควร | I4: ดึงจากแอปล่าสุด
A5: =ASOF -> 46328 | C5: ='Master Plan'!C4 -> 46433 | E5: ='Master Plan'!F4 -> 0 / 20 | F5: ='Master Plan'!D4 -> 0 / 20 | G5: =Milestone!G4 -> 0 | I5: =IF(ISNUMBER(TCRoof!B3),TCRoof!B3,"ยังไม่เชื่อม") -> ยังไม่เชื่อม
A7: Admin โครงการ | B7: 1. กรอกวันจริง / นัด / Y ที่ชีตอัปเดต (ช่องเหลือง) | H7: → อัปเดตรายสัปดาห์
B8: 2. แก้แถวที่มี ⚠ ใน Master Plan (คอลัมน์ขวาสุด) | H8: → Master Plan
B9: 3. นัดเลื่อน → บันทึก 1 แถว (เหตุผล + ผู้อนุมัติ) | H9: → บันทึกการเปลี่ยนแปลง
A11: วิศวกร | B11: 1. ดูงานของสัปดาห์นี้และ 3 สัปดาห์ข้างหน้า | H11: → งาน 3 สัปดาห์ข้างหน้า
B12: 2. กรอก S / Y ชิ้นงานของสัปดาห์ (กรองชื่อตัวเอง + ‘ช่วงนี้’), งานติดตั้งรายจุดที่ชีตจุดติดตั้ง | H12: → อัปเดตงาน WBS
B13: 3. ก่อนติ๊กเสร็จ ดูจุดตรวจ ICL ตามแบบมาตรฐาน, เจองานแก้ซ้ำ → บันทึกที่ Cost of Quality | H13: → ICL ตรวจหน้างาน
A15: ผู้รับเหมา | B15: 1. บันทึกงานในแอป TCRoof (รายงานประจำวัน, แผนงาน MP, IEC)
B16: 2. ดูแผนสถานีของตัวเองจากตารางด้านล่าง (กรอง ผรม.)
B17: ไม่ต้องกรอก Excel — ตัวเลขจากแอปเข้ามาเองทุก 5 นาที
A19: ผู้บริหาร / PM | B19: 1. ดูหมุดสำคัญ: ควรเสร็จ vs เสร็จจริง และ COD | H19: → Milestone
B20: 2. ดูความเสี่ยงระดับสูง และอนุมัติ CR ที่รออยู่ | H20: → ทะเบียนความเสี่ยง
B21: 3. ดูแนวโน้มรายสัปดาห์ | H21: → ประวัติสรุป
A24: หาสถานี: กรองคอลัมน์ ผรม. / วิศวกร แล้วคลิกรหัสเพื่อเปิดแผนของสถานีนั้น
A25: รหัส | B25: สถานี | C25: ผรม. | D25: วิศวกร | E25: COD คาดการณ์ | F25: ช้ากว่า Baseline (วัน) | G25: % งาน | H25: งานถัดไป | I25: ⚠ ตรวจข้อมูล
A26: P9-001 | B26: แม่แบบ หลังคาลอนคู่, กันย้อน HV, Inverter < 200 kVA | C26: 01 | D26: วศ.01 | E26: ='Master Plan'!$AH$8 -> 46433 | F26: ='Master Plan'!$AJ$8 -> -3 | G26: ='Master Plan'!$AM$8 -> 0 | H26: ='P9-001'!$B$5 -> จัดหาและรับอุปกรณ์ (หนังสือส่งแผง + ตรวจรับของ) | I26: ='Master Plan'!$AN$8
A27: P9-002 | B27: แม่แบบ หลังคาลอนคู่, กันย้อน HV, Inverter ≥ 200 kVA | C27: 02 | D27: วศ.02 | E27: ='Master Plan'!$AH$9 -> 46433 | F27: ='Master Plan'!$AJ$9 -> -3 | G27: ='Master Plan'!$AM$9 -> 0 | H27: ='P9-002'!$B$5 -> จัดหาและรับอุปกรณ์ (หนังสือส่งแผง + ตรวจรับของ) | I27: ='Master Plan'!$AN$9
A28: P9-003 | B28: แม่แบบ หลังคาลอนคู่, กันย้อน LV, Inverter < 200 kVA | C28: 03 | D28: วศ.03 | E28: ='Master Plan'!$AH$10 -> 46433 | F28: ='Master Plan'!$AJ$10 -> -3 | G28: ='Master Plan'!$AM$10 -> 0 | H28: ='P9-003'!$B$5 -> จัดหาและรับอุปกรณ์ (หนังสือส่งแผง + ตรวจรับของ) | I28: ='Master Plan'!$AN$10
A29: P9-004 | B29: แม่แบบ หลังคาลอนคู่, กันย้อน LV, Inverter ≥ 200 kVA | C29: 04 | D29: วศ.04 | E29: ='Master Plan'!$AH$11 -> 46433 | F29: ='Master Plan'!$AJ$11 -> -3 | G29: ='Master Plan'!$AM$11 -> 0 | H29: ='P9-004'!$B$5 -> จัดหาและรับอุปกรณ์ (หนังสือส่งแผง + ตรวจรับของ) | I29: ='Master Plan'!$AN$11
A30: P9-005 | B30: แม่แบบ หลังคาเมทัลชีท, กันย้อน HV, Inverter < 200 kVA | C30: 05 | D30: วศ.05 | E30: ='Master Plan'!$AH$12 -> 46433 | F30: ='Master Plan'!$AJ$12 -> -3 | G30: ='Master Plan'!$AM$12 -> 0 | H30: ='P9-005'!$B$5 -> จัดหาและรับอุปกรณ์ (หนังสือส่งแผง + ตรวจรับของ) | I30: ='Master Plan'!$AN$12
A31: P9-006 | B31: แม่แบบ หลังคาเมทัลชีท, กันย้อน HV, Inverter ≥ 200 kVA | C31: 06 | D31: วศ.06 | E31: ='Master Plan'!$AH$13 -> 46433 | F31: ='Master Plan'!$AJ$13 -> -3 | G31: ='Master Plan'!$AM$13 -> 0 | H31: ='P9-006'!$B$5 -> จัดหาและรับอุปกรณ์ (หนังสือส่งแผง + ตรวจรับของ) | I31: ='Master Plan'!$AN$13
A32: P9-007 | B32: แม่แบบ หลังคาเมทัลชีท, กันย้อน LV, Inverter < 200 kVA | C32: 07 | D32: วศ.07 | E32: ='Master Plan'!$AH$14 -> 46433 | F32: ='Master Plan'!$AJ$14 -> -3 | G32: ='Master Plan'!$AM$14 -> 0 | H32: ='P9-007'!$B$5 -> จัดหาและรับอุปกรณ์ (หนังสือส่งแผง + ตรวจรับของ) | I32: ='Master Plan'!$AN$14
A33: P9-008 | B33: แม่แบบ หลังคาเมทัลชีท, กันย้อน LV, Inverter ≥ 200 kVA | C33: 08 | D33: วศ.08 | E33: ='Master Plan'!$AH$15 -> 46433 | F33: ='Master Plan'!$AJ$15 -> -3 | G33: ='Master Plan'!$AM$15 -> 0 | H33: ='P9-008'!$B$5 -> จัดหาและรับอุปกรณ์ (หนังสือส่งแผง + ตรวจรับของ) | I33: ='Master Plan'!$AN$15
A34: P9-009 | B34: แม่แบบ ถังน้ำใส, กันย้อน HV, Inverter < 200 kVA | C34: 09 | D34: วศ.09 | E34: ='Master Plan'!$AH$16 -> 46433 | F34: ='Master Plan'!$AJ$16 -> -3 | G34: ='Master Plan'!$AM$16 -> 0 | H34: ='P9-009'!$B$5 -> จัดหาและรับอุปกรณ์ (หนังสือส่งแผง + ตรวจรับของ) | I34: ='Master Plan'!$AN$16
A35: P9-010 | B35: แม่แบบ ถังน้ำใส, กันย้อน HV, Inverter ≥ 200 kVA | C35: 10 | D35: วศ.10 | E35: ='Master Plan'!$AH$17 -> 46433 | F35: ='Master Plan'!$AJ$17 -> -3 | G35: ='Master Plan'!$AM$17 -> 0 | H35: ='P9-010'!$B$5 -> จัดหาและรับอุปกรณ์ (หนังสือส่งแผง + ตรวจรับของ) | I35: ='Master Plan'!$AN$17
A36: P9-011 | B36: แม่แบบ ถังน้ำใส, กันย้อน LV, Inverter < 200 kVA | C36: 11 | D36: วศ.11 | E36: ='Master Plan'!$AH$18 -> 46433 | F36: ='Master Plan'!$AJ$18 -> -3 | G36: ='Master Plan'!$AM$18 -> 0 | H36: ='P9-011'!$B$5 -> จัดหาและรับอุปกรณ์ (หนังสือส่งแผง + ตรวจรับของ) | I36: ='Master Plan'!$AN$18
A37: P9-012 | B37: แม่แบบ ถังน้ำใส, กันย้อน LV, Inverter ≥ 200 kVA | C37: 12 | D37: วศ.12 | E37: ='Master Plan'!$AH$19 -> 46433 | F37: ='Master Plan'!$AJ$19 -> -3 | G37: ='Master Plan'!$AM$19 -> 0 | H37: ='P9-012'!$B$5 -> จัดหาและรับอุปกรณ์ (หนังสือส่งแผง + ตรวจรับของ) | I37: ='Master Plan'!$AN$19
A38: P9-013 | B38: แม่แบบ ถังดินกลบ, กันย้อน HV, Inverter < 200 kVA | C38: 13 | D38: วศ.13 | E38: ='Master Plan'!$AH$20 -> 46433 | F38: ='Master Plan'!$AJ$20 -> -3 | G38: ='Master Plan'!$AM$20 -> 0 | H38: ='P9-013'!$B$5 -> จัดหาและรับอุปกรณ์ (หนังสือส่งแผง + ตรวจรับของ) | I38: ='Master Plan'!$AN$20
A39: P9-014 | B39: แม่แบบ ถังดินกลบ, กันย้อน HV, Inverter ≥ 200 kVA | C39: 14 | D39: วศ.14 | E39: ='Master Plan'!$AH$21 -> 46433 | F39: ='Master Plan'!$AJ$21 -> -3 | G39: ='Master Plan'!$AM$21 -> 0 | H39: ='P9-014'!$B$5 -> จัดหาและรับอุปกรณ์ (หนังสือส่งแผง + ตรวจรับของ) | I39: ='Master Plan'!$AN$21
A40: P9-015 | B40: แม่แบบ ถังดินกลบ, กันย้อน LV, Inverter < 200 kVA | C40: 15 | D40: วศ.15 | E40: ='Master Plan'!$AH$22 -> 46433 | F40: ='Master Plan'!$AJ$22 -> -3 | G40: ='Master Plan'!$AM$22 -> 0 | H40: ='P9-015'!$B$5 -> จัดหาและรับอุปกรณ์ (หนังสือส่งแผง + ตรวจรับของ) | I40: ='Master Plan'!$AN$22
A41: P9-016 | B41: แม่แบบ ถังดินกลบ, กันย้อน LV, Inverter ≥ 200 kVA | C41: 16 | D41: วศ.16 | E41: ='Master Plan'!$AH$23 -> 46433 | F41: ='Master Plan'!$AJ$23 -> -3 | G41: ='Master Plan'!$AM$23 -> 0 | H41: ='P9-016'!$B$5 -> จัดหาและรับอุปกรณ์ (หนังสือส่งแผง + ตรวจรับของ) | I41: ='Master Plan'!$AN$23
A42: P9-017 | B42: แม่แบบ Carport, กันย้อน HV, Inverter < 200 kVA | C42: 17 | D42: วศ.17 | E42: ='Master Plan'!$AH$24 -> 46433 | F42: ='Master Plan'!$AJ$24 -> -3 | G42: ='Master Plan'!$AM$24 -> 0 | H42: ='P9-017'!$B$5 -> จัดหาและรับอุปกรณ์ (หนังสือส่งแผง + ตรวจรับของ) | I42: ='Master Plan'!$AN$24
A43: P9-018 | B43: แม่แบบ Carport, กันย้อน HV, Inverter ≥ 200 kVA | C43: 18 | D43: วศ.18 | E43: ='Master Plan'!$AH$25 -> 46433 | F43: ='Master Plan'!$AJ$25 -> -3 | G43: ='Master Plan'!$AM$25 -> 0 | H43: ='P9-018'!$B$5 -> จัดหาและรับอุปกรณ์ (หนังสือส่งแผง + ตรวจรับของ) | I43: ='Master Plan'!$AN$25
A44: P9-019 | B44: แม่แบบ Carport, กันย้อน LV, Inverter < 200 kVA | C44: 19 | D44: วศ.19 | E44: ='Master Plan'!$AH$26 -> 46433 | F44: ='Master Plan'!$AJ$26 -> -3 | G44: ='Master Plan'!$AM$26 -> 0 | H44: ='P9-019'!$B$5 -> จัดหาและรับอุปกรณ์ (หนังสือส่งแผง + ตรวจรับของ) | I44: ='Master Plan'!$AN$26
A45: P9-020 | B45: แม่แบบ Carport, กันย้อน LV, Inverter ≥ 200 kVA | C45: 20 | D45: วศ.20 | E45: ='Master Plan'!$AH$27 -> 46433 | F45: ='Master Plan'!$AJ$27 -> -3 | G45: ='Master Plan'!$AM$27 -> 0 | H45: ='P9-020'!$B$5 -> จัดหาและรับอุปกรณ์ (หนังสือส่งแผง + ตรวจรับของ) | I45: ='Master Plan'!$AN$27

Sheet อัปเดตรายสัปดาห์
A1: อัปเดตความคืบหน้ารายสัปดาห์ – กรอกที่นี่ที่เดียว
A2: ช่องเหลือง: ใส่ ‘วันที่’ (วันเสร็จจริง หรือวันนัดถ้ายังไม่ถึง) หรือ ‘Y’ = เสร็จแล้วแต่ไม่รู้วันที่, ปีเป็น ค.ศ. 2026–2027 เท่านั้น (ระบบไม่รับปี พ.ศ.), ส้ม = วันนัด (หลังวันที่ข้อมูล), เทา = ไม่ต้องทำ, Master Plan และแผนรายโครงการอัปเดตทันที
A3: วันที่ข้อมูล: | B3: =ASOF -> 46328 | C3: ⚙ เปลี่ยนวันที่ข้อมูลที่ชีตสมมติฐาน
A6: สถานี | G6: Part 0 จัดหาและเตรียมงาน (น้ำหนัก 0) | J6: Part PERMIT | W6: Part ติดตั้งอุปกรณ์ | AG6: Part การทดสอบ ส่งมอบ และ PAC
A7: รหัส | B7: สถานี | C7: เขต กฟภ. | D7: Admin | E7: วิศวกร | F7: รอบ | G7: 0.1 บริหาร/HSE/QA | H7: 0.2 รับแผง/อุปกรณ์ | I7: 0.3 หนังสือขอดับไฟ | J7: 1.1 Kick Off | K7: 1.2 Eng. Approve | L7: 1.3 ส่งมอบพื้นที่ | M7: 1.4 อ.1 / เทศบาล | N7: 1.5 ยื่น พค.2 | O7: 1.5.3 พพ. ความเห็น | P7: 1.6 COP / แจ้ง กกพ. | Q7: 1.7.1 ยื่น PPIM | R7: 1.7.2 ยื่นแก้ไขล่าสุด | S7: 1.7.3 ผลพิจารณาแบบ | T7: 1.7.4 ชำระค่าธรรมเนียม | U7: 1.7.5 ขอตรวจระบบ | V7: 1.7.6 ขนานไฟ COD | W7: 2.1 โครงสร้าง+Walkway | X7: 2.2 DC | Y7: 2.3 แผง | Z7: 2.4 FTS | AA7: 2.5 Inverter | AB7: 2.6 AC / MV | AC7: 2.7 ตู้ควบคุม | AD7: 2.8 สื่อสาร+ZE | AE7: 2.9 Monitoring (ติดตั้ง) | AF7: 2.10 ดับไฟเชื่อมระบบ | AG7: 3.1 IEC 62446 | AH7: 3.1.7 ตรวจรับ กฟภ. | AI7: 3.1.2 As-built ส่ง ผรม. | AJ7: 3.1.8 As-built ลงนาม | AK7: 3.2 อบรม/PAC | AL7: 3.2.4 ส่งมอบงวด | AM7: 3.2.5 C-Form ข. | AN7: 3.2.6 C-Form ก. | AO7: 3.2.7 Monitoring ออนระบบ | AP7: หมายเหตุสัปดาห์นี้
A8: P9-001 | B8: แม่แบบ หลังคาลอนคู่, กันย้อน HV, Inverter < 200 kVA | C8: ตย.01 | D8: Admin | E8: วศ.01 | F8: รอบ 9
A9: P9-002 | B9: แม่แบบ หลังคาลอนคู่, กันย้อน HV, Inverter ≥ 200 kVA | C9: ตย.02 | D9: Admin | E9: วศ.02 | F9: รอบ 9
A10: P9-003 | B10: แม่แบบ หลังคาลอนคู่, กันย้อน LV, Inverter < 200 kVA | C10: ตย.03 | D10: Admin | E10: วศ.03 | F10: รอบ 9
A11: P9-004 | B11: แม่แบบ หลังคาลอนคู่, กันย้อน LV, Inverter ≥ 200 kVA | C11: ตย.04 | D11: Admin | E11: วศ.04 | F11: รอบ 9
A12: P9-005 | B12: แม่แบบ หลังคาเมทัลชีท, กันย้อน HV, Inverter < 200 kVA | C12: ตย.05 | D12: Admin | E12: วศ.05 | F12: รอบ 9
A13: P9-006 | B13: แม่แบบ หลังคาเมทัลชีท, กันย้อน HV, Inverter ≥ 200 kVA | C13: ตย.06 | D13: Admin | E13: วศ.06 | F13: รอบ 9
A14: P9-007 | B14: แม่แบบ หลังคาเมทัลชีท, กันย้อน LV, Inverter < 200 kVA | C14: ตย.07 | D14: Admin | E14: วศ.07 | F14: รอบ 9
A15: P9-008 | B15: แม่แบบ หลังคาเมทัลชีท, กันย้อน LV, Inverter ≥ 200 kVA | C15: ตย.08 | D15: Admin | E15: วศ.08 | F15: รอบ 9
A16: P9-009 | B16: แม่แบบ ถังน้ำใส, กันย้อน HV, Inverter < 200 kVA | C16: ตย.09 | D16: Admin | E16: วศ.09 | F16: รอบ 9
A17: P9-010 | B17: แม่แบบ ถังน้ำใส, กันย้อน HV, Inverter ≥ 200 kVA | C17: ตย.10 | D17: Admin | E17: วศ.10 | F17: รอบ 9
A18: P9-011 | B18: แม่แบบ ถังน้ำใส, กันย้อน LV, Inverter < 200 kVA | C18: ตย.11 | D18: Admin | E18: วศ.11 | F18: รอบ 9
A19: P9-012 | B19: แม่แบบ ถังน้ำใส, กันย้อน LV, Inverter ≥ 200 kVA | C19: ตย.12 | D19: Admin | E19: วศ.12 | F19: รอบ 9
... A27: P9-020 | B27: แม่แบบ Carport, กันย้อน LV, Inverter ≥ 200 kVA | C27: ตย.20 | D27: Admin | E27: วศ.20 | F27: รอบ 9

Sheet อัปเดตงาน WBS
A1: อัปเดตงาน WBS รายสัปดาห์ – ทุกสถานีในหน้าเดียว
A2: สัปดาห์ละครั้ง: กรองคอลัมน์ ‘วิศวกร’ เป็นชื่อตัวเอง และ ‘ช่วงนี้’ → กรอกสถานะ S = เริ่มแล้ว (นับ 50% เฉพาะงาน 50/50), Y = ครบตามเกณฑ์เสร็จ ทำหลายงานพร้อมกันได้ กรอก S หลายแถวได้, ดูจากรายงานประจำวัน (R2) และรูปในแอป TCRoof, ICL ไม่ผ่าน → ลด Y เป็น S แล้วบันทึก Cost of Quality
A3: ไม่ต้องกรอกที่นี่: หมุด ◆ (ใส่วันที่ในชีตอัปเดตรายสัปดาห์), โครงสร้าง / DC / แผงของสถานีที่ระบุจุดติดตั้งแล้ว (ติ๊กรายจุดในชีตจุดติดตั้ง), ขั้นงาน Inverter station (ชีตสถานี), งานที่ไม่เป็นชิ้นงาน เช่น ขนของ รอวัสดุ (ลงใน R2 อย่างเดียว)
A4: ช่วงนี้ (ยังไม่เสร็จ) | C4: เลยกำหนด | E4: เริ่มแล้ว (S) | G4: เสร็จ (Y)
A5: =COUNTIF($K$7:$K$1646,"ช่วงนี้") -> 770 | C5: =COUNTIF($K$7:$K$1646,"⚠*") -> 0 | E5: =COUNTIF($L$7:$L$1646,"S") -> 0 | G5: =COUNTIF($L$7:$L$1646,"Y") -> 0
A6: รหัส | B6: สถานี | C6: วิศวกร | D6: ผรม. | E6: WBS | F6: ชิ้นงาน | G6: เกณฑ์เสร็จ (ต้องมีหลักฐาน) | H6: วิธีนับ | I6: เริ่ม (คาดการณ์) | J6: เสร็จ (คาดการณ์) | K6: ช่วงนี้ | L6: สถานะ (S / Y) | M6: หลักฐาน / หมายเหตุ
A7: P9-001 | B7: แม่แบบ หลังคาลอนคู่, กันย้อน HV, Inverter < 200 kVA | C7: วศ.01 | D7: 01 | E7: 0.1.1 | F7: แผนบริหารโครงการ (PEP) + Baseline | G7: ผู้ว่าจ้างอนุมัติ Baseline ก่อนเริ่มรายงาน S-Curve | H7: 0/100 | I7: ='P9-001'!$N$10 -> 46328 | J7: ='P9-001'!$O$10 -> 46340 | K7: =IF(OR(L7="Y",LEFT('P9-001'!$T$10,1)="D"),"",IF(AND(ISNUMBER(J7),J7<ASOF),"⚠ เลยกำหนด",IF(AND(ISNUMBER(I7),I7<=ASOF+14,J7>=ASOF-7),"ช่วงนี้",""))) -> ช่วงนี้
A8: P9-001 | B8: แม่แบบ หลังคาลอนคู่, กันย้อน HV, Inverter < 200 kVA | C8: วศ.01 | D8: 01 | E8: 0.1.2 | F8: แผนความปลอดภัย (HSE Plan, JSA, Permit-to-Work) | G8: แผน HSE อนุมัติก่อนเข้าพื้นที่ | H8: 0/100 | I8: ='P9-001'!$N$11 -> 46328 | J8: ='P9-001'!$O$11 -> 46340 | K8: =IF(OR(L8="Y",LEFT('P9-001'!$T$11,1)="D"),"",IF(AND(ISNUMBER(J8),J8<ASOF),"⚠ เลยกำหนด",IF(AND(ISNUMBER(I8),I8<=ASOF+14,J8>=ASOF-7),"ช่วงนี้",""))) -> ช่วงนี้
A9: P9-001 | B9: แม่แบบ หลังคาลอนคู่, กันย้อน HV, Inverter < 200 kVA | C9: วศ.01 | D9: 01 | E9: 0.1.3 | F9: แผนคุณภาพ (PQP) + แผนตรวจทดสอบ (ITP) | G9: ITP อนุมัติ ใช้เป็นเกณฑ์ตรวจรับทุกงาน | H9: 0/100 | I9: ='P9-001'!$N$12 -> 46328 | J9: ='P9-001'!$O$12 -> 46340 | K9: =IF(OR(L9="Y",LEFT('P9-001'!$T$12,1)="D"),"",IF(AND(ISNUMBER(J9),J9<ASOF),"⚠ เลยกำหนด",IF(AND(ISNUMBER(I9),I9<=ASOF+14,J9>=ASOF-7),"ช่วงนี้",""))) -> ช่วงนี้
A10: P9-001 | B10: แม่แบบ หลังคาลอนคู่, กันย้อน HV, Inverter < 200 kVA | C10: วศ.01 | D10: 01 | E10: 0.1.4 | F10: เอกสารขออนุมัติวัสดุ (Material submittal) | G10: เอกสารอนุมัติวัสดุครบก่อนส่งของ | H10: 0/100 | I10: ='P9-001'!$N$13 -> 46328 | J10: ='P9-001'!$O$13 -> 46346 | K10: =IF(OR(L10="Y",LEFT('P9-001'!$T$13,1)="D"),"",IF(AND(ISNUMBER(J10),J10<ASOF),"⚠ เลยกำหนด",IF(AND(ISNUMBER(I10),I10<=ASOF+14,J10>=ASOF-7),"ช่วงนี้",""))) -> ช่วงนี้
A11: P9-001 | B11: แม่แบบ หลังคาลอนคู่, กันย้อน HV, Inverter < 200 kVA | C11: วศ.01 | D11: 01 | E11: 0.1.5 | F11: รายงานประจำ R1–R4 | G11: ส่งตรงเวลาทุกงวด, R2 ลงนามรับทราบโดยวิศวกร | H11: 0/100 | I11: ='P9-001'!$N$14 -> 46340 | J11: ='P9-001'!$O$14 -> 46450 | K11: =IF(OR(L11="Y",LEFT('P9-001'!$T$14,1)="D"),"",IF(AND(ISNUMBER(J11),J11<ASOF),"⚠ เลยกำหนด",IF(AND(ISNUMBER(I11),I11<=ASOF+14,J11>=ASOF-7),"ช่วงนี้",""))) -> ช่วงนี้
A12: P9-001 | B12: แม่แบบ หลังคาลอนคู่, กันย้อน HV, Inverter < 200 kVA | C12: วศ.01 | D12: 01 | E12: 0.1.6 | F12: การตรวจ HSE / NCR / Punch list หน้างาน | G12: NCR และ Punch list ปิดครบก่อน PAC | H12: 0/100 | I12: ='P9-001'!$N$15 -> 46340 | J12: ='P9-001'!$O$15 -> 46450 | K12: =IF(OR(L12="Y",LEFT('P9-001'!$T$15,1)="D"),"",IF(AND(ISNUMBER(J12),J12<ASOF),"⚠ เลยกำหนด",IF(AND(ISNUMBER(I12),I12<=ASOF+14,J12>=ASOF-7),"ช่วงนี้",""))) -> ช่วงนี้
A13: P9-001 | B13: แม่แบบ หลังคาลอนคู่, กันย้อน HV, Inverter < 200 kVA | C13: วศ.01 | D13: 01 | E13: 0.2.1 | F13: หนังสือส่งแผง / ใบเบิกจากคลัง | G13: มีเลขที่หนังสือ (TC-PML-…) | H13: 0/100 | I13: ='P9-001'!$N$17 -> 46328 | J13: ='P9-001'!$O$17 -> 46328 | K13: =IF(OR(L13="Y",LEFT('P9-001'!$T$17,1)="D"),"",IF(AND(ISNUMBER(J13),J13<ASOF),"⚠ เลยกำหนด",IF(AND(ISNUMBER(I13),I13<=ASOF+14,J13>=ASOF-7),"ช่วงนี้",""))) -> ช่วงนี้
A14: P9-001 | B14: แม่แบบ หลังคาลอนคู่, กันย้อน HV, Inverter < 200 kVA | C14: วศ.01 | D14: 01 | E14: 0.2.2 | F14: ผล FAT Inverter / ตู้ไฟ (+ CT/VT 22 kV) | G14: ใบรับรอง/ผล FAT แนบในเอกสารสถานี | H14: 0/100 | I14: ='P9-001'!$N$18 -> 46328 | J14: ='P9-001'!$O$18 -> 46328 | K14: =IF(OR(L14="Y",LEFT('P9-001'!$T$18,1)="D"),"",IF(AND(ISNUMBER(J14),J14<ASOF),"⚠ เลยกำหนด",IF(AND(ISNUMBER(I14),I14<=ASOF+14,J14>=ASOF-7),"ช่วงนี้",""))) -> ช่วงนี้
A15: P9-001 | B15: แม่แบบ หลังคาลอนคู่, กันย้อน HV, Inverter < 200 kVA | C15: วศ.01 | D15: 01 | E15: 0.2.3 | F15: แผง + Inverter ถึงหน้างาน (ตรวจรับ + S/N) | G15: จำนวนตรง BOM, ไม่มีชำรุด, S/N เข้าแอป | H15: 0/100 | I15: ='P9-001'!$N$19 -> 46328 | J15: ='P9-001'!$O$19 -> 46328 | K15: =IF(OR(L15="Y",LEFT('P9-001'!$T$19,1)="D"),"",IF(AND(ISNUMBER(J15),J15<ASOF),"⚠ เลยกำหนด",IF(AND(ISNUMBER(I15),I15<=ASOF+14,J15>=ASOF-7),"ช่วงนี้",""))) -> ช่วงนี้
A16: P9-001 | B16: แม่แบบ หลังคาลอนคู่, กันย้อน HV, Inverter < 200 kVA | C16: วศ.01 | D16: 01 | E16: 0.2.4 | F16: โครงยึด + Walkway ถึงหน้างาน | G16: ตรวจรับตาม shop drawing | H16: 0/100 | I16: ='P9-001'!$N$20 -> 46328 | J16: ='P9-001'!$O$20 -> 46328 | K16: =IF(OR(L16="Y",LEFT('P9-001'!$T$20,1)="D"),"",IF(AND(ISNUMBER(J16),J16<ASOF),"⚠ เลยกำหนด",IF(AND(ISNUMBER(I16),I16<=ASOF+14,J16>=ASOF-7),"ช่วงนี้",""))) -> ช่วงนี้
A17: P9-001 | B17: แม่แบบ หลังคาลอนคู่, กันย้อน HV, Inverter < 200 kVA | C17: วศ.01 | D17: 01 | E17: 0.2.5 | F17: สายไฟ + รางสาย ถึงหน้างาน | G17: ตรวจรับขนาด/ยี่ห้อตาม submittal | H17: 0/100 | I17: ='P9-001'!$N$21 -> 46328 | J17: ='P9-001'!$O$21 -> 46328 | K17: =IF(OR(L17="Y",LEFT('P9-001'!$T$21,1)="D"),"",IF(AND(ISNUMBER(J17),J17<ASOF),"⚠ เลยกำหนด",IF(AND(ISNUMBER(I17),I17<=ASOF+14,J17>=ASOF-7),"ช่วงนี้",""))) -> ช่วงนี้
A18: P9-001 | B18: แม่แบบ หลังคาลอนคู่, กันย้อน HV, Inverter < 200 kVA | C18: วศ.01 | D18: 01 | E18: 0.2.6 | F18: ตู้ไฟ FTS / DC / AC / METER / PQM / SEM ถึงหน้างาน | G18: ตรวจรับภายในตู้ตามแบบ SLD | H18: 0/100 | I18: ='P9-001'!$N$22 -> 46328 | J18: ='P9-001'!$O$22 -> 46328 | K18: =IF(OR(L18="Y",LEFT('P9-001'!$T$22,1)="D"),"",IF(AND(ISNUMBER(J18),J18<ASOF),"⚠ เลยกำหนด",IF(AND(ISNUMBER(I18),I18<=ASOF+14,J18>=ASOF-7),"ช่วงนี้",""))) -> ช่วงนี้
A19: P9-001 | B19: แม่แบบ หลังคาลอนคู่, กันย้อน HV, Inverter < 200 kVA | C19: วศ.01 | D19: 01 | E19: 0.2.7 | F19: อุปกรณ์ 22 kV ถึงหน้างาน (VT / CT ผ่านทดสอบ กฟภ.) | G19: มีผลทดสอบ CT/VT | H19: 0/100 | I19: ='P9-001'!$N$23 -> 46328 | J19: ='P9-001'!$O$23 -> 46328 | K19: =IF(OR(L19="Y",LEFT('P9-001'!$T$23,1)="D"),"",IF(AND(ISNUMBER(J19),J19<ASOF),"⚠ เลยกำหนด",IF(AND(ISNUMBER(I19),I19<=ASOF+14,J19>=ASOF-7),"ช่วงนี้",""))) -> ช่วงนี้
A20: P9-001 | B20: แม่แบบ หลังคาลอนคู่, กันย้อน HV, Inverter < 200 kVA | C20: วศ.01 | D20: 01 | E20: 0.2.8 | F20: มิเตอร์ + อุปกรณ์สื่อสาร ถึงหน้างาน | G20: ตรวจรับรุ่นตามแบบ | H20: 0/100 | I20: ='P9-001'!$N$24 -> 46328 | J20: ='P9-001'!$O$24 -> 46328 | K20: =IF(OR(L20="Y",LEFT('P9-001'!$T$24,1)="D"),"",IF(AND(ISNUMBER(J20),J20<ASOF),"⚠ เลยกำหนด",IF(AND(ISNUMBER(I20),I20<=ASOF+14,J20>=ASOF-7),"ช่วงนี้",""))) -> ช่วงนี้
A21: P9-001 | B21: แม่แบบ หลังคาลอนคู่, กันย้อน HV, Inverter < 200 kVA | C21: วศ.01 | D21: 01 | E21: 0.3.1 | F21: ร่างหนังสือแจ้งดับไฟ | G21: ร่างหนังสือ + ช่วงดับไฟที่ไม่กระทบการสูบจ่ายน้ำ (สาขายืนยัน) | H21: 0/100 | I21: ='P9-001'!$N$26 -> 46329 | J21: ='P9-001'!$O$26 -> 46329 | K21: =IF(OR(L21="Y",LEFT('P9-001'!$T$26,1)="D"),"",IF(AND(ISNUMBER(J21),J21<ASOF),"⚠ เลยกำหนด",IF(AND(ISNUMBER(I21),I21<=ASOF+14,J21>=ASOF-7),"ช่วงนี้",""))) -> ช่วงนี้
A22: P9-001 | B22: แม่แบบ หลังคาลอนคู่, กันย้อน HV, Inverter < 200 kVA | C22: วศ.01 | D22: 01 | E22: 0.3.2 | F22: หนังสือแจ้งดับไฟ (ส่งล่วงหน้า ≥ 7 วัน) | G22: เลขที่ TC-PML-… และวันส่ง | H22: 0/100 | I22: ='P9-001'!$N$27 -> 46329 | J22: ='P9-001'!$O$27 -> 46329 | K22: =IF(OR(L22="Y",LEFT('P9-001'!$T$27,1)="D"),"",IF(AND(ISNUMBER(J22),J22<ASOF),"⚠ เลยกำหนด",IF(AND(ISNUMBER(I22),I22<=ASOF+14,J22>=ASOF-7),"ช่วงนี้",""))) -> ช่วงนี้
A23: P9-001 | B23: แม่แบบ หลังคาลอนคู่, กันย้อน HV, Inverter < 200 kVA | C23: วศ.01 | D23: 01 | E23: 0.3.3 | F23: วันดับไฟที่ยืนยันแล้ว (สาขา / กฟภ.) | G23: วันดับไฟยืนยันเป็นลายลักษณ์อักษร (สาขา + กฟภ. ถ้า HV) | H23: 0/100 | I23: ='P9-001'!$N$28 -> 46329 | J23: ='P9-001'!$O$28 -> 46329 | K23: =IF(OR(L23="Y",LEFT('P9-001'!$T$28,1)="D"),"",IF(AND(ISNUMBER(J23),J23<ASOF),"⚠ เลยกำหนด",IF(AND(ISNUMBER(I23),I23<=ASOF+14,J23>=ASOF-7),"ช่วงนี้",""))) -> ช่วงนี้
A24: P9-001 | B24: แม่แบบ หลังคาลอนคู่, กันย้อน HV, Inverter < 200 kVA | C24: วศ.01 | D24: 01 | E24: 1.1.1 | F24: บันทึกประชุม Kick off | G24: บันทึกการประชุม (MOM) ลงนามผู้เข้าร่วม | H24: 0/100 | I24: ='P9-001'!$N$31 -> 46328 | J24: ='P9-001'!$O$31 -> 46328 | K24: =IF(OR(L24="Y",LEFT('P9-001'!$T$31,1)="D"),"",IF(AND(ISNUMBER(J24),J24<ASOF),"⚠ เลยกำหนด",IF(AND(ISNUMBER(I24),I24<=ASOF+14,J24>=ASOF-7),"ช่วงนี้",""))) -> ช่วงนี้
A25: P9-001 | B25: แม่แบบ หลังคาลอนคู่, กันย้อน HV, Inverter < 200 kVA | C25: วศ.01 | D25: 01 | E25: 1.1.2 | F25: งาน PWA ในแอป TCRoof | G25: งานในแอปครบ: งาน PWA, เลข MP, ขนาด Inverter, ผู้รับเหมา, ทีม | H25: 0/100 | I25: ='P9-001'!$N$32 -> 46328 | J25: ='P9-001'!$O$32 -> 46328 | K25: =IF(OR(L25="Y",LEFT('P9-001'!$T$32,1)="D"),"",IF(AND(ISNUMBER(J25),J25<ASOF),"⚠ เลยกำหนด",IF(AND(ISNUMBER(I25),I25<=ASOF+14,J25>=ASOF-7),"ช่วงนี้",""))) -> ช่วงนี้
A26: P9-001 | B26: แม่แบบ หลังคาลอนคู่, กันย้อน HV, Inverter < 200 kVA | C26: วศ.01 | D26: 01 | E26: 1.1.3 | F26: แบบสำรวจหน้างาน A1–E1 (REV 00) | G26: แบบสำรวจ A1–E1 ลงนาม 2 ฝ่าย ออก REV 00 | H26: 0/100 | I26: ='P9-001'!$N$33 -> 46328 | J26: ='P9-001'!$O$33 -> 46328 | K26: =IF(OR(L26="Y",LEFT('P9-001'!$T$33,1)="D"),"",IF(AND(ISNUMBER(J26),J26<ASOF),"⚠ เลยกำหนด",IF(AND(ISNUMBER(I26),I26<=ASOF+14,J26>=ASOF-7),"ช่วงนี้",""))) -> ช่วงนี้
A27: P9-001 | B27: แม่แบบ หลังคาลอนคู่, กันย้อน HV, Inverter < 200 kVA | C27: วศ.01 | D27: 01 | E27: 1.2.1 | F27: SLD + Layout + String sizing | G27: SLD + Layout + String sizing ลงนามวิศวกร | H27: 0/100 | I27: ='P9-001'!$N$35 -> 46328 | J27: ='P9-001'!$O$35 -> 46328 | K27: =IF(OR(L27="Y",LEFT('P9-001'!$T$35,1)="D"),"",IF(AND(ISNUMBER(J27),J27<ASOF),"⚠ เลยกำหนด",IF(AND(ISNUMBER(I27),I27<=ASOF+14,J27>=ASOF-7),"ช่วงนี้",""))) -> ช่วงนี้
A28: P9-001 | B28: แม่แบบ หลังคาลอนคู่, กันย้อน HV, Inverter < 200 kVA | C28: วศ.01 | D28: 01 | E28: 1.2.2 | F28: รายการคำนวณไฟฟ้า / โครงสร้าง | G28: รายการคำนวณไฟฟ้า / โยธาลงนาม (มีผลน้ำหนักบนหลังคา) | H28: 0/100 | I28: ='P9-001'!$N$36 -> 46328 | J28: ='P9-001'!$O$36 -> 46328 | K28: =IF(OR(L28="Y",LEFT('P9-001'!$T$36,1)="D"),"",IF(AND(ISNUMBER(J28),J28<ASOF),"⚠ เลยกำหนด",IF(AND(ISNUMBER(I28),I28<=ASOF+14,J28>=ASOF-7),"ช่วงนี้",""))) -> ช่วงนี้
A29: P9-001 | B29: แม่แบบ หลังคาลอนคู่, กันย้อน HV, Inverter < 200 kVA | C29: วศ.01 | D29: 01 | E29: 1.2.3 | F29: ค่าตั้ง Protection / Zero export | G29: ตารางค่าตั้ง Protection / Zero export ลงนาม | H29: 0/100 | I29: ='P9-001'!$N$37 -> 46328 | J29: ='P9-001'!$O$37 -> 46328 | K29: =IF(OR(L29="Y",LEFT('P9-001'!$T$37,1)="D"),"",IF(AND(ISNUMBER(J29),J29<ASOF),"⚠ เลยกำหนด",IF(AND(ISNUMBER(I29),I29<=ASOF+14,J29>=ASOF-7),"ช่วงนี้",""))) -> ช่วงนี้
A30: P9-001 | B30: แม่แบบ หลังคาลอนคู่, กันย้อน HV, Inverter < 200 kVA | C30: วศ.01 | D30: 01 | E30: 1.2.4 | F30: แบบที่ กปภ. อนุมัติ (REV ล่าสุด) | G30: หนังสืออนุมัติแบบจาก กปภ. (REV ล่าสุด) | H30: 0/100 | I30: ='P9-001'!$N$38 -> 46328 | J30: ='P9-001'!$O$38 -> 46328 | K30: =IF(OR(L30="Y",LEFT('P9-001'!$T$38,1)="D"),"",IF(AND(ISNUMBER(J30),J30<ASOF),"⚠ เลยกำหนด",IF(AND(ISNUMBER(I30),I30<=ASOF+14,J30>=ASOF-7),"ช่วงนี้",""))) -> ช่วงนี้
A31: P9-001 | B31: แม่แบบ หลังคาลอนคู่, กันย้อน HV, Inverter < 200 kVA | C31: วศ.01 | D31: 01 | E31: 1.3.1 | F31: บันทึกส่งมอบพื้นที่ | G31: บันทึกส่งมอบพื้นที่ลงนาม กปภ.สาขา | H31: 0/100 | I31: ='P9-001'!$N$40 -> 46328 | J31: ='P9-001'!$O$40 -> 46328 | K31: =IF(OR(L31="Y",LEFT('P9-001'!$T$40,1)="D"),"",IF(AND(ISNUMBER(J31),J31<ASOF),"⚠ เลยกำหนด",IF(AND(ISNUMBER(I31),I31<=ASOF+14,J31>=ASOF-7),"ช่วงนี้",""))) -> ช่วงนี้
A32: P9-001 | B32: แม่แบบ หลังคาลอนคู่, กันย้อน HV, Inverter < 200 kVA | C32: วศ.01 | D32: 01 | E32: 1.3.2 | F32: สิ่งอำนวยความสะดวกหน้างาน (Mobilization) | G32: Site office / ไฟ-น้ำชั่วคราว / กองวัสดุ / ป้ายพร้อม + รูปถ่าย | H32: 0/100 | I32: ='P9-001'!$N$41 -> 46328 | J32: ='P9-001'!$O$41 -> 46328 | K32: =IF(OR(L32="Y",LEFT('P9-001'!$T$41,1)="D"),"",IF(AND(ISNUMBER(J32),J32<ASOF),"⚠ เลยกำหนด",IF(AND(ISNUMBER(I32),I32<=ASOF+14,J32>=ASOF-7),"ช่วงนี้",""))) -> ช่วงนี้
A33: P9-001 | B33: แม่แบบ หลังคาลอนคู่, กันย้อน HV, Inverter < 200 kVA | C33: วศ.01 | D33: 01 | E33: 1.3.3 | F33: คำขอปฏิบัติงาน R1 ฉบับแรก | G33: R1 ฉบับแรกอนุมัติโดย Inspector | H33: 0/100 | I33: ='P9-001'!$N$42 -> 46328 | J33: ='P9-001'!$O$42 -> 46328 | K33: =IF(OR(L33="Y",LEFT('P9-001'!$T$42,1)="D"),"",IF(AND(ISNUMBER(J33),J33<ASOF),"⚠ เลยกำหนด",IF(AND(ISNUMBER(I33),I33<=ASOF+14,J33>=ASOF-7),"ช่วงนี้",""))) -> ช่วงนี้
A34: P9-001 | B34: แม่แบบ หลังคาลอนคู่, กันย้อน HV, Inverter < 200 kVA | C34: วศ.01 | D34: 01 | E34: 1.4.1 | F34: ผลตรวจน้ำหนักบนหลังคา (เลือก อ.1 / แจ้ง) | G34: ผลคำนวณน้ำหนักบนหลังคา + เลือกขอ อ.1 หรือแจ้ง | H34: 0/100 | I34: ='P9-001'!$N$44 -> 46328 | J34: ='P9-001'!$O$44 -> 46328 | K34: =IF(OR(L34="Y",LEFT('P9-001'!$T$44,1)="D"),"",IF(AND(ISNUMBER(J34),J34<ASOF),"⚠ เลยกำหนด",IF(AND(ISNUMBER(I34),I34<=ASOF+14,J34>=ASOF-7),"ช่วงนี้",""))) -> ช่วงนี้
A35: P9-001 | B35: แม่แบบ หลังคาลอนคู่, กันย้อน HV, Inverter < 200 kVA | C35: วศ.01 | D35: 01 | E35: 1.4.2 | F35: ชุดเอกสารขออนุญาต / แจ้งเทศบาล | G35: ชุดเอกสารครบตามรายการของเทศบาล / อบต. | H35: 0/100 | I35: ='P9-001'!$N$45 -> 46328 | J35: ='P9-001'!$O$45 -> 46328 | K35: =IF(OR(L35="Y",LEFT('P9-001'!$T$45,1)="D"),"",IF(AND(ISNUMBER(J35),J35<ASOF),"⚠ เลยกำหนด",IF(AND(ISNUMBER(I35),I35<=ASOF+14,J35>=ASOF-7),"ช่วงนี้",""))) -> ช่วงนี้
A36: P9-001 | B36: แม่แบบ หลังคาลอนคู่, กันย้อน HV, Inverter < 200 kVA | C36: วศ.01 | D36: 01 | E36: 1.4.3 | F36: อ.1 / หนังสือรับแจ้งเทศบาล | G36: ใบรับคำขอ (ยื่น) → อ.1 / หนังสือรับแจ้ง (ได้รับ) | H36: 0/100 | I36: ='P9-001'!$N$46 -> 46328 | J36: ='P9-001'!$O$46 -> 46328 | K36: =IF(OR(L36="Y",LEFT('P9-001'!$T$46,1)="D"),"",IF(AND(ISNUMBER(J36),J36<ASOF),"⚠ เลยกำหนด",IF(AND(ISNUMBER(I36),I36<=ASOF+14,J36>=ASOF-7),"ช่วงนี้",""))) -> ช่วงนี้
A37: P9-001 | B37: แม่แบบ หลังคาลอนคู่, กันย้อน HV, Inverter < 200 kVA | C37: วศ.01 | D37: 01 | E37: 1.6.1 | F37: ผลตรวจเกณฑ์ยกเว้น กกพ. | G37: ผลตรวจเกณฑ์ยกเว้น + ช่องทางแจ้งที่เลือก | H37: 0/100 | I37: ='P9-001'!$N$53 | J37: ='P9-001'!$O$53 | K37: =IF(OR(L37="Y",LEFT('P9-001'!$T$53,1)="D"),"",IF(AND(ISNUMBER(J37),J37<ASOF),"⚠ เลยกำหนด",IF(AND(ISNUMBER(I37),I37<=ASOF+14,J37>=ASOF-7),"ช่วงนี้","")))
A38: P9-001 | B38: แม่แบบ หลังคาลอนคู่, กันย้อน HV, Inverter < 200 kVA | C38: วศ.01 | D38: 01 | E38: 1.6.2 | F38: หลักฐานแจ้งยกเว้น กกพ. | G38: หลักฐานการแจ้ง กกพ. / ชื่อบนเว็บ กกพ. | H38: 0/100 | I38: ='P9-001'!$N$54 | J38: ='P9-001'!$O$54 | K38: =IF(OR(L38="Y",LEFT('P9-001'!$T$54,1)="D"),"",IF(AND(ISNUMBER(J38),J38<ASOF),"⚠ เลยกำหนด",IF(AND(ISNUMBER(I38),I38<=ASOF+14,J38>=ASOF-7),"ช่วงนี้","")))
A39: P9-001 | B39: แม่แบบ หลังคาลอนคู่, กันย้อน HV, Inverter < 200 kVA | C39: วศ.01 | D39: 01 | E39: 2.1.1 | F39: ผังจุดยึด (Mark ตาม shop drawing) | G39: ผังจุดยึด / Mark ครบตาม shop drawing + รูปถ่าย | H39: =IF(COUNTIFS(SITE_ST,"P9-001",SITE_TYPE,"?*")>0,"ตามจุดติดตั้ง →","0/100") -> ตามจุดติดตั้ง → | I39: ='P9-001'!$N$63 -> 46328 | J39: ='P9-001'!$O$63 -> 46329 | K39: =IF(OR(L39="Y",LEFT('P9-001'!$T$63,1)="D"),"",IF(AND(ISNUMBER(J39),J39<ASOF),"⚠ เลยกำหนด",IF(AND(ISNUMBER(I39),I39<=ASOF+14,J39>=ASOF-7),"ช่วงนี้",""))) -> ช่วงนี้
A40: P9-001 | B40: แม่แบบ หลังคาลอนคู่, กันย้อน HV, Inverter < 200 kVA | C40: วศ.01 | D40: 01 | E40: 2.1.2 | F40: บันไดเซอร์วิส / ทางขึ้นลง + Lifeline ชั่วคราว | G40: บันไดตรวจรับแล้ว (ยึดผนังครบ, กรงต่อเนื่อง, ทาสีกันสนิม) ก่อนใช้ขึ้นลง | H40: 0/100 | I40: ='P9-001'!$N$64 -> 46328 | J40: ='P9-001'!$O$64 -> 46331 | K40: =IF(OR(L40="Y",LEFT('P9-001'!$T$64,1)="D"),"",IF(AND(ISNUMBER(J40),J40<ASOF),"⚠ เลยกำหนด",IF(AND(ISNUMBER(I40),I40<=ASOF+14,J40>=ASOF-7),"ช่วงนี้",""))) -> ช่วงนี้
A41: P9-001 | B41: แม่แบบ หลังคาลอนคู่, กันย้อน HV, Inverter < 200 kVA | C41: วศ.01 | D41: 01 | E41: 2.1.3 | F41: ฐานยึดโครงสร้าง (Hanger bolt / Kliplok / พุก) | G41: ฐานยึดครบทุกจุด + กันซึม, ฐานคอนกรีตบ่มครบ 7 วัน (ถ้ามี), รูปถ่าย | H41: =IF(COUNTIFS(SITE_ST,"P9-001",SITE_TYPE,"?*")>0,"ตามจุดติดตั้ง →","50/50") -> ตามจุดติดตั้ง → | I41: ='P9-001'!$N$65 -> 46329 | J41: ='P9-001'!$O$65 -> 46335 | K41: =IF(OR(L41="Y",LEFT('P9-001'!$T$65,1)="D"),"",IF(AND(ISNUMBER(J41),J41<ASOF),"⚠ เลยกำหนด",IF(AND(ISNUMBER(I41),I41<=ASOF+14,J41>=ASOF-7),"ช่วงนี้",""))) -> ช่วงนี้
A42: P9-001 | B42: แม่แบบ หลังคาลอนคู่, กันย้อน HV, Inverter < 200 kVA | C42: วศ.01 | D42: 01 | E42: 2.1.4 | F42: โครง Rail อลูมิเนียม (ขันตามแรงบิด) | G42: Rail / โครงครบ + บันทึกแรงขัน (M8 12, M10 21 N·m) | H42: =IF(COUNTIFS(SITE_ST,"P9-001",SITE_TYPE,"?*")>0,"ตามจุดติดตั้ง →","50/50") -> ตามจุดติดตั้ง → | I42: ='P9-001'!$N$66 -> 46333 | J42: ='P9-001'!$O$66 -> 46339 | K42: =IF(OR(L42="Y",LEFT('P9-001'!$T$66,1)="D"),"",IF(AND(ISNUMBER(J42),J42<ASOF),"⚠ เลยกำหนด",IF(AND(ISNUMBER(I42),I42<=ASOF+14,J42>=ASOF-7),"ช่วงนี้",""))) -> ช่วงนี้
A43: P9-001 | B43: แม่แบบ หลังคาลอนคู่, กันย้อน HV, Inverter < 200 kVA | C43: วศ.01 | D43: 01 | E43: 2.1.5 | F43: Walkway HDG + Lifeline ถาวร | G43: Walkway ยึดครบ ไม่โยก + Lifeline ตึง clips ครบสองปลาย | H43: =IF(COUNTIFS(SITE_ST,"P9-001",SITE_TYPE,"?*")>0,"ตามจุดติดตั้ง →","50/50") -> ตามจุดติดตั้ง → | I43: ='P9-001'!$N$67 -> 46336 | J43: ='P9-001'!$O$67 -> 46340 | K43: =IF(OR(L43="Y",LEFT('P9-001'!$T$67,1)="D"),"",IF(AND(ISNUMBER(J43),J43<ASOF),"⚠ เลยกำหนด",IF(AND(ISNUMBER(I43),I43<=ASOF+14,J43>=ASOF-7),"ช่วงนี้",""))) -> ช่วงนี้
A44: P9-001 | B44: แม่แบบ หลังคาลอนคู่, กันย้อน HV, Inverter < 200 kVA | C44: วศ.01 | D44: 01 | E44: 2.1.6 | F44: ท่อน้ำล้างแผง + ก๊อก | G44: ท่อน้ำ + ก๊อกครบ ทดสอบไม่รั่ว | H44: =IF(COUNTIFS(SITE_ST,"P9-001",SITE_TYPE,"?*")>0,"ตามจุดติดตั้ง →","0/100") -> ตามจุดติดตั้ง → | I44: ='P9-001'!$N$68 -> 46338 | J44: ='P9-001'!$O$68 -> 46341 | K44: =IF(OR(L44="Y",LEFT('P9-001'!$T$68,1)="D"),"",IF(AND(ISNUMBER(J44),J44<ASOF),"⚠ เลยกำหนด",IF(AND(ISNUMBER(I44),I44<=ASOF+14,J44>=ASOF-7),"ช่วงนี้",""))) -> ช่วงนี้
A45: P9-001 | B45: แม่แบบ หลังคาลอนคู่, กันย้อน HV, Inverter < 200 kVA | C45: วศ.01 | D45: 01 | E45: 2.1.7 | F45: ICL โครงสร้าง | G45: ใบ ICL โครงสร้างลงนาม วศ. (ทุกจุดติดตั้ง) | H45: =IF(COUNTIFS(SITE_ST,"P9-001",SITE_TYPE,"?*")>0,"ตามจุดติดตั้ง →","0/100") -> ตามจุดติดตั้ง → | I45: ='P9-001'!$N$69 -> 46340 | J45: ='P9-001'!$O$69 -> 46341 | K45: =IF(OR(L45="Y",LEFT('P9-001'!$T$69,1)="D"),"",IF(AND(ISNUMBER(J45),J45<ASOF),"⚠ เลยกำหนด",IF(AND(ISNUMBER(I45),I45<=ASOF+14,J45>=ASOF-7),"ช่วงนี้",""))) -> ช่วงนี้
A46: P9-001 | B46: แม่แบบ หลังคาลอนคู่, กันย้อน HV, Inverter < 200 kVA | C46: วศ.01 | D46: 01 | E46: 2.2.1 | F46: รางเดินสาย DC (Tray / Steel support) | G46: Tray / รางครบตามแนว มีฝาครบ + Hold-down clamp ทุกจุด | H46: =IF(COUNTIFS(SITE_ST,"P9-001",SITE_TYPE,"?*")>0,"ตามจุดติดตั้ง →","50/50") -> ตามจุดติดตั้ง → | I46: ='P9-001'!$N$71 -> 46343 | J46: ='P9-001'!$O$71 -> 46344 | K46: =IF(OR(L46="Y",LEFT('P9-001'!$T$71,1)="D"),"",IF(AND(ISNUMBER(J46),J46<ASOF),"⚠ เลยกำหนด",IF(AND(ISNUMBER(I46),I46<=ASOF+14,J46>=ASOF-7),"ช่วงนี้","")))
A47: P9-001 | B47: แม่แบบ หลังคาลอนคู่, กันย้อน HV, Inverter < 200 kVA | C47: วศ.01 | D47: 01 | E47: 2.2.2 | F47: สาย PV + MC4 + ป้ายสาย | G47: สาย PV ครบทุกสตริง + MC4 + Label ตาม String map | H47: =IF(COUNTIFS(SITE_ST,"P9-001",SITE_TYPE,"?*")>0,"ตามจุดติดตั้ง →","50/50") -> ตามจุดติดตั้ง → | I47: ='P9-001'!$N$72 -> 46344 | J47: ='P9-001'!$O$72 -> 46345 | K47: =IF(OR(L47="Y",LEFT('P9-001'!$T$72,1)="D"),"",IF(AND(ISNUMBER(J47),J47<ASOF),"⚠ เลยกำหนด",IF(AND(ISNUMBER(I47),I47<=ASOF+14,J47>=ASOF-7),"ช่วงนี้","")))
A48: P9-001 | B48: แม่แบบ หลังคาลอนคู่, กันย้อน HV, Inverter < 200 kVA | C48: วศ.01 | D48: 01 | E48: 2.2.3 | F48: ตู้ DC-DB (Fuse + SPD) | G48: ตู้ DC-DB ครบ: Fuse ทุกสตริง, SPD ถูกชนิด, ป้ายชื่อ, IP65 ถ้าอยู่นอกอาคาร | H48: =IF(COUNTIFS(SITE_ST,"P9-001",SITE_TYPE,"?*")>0,"ตามจุดติดตั้ง →","0/100") -> ตามจุดติดตั้ง → | I48: ='P9-001'!$N$73 -> 46344 | J48: ='P9-001'!$O$73 -> 46345 | K48: =IF(OR(L48="Y",LEFT('P9-001'!$T$73,1)="D"),"",IF(AND(ISNUMBER(J48),J48<ASOF),"⚠ เลยกำหนด",IF(AND(ISNUMBER(I48),I48<=ASOF+14,J48>=ASOF-7),"ช่วงนี้","")))
A49: P9-001 | B49: แม่แบบ หลังคาลอนคู่, กันย้อน HV, Inverter < 200 kVA | C49: วศ.01 | D49: 01 | E49: 2.2.4 | F49: ระบบต่อลงดินโครงแผง (Bonding) | G49: Bonding ครบ Rail / Walkway / Ground lug + สายดินขนาดตามแบบ E10 | H49: =IF(COUNTIFS(SITE_ST,"P9-001",SITE_TYPE,"?*")>0,"ตามจุดติดตั้ง →","0/100") -> ตามจุดติดตั้ง → | I49: ='P9-001'!$N$74 -> 46345 | J49: ='P9-001'!$O$74 -> 46346 | K49: =IF(OR(L49="Y",LEFT('P9-001'!$T$74,1)="D"),"",IF(AND(ISNUMBER(J49),J49<ASOF),"⚠ เลยกำหนด",IF(AND(ISNUMBER(I49),I49<=ASOF+14,J49>=ASOF-7),"ช่วงนี้","")))
A50: P9-001 | B50: แม่แบบ หลังคาลอนคู่, กันย้อน HV, Inverter < 200 kVA | C50: วศ.01 | D50: 01 | E50: 2.2.5 | F50: ICL ระบบ DC (Polarity / Continuity) | G50: ใบ ICL ระบบ DC ลงนาม วศ. | H50: =IF(COUNTIFS(SITE_ST,"P9-001",SITE_TYPE,"?*")>0,"ตามจุดติดตั้ง →","0/100") -> ตามจุดติดตั้ง → | I50: ='P9-001'!$N$75 -> 46345 | J50: ='P9-001'!$O$75 -> 46346 | K50: =IF(OR(L50="Y",LEFT('P9-001'!$T$75,1)="D"),"",IF(AND(ISNUMBER(J50),J50<ASOF),"⚠ เลยกำหนด",IF(AND(ISNUMBER(I50),I50<=ASOF+14,J50>=ASOF-7),"ช่วงนี้","")))
A51: P9-001 | B51: แม่แบบ หลังคาลอนคู่, กันย้อน HV, Inverter < 200 kVA | C51: วศ.01 | D51: 01 | E51: 2.3.1 | F51: แผงถึงจุดติดตั้ง (Lifting plan) | G51: แผงถึงจุดติดตั้งครบตาม Lifting plan ไม่มีแผงเสียหาย | H51: =IF(COUNTIFS(SITE_ST,"P9-001",SITE_TYPE,"?*")>0,"ตามจุดติดตั้ง →","0/100") -> ตามจุดติดตั้ง → | I51: ='P9-001'!$N$77 -> 46342 | J51: ='P9-001'!$O$77 -> 46344 | K51: =IF(OR(L51="Y",LEFT('P9-001'!$T$77,1)="D"),"",IF(AND(ISNUMBER(J51),J51<ASOF),"⚠ เลยกำหนด",IF(AND(ISNUMBER(I51),I51<=ASOF+14,J51>=ASOF-7),"ช่วงนี้",""))) -> ช่วงนี้
A52: P9-001 | B52: แม่แบบ หลังคาลอนคู่, กันย้อน HV, Inverter < 200 kVA | C52: วศ.01 | D52: 01 | E52: 2.3.2 | F52: แผงบนโครง (Clamp ตามแรงบิด) | G52: แผงครบตาม Layout + บันทึกแรงขัน Clamp | H52: =IF(COUNTIFS(SITE_ST,"P9-001",SITE_TYPE,"?*")>0,"ตามจุดติดตั้ง →","50/50") -> ตามจุดติดตั้ง → | I52: ='P9-001'!$N$78 -> 46343 | J52: ='P9-001'!$O$78 -> 46346 | K52: =IF(OR(L52="Y",LEFT('P9-001'!$T$78,1)="D"),"",IF(AND(ISNUMBER(J52),J52<ASOF),"⚠ เลยกำหนด",IF(AND(ISNUMBER(I52),I52<=ASOF+14,J52>=ASOF-7),"ช่วงนี้","")))
A53: P9-001 | B53: แม่แบบ หลังคาลอนคู่, กันย้อน HV, Inverter < 200 kVA | C53: วศ.01 | D53: 01 | E53: 2.3.3 | F53: String ต่อครบตาม String map | G53: ต่อสายครบทุกสตริงตาม String map, Voc ตรงตามคำนวณ | H53: =IF(COUNTIFS(SITE_ST,"P9-001",SITE_TYPE,"?*")>0,"ตามจุดติดตั้ง →","50/50") -> ตามจุดติดตั้ง → | I53: ='P9-001'!$N$79 -> 46344 | J53: ='P9-001'!$O$79 -> 46347 | K53: =IF(OR(L53="Y",LEFT('P9-001'!$T$79,1)="D"),"",IF(AND(ISNUMBER(J53),J53<ASOF),"⚠ เลยกำหนด",IF(AND(ISNUMBER(I53),I53<=ASOF+14,J53>=ASOF-7),"ช่วงนี้","")))
A54: P9-001 | B54: แม่แบบ หลังคาลอนคู่, กันย้อน HV, Inverter < 200 kVA | C54: วศ.01 | D54: 01 | E54: 2.3.4 | F54: S/N แผง + ภาพมุมสูง | G54: สแกน S/N ครบทุกแผง + รูปมุมสูง | H54: =IF(COUNTIFS(SITE_ST,"P9-001",SITE_TYPE,"?*")>0,"ตามจุดติดตั้ง →","0/100") -> ตามจุดติดตั้ง → | I54: ='P9-001'!$N$80 -> 46346 | J54: ='P9-001'!$O$80 -> 46347 | K54: =IF(OR(L54="Y",LEFT('P9-001'!$T$80,1)="D"),"",IF(AND(ISNUMBER(J54),J54<ASOF),"⚠ เลยกำหนด",IF(AND(ISNUMBER(I54),I54<=ASOF+14,J54>=ASOF-7),"ช่วงนี้","")))
A55: P9-001 | B55: แม่แบบ หลังคาลอนคู่, กันย้อน HV, Inverter < 200 kVA | C55: วศ.01 | D55: 01 | E55: 2.3.5 | F55: ICL แผง + String | G55: ใบ ICL แผงลงนาม วศ. | H55: =IF(COUNTIFS(SITE_ST,"P9-001",SITE_TYPE,"?*")>0,"ตามจุดติดตั้ง →","0/100") -> ตามจุดติดตั้ง → | I55: ='P9-001'!$N$81 -> 46347 | J55: ='P9-001'!$O$81 -> 46347 | K55: =IF(OR(L55="Y",LEFT('P9-001'!$T$81,1)="D"),"",IF(AND(ISNUMBER(J55),J55<ASOF),"⚠ เลยกำหนด",IF(AND(ISNUMBER(I55),I55<=ASOF+14,J55>=ASOF-7),"ช่วงนี้","")))
A56: P9-001 | B56: แม่แบบ หลังคาลอนคู่, กันย้อน HV, Inverter < 200 kVA | C56: วศ.01 | D56: 01 | E56: 2.4.1 | F56: ตู้ FTS-DB (Rapid shutdown) | G56: ตู้ FTS-DB ครบตาม E11 (4 สตริงต่อ FTS) | H56: 0/100 | I56: ='P9-001'!$N$83 -> 46345 | J56: ='P9-001'!$O$83 -> 46346 | K56: =IF(OR(L56="Y",LEFT('P9-001'!$T$83,1)="D"),"",IF(AND(ISNUMBER(J56),J56<ASOF),"⚠ เลยกำหนด",IF(AND(ISNUMBER(I56),I56<=ASOF+14,J56>=ASOF-7),"ช่วงนี้","")))
A57: P9-001 | B57: แม่แบบ หลังคาลอนคู่, กันย้อน HV, Inverter < 200 kVA | C57: วศ.01 | D57: 01 | E57: 2.4.2 | F57: วงจรควบคุม E-Stop + ป้ายเตือน | G57: สายควบคุม + E-Stop + ป้ายเตือนครบ | H57: 0/100 | I57: ='P9-001'!$N$84 -> 46346 | J57: ='P9-001'!$O$84 -> 46347 | K57: =IF(OR(L57="Y",LEFT('P9-001'!$T$84,1)="D"),"",IF(AND(ISNUMBER(J57),J57<ASOF),"⚠ เลยกำหนด",IF(AND(ISNUMBER(I57),I57<=ASOF+14,J57>=ASOF-7),"ช่วงนี้","")))
A58: P9-001 | B58: แม่แบบ หลังคาลอนคู่, กันย้อน HV, Inverter < 200 kVA | C58: วศ.01 | D58: 01 | E58: 2.5.1 | F58: Inverter station (ฐาน / โรงเรือน) | G58: Inverter station ครบทุกขั้นตามรูปแบบ (ชีต Inverter station) | H58: ตามขั้น Inverter station | I58: ='P9-001'!$N$86 -> 46343 | J58: ='P9-001'!$O$86 -> 46345 | K58: =IF(OR(L58="Y",LEFT('P9-001'!$T$86,1)="D"),"",IF(AND(ISNUMBER(J58),J58<ASOF),"⚠ เลยกำหนด",IF(AND(ISNUMBER(I58),I58<=ASOF+14,J58>=ASOF-7),"ช่วงนี้","")))
A59: P9-001 | B59: แม่แบบ หลังคาลอนคู่, กันย้อน HV, Inverter < 200 kVA | C59: วศ.01 | D59: 01 | E59: 2.5.2 | F59: Inverter บน Rack + S/N | G59: Inverter ครบทุกตัว + สแกน S/N | H59: 50/50 | I59: ='P9-001'!$N$87 -> 46344 | J59: ='P9-001'!$O$87 -> 46346 | K59: =IF(OR(L59="Y",LEFT('P9-001'!$T$87,1)="D"),"",IF(AND(ISNUMBER(J59),J59<ASOF),"⚠ เลยกำหนด",IF(AND(ISNUMBER(I59),I59<=ASOF+14,J59>=ASOF-7),"ช่วงนี้","")))
A60: P9-001 | B60: แม่แบบ หลังคาลอนคู่, กันย้อน HV, Inverter < 200 kVA | C60: วศ.01 | D60: 01 | E60: 2.5.3 | F60: สาย AC Inverter → AC-DB | G60: สาย Inverter → AC-DB ครบ ขันขั้วตามค่า | H60: 0/100 | I60: ='P9-001'!$N$88 -> 46345 | J60: ='P9-001'!$O$88 -> 46346 | K60: =IF(OR(L60="Y",LEFT('P9-001'!$T$88,1)="D"),"",IF(AND(ISNUMBER(J60),J60<ASOF),"⚠ เลยกำหนด",IF(AND(ISNUMBER(I60),I60<=ASOF+14,J60>=ASOF-7),"ช่วงนี้","")))
A61: P9-001 | B61: แม่แบบ หลังคาลอนคู่, กันย้อน HV, Inverter < 200 kVA | C61: วศ.01 | D61: 01 | E61: 2.5.4 | F61: ICL Inverter | G61: ใบ ICL Inverter ลงนาม วศ. | H61: 0/100 | I61: ='P9-001'!$N$89 -> 46346 | J61: ='P9-001'!$O$89 -> 46346 | K61: =IF(OR(L61="Y",LEFT('P9-001'!$T$89,1)="D"),"",IF(AND(ISNUMBER(J61),J61<ASOF),"⚠ เลยกำหนด",IF(AND(ISNUMBER(I61),I61<=ASOF+14,J61>=ASOF-7),"ช่วงนี้","")))
A62: P9-001 | B62: แม่แบบ หลังคาลอนคู่, กันย้อน HV, Inverter < 200 kVA | C62: วศ.01 | D62: 01 | E62: 2.6.1 | F62: แนวสาย AC ถึงจุดเชื่อม (ท่อ / ราง / สาย) | G62: แนวท่อ / รางสาย AC ครบ + สายถึงจุดเชื่อม | H62: 50/50 | I62: ='P9-001'!$N$91 -> 46344 | J62: ='P9-001'!$O$91 -> 46346 | K62: =IF(OR(L62="Y",LEFT('P9-001'!$T$91,1)="D"),"",IF(AND(ISNUMBER(J62),J62<ASOF),"⚠ เลยกำหนด",IF(AND(ISNUMBER(I62),I62<=ASOF+14,J62>=ASOF-7),"ช่วงนี้","")))
A63: P9-001 | B63: แม่แบบ หลังคาลอนคู่, กันย้อน HV, Inverter < 200 kVA | C63: วศ.01 | D63: 01 | E63: 2.6.2 | F63: Breaker / Busbar จุดเชื่อม (พร้อมวันดับไฟ) | G63: Breaker / Busbar พร้อมติดตั้งในวันดับไฟ | H63: 0/100 | I63: ='P9-001'!$N$92 -> 46346 | J63: ='P9-001'!$O$92 -> 46347 | K63: =IF(OR(L63="Y",LEFT('P9-001'!$T$92,1)="D"),"",IF(AND(ISNUMBER(J63),J63<ASOF),"⚠ เลยกำหนด",IF(AND(ISNUMBER(I63),I63<=ASOF+14,J63>=ASOF-7),"ช่วงนี้","")))
A64: P9-001 | B64: แม่แบบ หลังคาลอนคู่, กันย้อน HV, Inverter < 200 kVA | C64: วศ.01 | D64: 01 | E64: 2.6.3 | F64: ระบบดินฝั่ง AC (< 5 Ω) | G64: ผลวัดค่าดิน < 5 Ω (บันทึกค่า) | H64: 50/50 | I64: ='P9-001'!$N$93 -> 46344 | J64: ='P9-001'!$O$93 -> 46346 | K64: =IF(OR(L64="Y",LEFT('P9-001'!$T$93,1)="D"),"",IF(AND(ISNUMBER(J64),J64<ASOF),"⚠ เลยกำหนด",IF(AND(ISNUMBER(I64),I64<=ASOF+14,J64>=ASOF-7),"ช่วงนี้","")))
A65: P9-001 | B65: แม่แบบ หลังคาลอนคู่, กันย้อน HV, Inverter < 200 kVA | C65: วศ.01 | D65: 01 | E65: 2.6.4 | F65: ไฟแสงสว่าง + เต้ารับ Inverter station | G65: ไฟแสงสว่าง / เต้ารับ Inverter station ใช้งานได้ | H65: 0/100 | I65: ='P9-001'!$N$94 -> 46346 | J65: ='P9-001'!$O$94 -> 46347 | K65: =IF(OR(L65="Y",LEFT('P9-001'!$T$94,1)="D"),"",IF(AND(ISNUMBER(J65),J65<ASOF),"⚠ เลยกำหนด",IF(AND(ISNUMBER(I65),I65<=ASOF+14,J65>=ASOF-7),"ช่วงนี้","")))
A66: P9-001 | B66: แม่แบบ หลังคาลอนคู่, กันย้อน HV, Inverter < 200 kVA | C66: วศ.01 | D66: 01 | E66: 2.6.5 | F66: ICL ระบบ AC | G66: ใบ ICL ระบบ AC + ผลวัดค่าดิน | H66: 0/100 | I66: ='P9-001'!$N$95 -> 46347 | J66: ='P9-001'!$O$95 -> 46347 | K66: =IF(OR(L66="Y",LEFT('P9-001'!$T$95,1)="D"),"",IF(AND(ISNUMBER(J66),J66<ASOF),"⚠ เลยกำหนด",IF(AND(ISNUMBER(I66),I66<=ASOF+14,J66>=ASOF-7),"ช่วงนี้","")))
A67: P9-001 | B67: แม่แบบ หลังคาลอนคู่, กันย้อน HV, Inverter < 200 kVA | C67: วศ.01 | D67: 01 | E67: 2.7.1 | F67: ตู้ AC-DB (MCCB, ELR, SPD, DPM) | G67: ตู้ AC-DB ครบ: MCCB, ELR, SPD, DPM + ป้ายชื่อ | H67: 50/50 | I67: ='P9-001'!$N$97 -> 46345 | J67: ='P9-001'!$O$97 -> 46347 | K67: =IF(OR(L67="Y",LEFT('P9-001'!$T$97,1)="D"),"",IF(AND(ISNUMBER(J67),J67<ASOF),"⚠ เลยกำหนด",IF(AND(ISNUMBER(I67),I67<=ASOF+14,J67>=ASOF-7),"ช่วงนี้","")))
A68: P9-001 | B68: แม่แบบ หลังคาลอนคู่, กันย้อน HV, Inverter < 200 kVA | C68: วศ.01 | D68: 01 | E68: 2.7.2 | F68: ตู้ METER-DB (Revenue meter + CT 0.5S) | G68: ตู้ METER-DB + Revenue meter + VPN ครบตาม E16 | H68: 0/100 | I68: ='P9-001'!$N$98 -> 46346 | J68: ='P9-001'!$O$98 -> 46347 | K68: =IF(OR(L68="Y",LEFT('P9-001'!$T$98,1)="D"),"",IF(AND(ISNUMBER(J68),J68<ASOF),"⚠ เลยกำหนด",IF(AND(ISNUMBER(I68),I68<=ASOF+14,J68>=ASOF-7),"ช่วงนี้","")))
A69: P9-001 | B69: แม่แบบ หลังคาลอนคู่, กันย้อน HV, Inverter < 200 kVA | C69: วศ.01 | D69: 01 | E69: 2.7.3 | F69: ICL ตู้ AC-DB / METER-DB | G69: ใบ ICL ตู้ควบคุมลงนาม วศ. | H69: 0/100 | I69: ='P9-001'!$N$99 -> 46347 | J69: ='P9-001'!$O$99 -> 46347 | K69: =IF(OR(L69="Y",LEFT('P9-001'!$T$99,1)="D"),"",IF(AND(ISNUMBER(J69),J69<ASOF),"⚠ เลยกำหนด",IF(AND(ISNUMBER(I69),I69<=ASOF+14,J69>=ASOF-7),"ช่วงนี้","")))
A70: P9-001 | B70: แม่แบบ หลังคาลอนคู่, กันย้อน HV, Inverter < 200 kVA | C70: วศ.01 | D70: 01 | E70: 2.8.2 | F70: ชุดอุปกรณ์กันย้อน 22 kV บนเสา (E18) | G70: อุปกรณ์บนเสา 22 kV ครบตาม E18, หลักดิน HV / LV ตามระยะ | H70: 0/100 | I70: ='P9-001'!$N$102 -> 46346 | J70: ='P9-001'!$O$102 -> 46347 | K70: =IF(OR(L70="Y",LEFT('P9-001'!$T$102,1)="D"),"",IF(AND(ISNUMBER(J70),J70<ASOF),"⚠ เลยกำหนด",IF(AND(ISNUMBER(I70),I70<=ASOF+14,J70>=ASOF-7),"ช่วงนี้","")))
A71: P9-001 | B71: แม่แบบ หลังคาลอนคู่, กันย้อน HV, Inverter < 200 kVA | C71: วศ.01 | D71: 01 | E71: 2.8.3 | F71: ตู้ PQM / Smart Energy Manager | G71: ตู้ PQM / SEM ครบ อ่านค่าได้ | H71: 0/100 | I71: ='P9-001'!$N$104 -> 46347 | J71: ='P9-001'!$O$104 -> 46348 | K71: =IF(OR(L71="Y",LEFT('P9-001'!$T$104,1)="D"),"",IF(AND(ISNUMBER(J71),J71<ASOF),"⚠ เลยกำหนด",IF(AND(ISNUMBER(I71),I71<=ASOF+14,J71>=ASOF-7),"ช่วงนี้","")))
A72: P9-001 | B72: แม่แบบ หลังคาลอนคู่, กันย้อน HV, Inverter < 200 kVA | C72: วศ.01 | D72: 01 | E72: 2.8.4 | F72: เครือข่ายสื่อสาร (Fiber / CAT6 / RS485 / VPN) | G72: สื่อสารถึง Inverter / มิเตอร์ครบ ทดสอบ ping ได้ | H72: 0/100 | I72: ='P9-001'!$N$105 -> 46347 | J72: ='P9-001'!$O$105 -> 46348 | K72: =IF(OR(L72="Y",LEFT('P9-001'!$T$105,1)="D"),"",IF(AND(ISNUMBER(J72),J72<ASOF),"⚠ เลยกำหนด",IF(AND(ISNUMBER(I72),I72<=ASOF+14,J72>=ASOF-7),"ช่วงนี้","")))
A73: P9-001 | B73: แม่แบบ หลังคาลอนคู่, กันย้อน HV, Inverter < 200 kVA | C73: วศ.01 | D73: 01 | E73: 2.8.5 | F73: ICL กันย้อน + สื่อสาร | G73: ใบ ICL กันย้อนลงนาม วศ. | H73: 0/100 | I73: ='P9-001'!$N$106 -> 46348 | J73: ='P9-001'!$O$106 -> 46348 | K73: =IF(OR(L73="Y",LEFT('P9-001'!$T$106,1)="D"),"",IF(AND(ISNUMBER(J73),J73<ASOF),"⚠ เลยกำหนด",IF(AND(ISNUMBER(I73),I73<=ASOF+14,J73>=ASOF-7),"ช่วงนี้","")))
A74: P9-001 | B74: แม่แบบ หลังคาลอนคู่, กันย้อน HV, Inverter < 200 kVA | C74: วศ.01 | D74: 01 | E74: 2.9.1 | F74: Data logger เชื่อม Data center กปภ. | G74: Data logger ส่งข้อมูลถึง Data center กปภ. | H74: 0/100 | I74: ='P9-001'!$N$108 -> 46347 | J74: ='P9-001'!$O$108 -> 46348 | K74: =IF(OR(L74="Y",LEFT('P9-001'!$T$108,1)="D"),"",IF(AND(ISNUMBER(J74),J74<ASOF),"⚠ เลยกำหนด",IF(AND(ISNUMBER(I74),I74<=ASOF+14,J74>=ASOF-7),"ช่วงนี้","")))
A75: P9-001 | B75: แม่แบบ หลังคาลอนคู่, กันย้อน HV, Inverter < 200 kVA | C75: วศ.01 | D75: 01 | E75: 2.9.2 | F75: ผลทดสอบส่งข้อมูลมิเตอร์ / Inverter | G75: ข้อมูล Inverter / Revenue meter / PQ meter ขึ้นครบ | H75: 0/100 | I75: ='P9-001'!$N$109 -> 46348 | J75: ='P9-001'!$O$109 -> 46348 | K75: =IF(OR(L75="Y",LEFT('P9-001'!$T$109,1)="D"),"",IF(AND(ISNUMBER(J75),J75<ASOF),"⚠ เลยกำหนด",IF(AND(ISNUMBER(I75),I75<=ASOF+14,J75>=ASOF-7),"ช่วงนี้","")))
A76: P9-001 | B76: แม่แบบ หลังคาลอนคู่, กันย้อน HV, Inverter < 200 kVA | C76: วศ.01 | D76: 01 | E76: 2.9.3 | F76: Weather station (Irradiance + อุณหภูมิแผง) | G76: ค่าแสง / อุณหภูมิแผงขึ้นใน Data logger | H76: 0/100 | I76: ='P9-001'!$N$110 -> 46347 | J76: ='P9-001'!$O$110 -> 46348 | K76: =IF(OR(L76="Y",LEFT('P9-001'!$T$110,1)="D"),"",IF(AND(ISNUMBER(J76),J76<ASOF),"⚠ เลยกำหนด",IF(AND(ISNUMBER(I76),I76<=ASOF+14,J76>=ASOF-7),"ช่วงนี้","")))
A77: P9-001 | B77: แม่แบบ หลังคาลอนคู่, กันย้อน HV, Inverter < 200 kVA | C77: วศ.01 | D77: 01 | E77: 2.10.1 | F77: จุดต่อร่วมกับ MDB (ดับไฟ + LOTO) | G77: เชื่อมจุดต่อร่วมเสร็จในเวลาดับไฟ | H77: =IF(COUNTIFS(SITE_ST,"P9-001",SITE_TYPE,"?*")>0,"ตามจุดติดตั้ง →","0/100") -> ตามจุดติดตั้ง → | I77: ='P9-001'!$N$112 -> 46349 | J77: ='P9-001'!$O$112 -> 46349 | K77: =IF(OR(L77="Y",LEFT('P9-001'!$T$112,1)="D"),"",IF(AND(ISNUMBER(J77),J77<ASOF),"⚠ เลยกำหนด",IF(AND(ISNUMBER(I77),I77<=ASOF+14,J77>=ASOF-7),"ช่วงนี้","")))
A78: P9-001 | B78: แม่แบบ หลังคาลอนคู่, กันย้อน HV, Inverter < 200 kVA | C78: วศ.01 | D78: 01 | E78: 2.10.2 | F78: ระบบจ่ายไฟคืน (ลำดับเฟส / แรงดันถูกต้อง) | G78: จ่ายไฟคืน + ลำดับเฟส / แรงดันถูก บันทึกค่า | H78: =IF(COUNTIFS(SITE_ST,"P9-001",SITE_TYPE,"?*")>0,"ตามจุดติดตั้ง →","0/100") -> ตามจุดติดตั้ง → | I78: ='P9-001'!$N$113 -> 46349 | J78: ='P9-001'!$O$113 -> 46349 | K78: =IF(OR(L78="Y",LEFT('P9-001'!$T$113,1)="D"),"",IF(AND(ISNUMBER(J78),J78<ASOF),"⚠ เลยกำหนด",IF(AND(ISNUMBER(I78),I78<=ASOF+14,J78>=ASOF-7),"ช่วงนี้","")))
A79: P9-001 | B79: แม่แบบ หลังคาลอนคู่, กันย้อน HV, Inverter < 200 kVA | C79: วศ.01 | D79: 01 | E79: 3.1.1 | F79: Mechanical completion + Punch list A | G79: Walk-down ลงนาม, Punch list A ปิดครบ | H79: 0/100 | I79: ='P9-001'!$N$116 -> 46359 | J79: ='P9-001'!$O$116 -> 46359 | K79: =IF(OR(L79="Y",LEFT('P9-001'!$T$116,1)="D"),"",IF(AND(ISNUMBER(J79),J79<ASOF),"⚠ เลยกำหนด",IF(AND(ISNUMBER(I79),I79<=ASOF+14,J79>=ASOF-7),"ช่วงนี้","")))
A80: P9-001 | B80: แม่แบบ หลังคาลอนคู่, กันย้อน HV, Inverter < 200 kVA | C80: วศ.01 | D80: 01 | E80: 3.1.2 | F80: ผล IEC 62446 ก่อนเชื่อม (ราย String) | G80: ผล IEC 62446 ก่อนเชื่อม ครบทุก String (แอป IEC ขั้น 2) | H80: 0/100 | I80: ='P9-001'!$N$117 -> 46359 | J80: ='P9-001'!$O$117 -> 46359 | K80: =IF(OR(L80="Y",LEFT('P9-001'!$T$117,1)="D"),"",IF(AND(ISNUMBER(J80),J80<ASOF),"⚠ เลยกำหนด",IF(AND(ISNUMBER(I80),I80<=ASOF+14,J80>=ASOF-7),"ช่วงนี้","")))
A81: P9-001 | B81: แม่แบบ หลังคาลอนคู่, กันย้อน HV, Inverter < 200 kVA | C81: วศ.01 | D81: 01 | E81: 3.1.3 | F81: รายงาน Thermography แผง | G81: รายงาน Thermography แผง 100% | H81: 0/100 | I81: ='P9-001'!$N$118 -> 46359 | J81: ='P9-001'!$O$118 -> 46359 | K81: =IF(OR(L81="Y",LEFT('P9-001'!$T$118,1)="D"),"",IF(AND(ISNUMBER(J81),J81<ASOF),"⚠ เลยกำหนด",IF(AND(ISNUMBER(I81),I81<=ASOF+14,J81>=ASOF-7),"ช่วงนี้","")))
A82: P9-001 | B82: แม่แบบ หลังคาลอนคู่, กันย้อน HV, Inverter < 200 kVA | C82: วศ.01 | D82: 01 | E82: 3.1.4 | F82: ผลทดสอบ FTS / ELR / Shunt trip | G82: ผลทดสอบ FTS / ELR / Shunt trip / SPD ผ่าน | H82: 0/100 | I82: ='P9-001'!$N$119 -> 46359 | J82: ='P9-001'!$O$119 -> 46359 | K82: =IF(OR(L82="Y",LEFT('P9-001'!$T$119,1)="D"),"",IF(AND(ISNUMBER(J82),J82<ASOF),"⚠ เลยกำหนด",IF(AND(ISNUMBER(I82),I82<=ASOF+14,J82>=ASOF-7),"ช่วงนี้","")))
A83: P9-001 | B83: แม่แบบ หลังคาลอนคู่, กันย้อน HV, Inverter < 200 kVA | C83: วศ.01 | D83: 01 | E83: 3.1.5 | F83: ผล Start-up + Zero export / Anti-islanding | G83: ผล Start-up + ทดสอบ Zero export / Anti-islanding ผ่าน | H83: 0/100 | I83: ='P9-001'!$N$120 -> 46359 | J83: ='P9-001'!$O$120 -> 46359 | K83: =IF(OR(L83="Y",LEFT('P9-001'!$T$120,1)="D"),"",IF(AND(ISNUMBER(J83),J83<ASOF),"⚠ เลยกำหนด",IF(AND(ISNUMBER(I83),I83<=ASOF+14,J83>=ASOF-7),"ช่วงนี้","")))
A84: P9-001 | B84: แม่แบบ หลังคาลอนคู่, กันย้อน HV, Inverter < 200 kVA | C84: วศ.01 | D84: 01 | E84: 3.1.6 | F84: ผล IEC หลังเชื่อม + ผลผลิต 7 วัน | G84: ผล IEC หลังเชื่อม + ผลการผลิต 7 วัน, ทีมกดปิดการทดสอบ | H84: 0/100 | I84: ='P9-001'!$N$121 -> 46359 | J84: ='P9-001'!$O$121 -> 46359 | K84: =IF(OR(L84="Y",LEFT('P9-001'!$T$121,1)="D"),"",IF(AND(ISNUMBER(J84),J84<ASOF),"⚠ เลยกำหนด",IF(AND(ISNUMBER(I84),I84<=ASOF+14,J84>=ASOF-7),"ช่วงนี้","")))
A85: P9-001 | B85: แม่แบบ หลังคาลอนคู่, กันย้อน HV, Inverter < 200 kVA | C85: วศ.01 | D85: 01 | E85: 3.2.1 | F85: การอบรมเจ้าหน้าที่ กปภ. | G85: บันทึกการอบรม + รายชื่อผู้เข้าอบรม | H85: 0/100 | I85: ='P9-001'!$N$125 -> 46437 | J85: ='P9-001'!$O$125 -> 46441 | K85: =IF(OR(L85="Y",LEFT('P9-001'!$T$125,1)="D"),"",IF(AND(ISNUMBER(J85),J85<ASOF),"⚠ เลยกำหนด",IF(AND(ISNUMBER(I85),I85<=ASOF+14,J85>=ASOF-7),"ช่วงนี้","")))
A86: P9-001 | B86: แม่แบบ หลังคาลอนคู่, กันย้อน HV, Inverter < 200 kVA | C86: วศ.01 | D86: 01 | E86: 3.2.2 | F86: ชุดเอกสารส่งมอบ (Handover pack) | G86: Handover pack ครบตามโฟลเดอร์ส่งมอบ 1–4 + กปภ. รับเอกสาร | H86: 0/100 | I86: ='P9-001'!$N$126 -> 46440 | J86: ='P9-001'!$O$126 -> 46447 | K86: =IF(OR(L86="Y",LEFT('P9-001'!$T$126,1)="D"),"",IF(AND(ISNUMBER(J86),J86<ASOF),"⚠ เลยกำหนด",IF(AND(ISNUMBER(I86),I86<=ASOF+14,J86>=ASOF-7),"ช่วงนี้","")))
A87: P9-001 | B87: แม่แบบ หลังคาลอนคู่, กันย้อน HV, Inverter < 200 kVA | C87: วศ.01 | D87: 01 | E87: 3.2.3 | F87: PAC (หนังสือรับมอบชั่วคราว) | G87: PAC ลงนาม | H87: 0/100 | I87: ='P9-001'!$N$127 -> 46447 | J87: ='P9-001'!$O$127 -> 46450 | K87: =IF(OR(L87="Y",LEFT('P9-001'!$T$127,1)="D"),"",IF(AND(ISNUMBER(J87),J87<ASOF),"⚠ เลยกำหนด",IF(AND(ISNUMBER(I87),I87<=ASOF+14,J87>=ASOF-7),"ช่วงนี้","")))
A88: P9-002 | B88: แม่แบบ หลังคาลอนคู่, กันย้อน HV, Inverter ≥ 200 kVA | C88: วศ.02 | D88: 02 | E88: 0.1.1 | F88: แผนบริหารโครงการ (PEP) + Baseline | G88: ผู้ว่าจ้างอนุมัติ Baseline ก่อนเริ่มรายงาน S-Curve | H88: 0/100 | I88: ='P9-002'!$N$10 -> 46328 | J88: ='P9-002'!$O$10 -> 46340 | K88: =IF(OR(L88="Y",LEFT('P9-002'!$T$10,1)="D"),"",IF(AND(ISNUMBER(J88),J88<ASOF),"⚠ เลยกำหนด",IF(AND(ISNUMBER(I88),I88<=ASOF+14,J88>=ASOF-7),"ช่วงนี้",""))) -> ช่วงนี้
A89: P9-002 | B89: แม่แบบ หลังคาลอนคู่, กันย้อน HV, Inverter ≥ 200 kVA | C89: วศ.02 | D89: 02 | E89: 0.1.2 | F89: แผนความปลอดภัย (HSE Plan, JSA, Permit-to-Work) | G89: แผน HSE อนุมัติก่อนเข้าพื้นที่ | H89: 0/100 | I89: ='P9-002'!$N$11 -> 46328 | J89: ='P9-002'!$O$11 -> 46340 | K89: =IF(OR(L89="Y",LEFT('P9-002'!$T$11,1)="D"),"",IF(AND(ISNUMBER(J89),J89<ASOF),"⚠ เลยกำหนด",IF(AND(ISNUMBER(I89),I89<=ASOF+14,J89>=ASOF-7),"ช่วงนี้",""))) -> ช่วงนี้
A90: P9-002 | B90: แม่แบบ หลังคาลอนคู่, กันย้อน HV, Inverter ≥ 200 kVA | C90: วศ.02 | D90: 02 | E90: 0.1.3 | F90: แผนคุณภาพ (PQP) + แผนตรวจทดสอบ (ITP) | G90: ITP อนุมัติ ใช้เป็นเกณฑ์ตรวจรับทุกงาน | H90: 0/100 | I90: ='P9-002'!$N$12 -> 46328 | J90: ='P9-002'!$O$12 -> 46340 | K90: =IF(OR(L90="Y",LEFT('P9-002'!$T$12,1)="D"),"",IF(AND(ISNUMBER(J90),J90<ASOF),"⚠ เลยกำหนด",IF(AND(ISNUMBER(I90),I90<=ASOF+14,J90>=ASOF-7),"ช่วงนี้",""))) -> ช่วงนี้
A91: P9-002 | B91: แม่แบบ หลังคาลอนคู่, กันย้อน HV, Inverter ≥ 200 kVA | C91: วศ.02 | D91: 02 | E91: 0.1.4 | F91: เอกสารขออนุมัติวัสดุ (Material submittal) | G91: เอกสารอนุมัติวัสดุครบก่อนส่งของ | H91: 0/100 | I91: ='P9-002'!$N$13 -> 46328 | J91: ='P9-002'!$O$13 -> 46346 | K91: =IF(OR(L91="Y",LEFT('P9-002'!$T$13,1)="D"),"",IF(AND(ISNUMBER(J91),J91<ASOF),"⚠ เลยกำหนด",IF(AND(ISNUMBER(I91),I91<=ASOF+14,J91>=ASOF-7),"ช่วงนี้",""))) -> ช่วงนี้
A92: P9-002 | B92: แม่แบบ หลังคาลอนคู่, กันย้อน HV, Inverter ≥ 200 kVA | C92: วศ.02 | D92: 02 | E92: 0.1.5 | F92: รายงานประจำ R1–R4 | G92: ส่งตรงเวลาทุกงวด, R2 ลงนามรับทราบโดยวิศวกร | H92: 0/100 | I92: ='P9-002'!$N$14 -> 46340 | J92: ='P9-002'!$O$14 -> 46450 | K92: =IF(OR(L92="Y",LEFT('P9-002'!$T$14,1)="D"),"",IF(AND(ISNUMBER(J92),J92<ASOF),"⚠ เลยกำหนด",IF(AND(ISNUMBER(I92),I92<=ASOF+14,J92>=ASOF-7),"ช่วงนี้",""))) -> ช่วงนี้
A93: P9-002 | B93: แม่แบบ หลังคาลอนคู่, กันย้อน HV, Inverter ≥ 200 kVA | C93: วศ.02 | D93: 02 | E93: 0.1.6 | F93: การตรวจ HSE / NCR / Punch list หน้างาน | G93: NCR และ Punch list ปิดครบก่อน PAC | H93: 0/100 | I93: ='P9-002'!$N$15 -> 46340 | J93: ='P9-002'!$O$15 -> 46450 | K93: =IF(OR(L93="Y",LEFT('P9-002'!$T$15,1)="D"),"",IF(AND(ISNUMBER(J93),J93<ASOF),"⚠ เลยกำหนด",IF(AND(ISNUMBER(I93),I93<=ASOF+14,J93>=ASOF-7),"ช่วงนี้",""))) -> ช่วงนี้
A94: P9-002 | B94: แม่แบบ หลังคาลอนคู่, กันย้อน HV, Inverter ≥ 200 kVA | C94: วศ.02 | D94: 02 | E94: 0.2.1 | F94: หนังสือส่งแผง / ใบเบิกจากคลัง | G94: มีเลขที่หนังสือ (TC-PML-…) | H94: 0/100 | I94: ='P9-002'!$N$17 -> 46328 | J94: ='P9-002'!$O$17 -> 46328 | K94: =IF(OR(L94="Y",LEFT('P9-002'!$T$17,1)="D"),"",IF(AND(ISNUMBER(J94),J94<ASOF),"⚠ เลยกำหนด",IF(AND(ISNUMBER(I94),I94<=ASOF+14,J94>=ASOF-7),"ช่วงนี้",""))) -> ช่วงนี้
A95: P9-002 | B95: แม่แบบ หลังคาลอนคู่, กันย้อน HV, Inverter ≥ 200 kVA | C95: วศ.02 | D95: 02 | E95: 0.2.2 | F95: ผล FAT Inverter / ตู้ไฟ (+ CT/VT 22 kV) | G95: ใบรับรอง/ผล FAT แนบในเอกสารสถานี | H95: 0/100 | I95: ='P9-002'!$N$18 -> 46328 | J95: ='P9-002'!$O$18 -> 46328 | K95: =IF(OR(L95="Y",LEFT('P9-002'!$T$18,1)="D"),"",IF(AND(ISNUMBER(J95),J95<ASOF),"⚠ เลยกำหนด",IF(AND(ISNUMBER(I95),I95<=ASOF+14,J95>=ASOF-7),"ช่วงนี้",""))) -> ช่วงนี้
A96: P9-002 | B96: แม่แบบ หลังคาลอนคู่, กันย้อน HV, Inverter ≥ 200 kVA | C96: วศ.02 | D96: 02 | E96: 0.2.3 | F96: แผง + Inverter ถึงหน้างาน (ตรวจรับ + S/N) | G96: จำนวนตรง BOM, ไม่มีชำรุด, S/N เข้าแอป | H96: 0/100 | I96: ='P9-002'!$N$19 -> 46328 | J96: ='P9-002'!$O$19 -> 46328 | K96: =IF(OR(L96="Y",LEFT('P9-002'!$T$19,1)="D"),"",IF(AND(ISNUMBER(J96),J96<ASOF),"⚠ เลยกำหนด",IF(AND(ISNUMBER(I96),I96<=ASOF+14,J96>=ASOF-7),"ช่วงนี้",""))) -> ช่วงนี้
A97: P9-002 | B97: แม่แบบ หลังคาลอนคู่, กันย้อน HV, Inverter ≥ 200 kVA | C97: วศ.02 | D97: 02 | E97: 0.2.4 | F97: โครงยึด + Walkway ถึงหน้างาน | G97: ตรวจรับตาม shop drawing | H97: 0/100 | I97: ='P9-002'!$N$20 -> 46328 | J97: ='P9-002'!$O$20 -> 46328 | K97: =IF(OR(L97="Y",LEFT('P9-002'!$T$20,1)="D"),"",IF(AND(ISNUMBER(J97),J97<ASOF),"⚠ เลยกำหนด",IF(AND(ISNUMBER(I97),I97<=ASOF+14,J97>=ASOF-7),"ช่วงนี้",""))) -> ช่วงนี้
A98: P9-002 | B98: แม่แบบ หลังคาลอนคู่, กันย้อน HV, Inverter ≥ 200 kVA | C98: วศ.02 | D98: 02 | E98: 0.2.5 | F98: สายไฟ + รางสาย ถึงหน้างาน | G98: ตรวจรับขนาด/ยี่ห้อตาม submittal | H98: 0/100 | I98: ='P9-002'!$N$21 -> 46328 | J98: ='P9-002'!$O$21 -> 46328 | K98: =IF(OR(L98="Y",LEFT('P9-002'!$T$21,1)="D"),"",IF(AND(ISNUMBER(J98),J98<ASOF),"⚠ เลยกำหนด",IF(AND(ISNUMBER(I98),I98<=ASOF+14,J98>=ASOF-7),"ช่วงนี้",""))) -> ช่วงนี้
A99: P9-002 | B99: แม่แบบ หลังคาลอนคู่, กันย้อน HV, Inverter ≥ 200 kVA | C99: วศ.02 | D99: 02 | E99: 0.2.6 | F99: ตู้ไฟ FTS / DC / AC / METER / PQM / SEM ถึงหน้างาน | G99: ตรวจรับภายในตู้ตามแบบ SLD | H99: 0/100 | I99: ='P9-002'!$N$22 -> 46328 | J99: ='P9-002'!$O$22 -> 46328 | K99: =IF(OR(L99="Y",LEFT('P9-002'!$T$22,1)="D"),"",IF(AND(ISNUMBER(J99),J99<ASOF),"⚠ เลยกำหนด",IF(AND(ISNUMBER(I99),I99<=ASOF+14,J99>=ASOF-7),"ช่วงนี้",""))) -> ช่วงนี้
A100: P9-002 | B100: แม่แบบ หลังคาลอนคู่, กันย้อน HV, Inverter ≥ 200 kVA | C100: วศ.02 | D100: 02 | E100: 0.2.7 | F100: อุปกรณ์ 22 kV ถึงหน้างาน (VT / CT ผ่านทดสอบ กฟภ.) | G100: มีผลทดสอบ CT/VT | H100: 0/100 | I100: ='P9-002'!$N$23 -> 46328 | J100: ='P9-002'!$O$23 -> 46328 | K100: =IF(OR(L100="Y",LEFT('P9-002'!$T$23,1)="D"),"",IF(AND(ISNUMBER(J100),J100<ASOF),"⚠ เลยกำหนด",IF(AND(ISNUMBER(I100),I100<=ASOF+14,J100>=ASOF-7),"ช่วงนี้",""))) -> ช่วงนี้
...

Sheet Master Plan
A1: MASTER PLAN – โครงการ Solar Rooftop การประปาส่วนภูมิภาค เฟส 3–4
A2: 20 สถานี, สัญญา PEA(EMD)-03/2024 | D2: ✎ อัปเดตรายสัปดาห์ | J2: ⚙ สมมติฐาน | M2: ⚠ ความเสี่ยง | P2: ↻ บันทึกการเปลี่ยนแปลง | T2: ✗ Cost of Quality | W2: ◆ Milestone | Z2: ⟳ TCRoof (สด)
A3: วันที่ข้อมูล | C3: COD ทั้งเฟส (คาดการณ์) | D3: COD แล้ว | F3: ติดตั้งแล้ว | I3: กฟภ. ตรวจแล้ว | K3: ส่งมอบงวดแล้ว | N3: Milestone เสร็จ | P3: % งาน (ถ่วง kWp) | R3: สถานี COD ช้ากว่า Baseline | T3: ช้าแต่ยังไม่บันทึกเหตุผล
A4: =ASOF -> 46328 | C4: =MAX($AH$8:$AH$27) -> 46433 | D4: =COUNTIFS($X$8:$X$27,"<="&ASOF,$X$8:$X$27,"<>")&" / 20" -> 0 / 20 | F4: =COUNTIFS($N$8:$N$27,"<="&ASOF,$N$8:$N$27,"<>")&" / 20" -> 0 / 20 | I4: =COUNTIFS($O$8:$O$27,"<="&ASOF,$O$8:$O$27,"<>")&" / 20" -> 0 / 20 | K4: =COUNTIFS($Q$8:$Q$27,"<="&ASOF,$Q$8:$Q$27,"<>")&" / 20" -> 0 / 20 | N4: =TEXT(SUM($AK$8:$AK$27)/SUM($AL$8:$AL$27),"0%")&" ("&SUM($AK$8:$AK$27)&"/"&SUM($AL$8:$AL$27)&")" -> 0% (0/150) | P4: =SUMPRODUCT($AM$8:$AM$27,$F$8:$F$27)/SUM($F$8:$F$27) -> 0 | R4: =COUNTIF($AJ$8:$AJ$27,">0") -> 0 | T4: =COUNTIF($AP$8:$AP$27,">0") -> 0
A5: คลิกรหัสสถานีเพื่อเปิดแผนรายโครงการ, เขียว = ลิงก์จากชีต ‘อัปเดตรายสัปดาห์’, ฟ้า = แผนที่สูตรคำนวณ (เลื่อนเป็นวันทำงาน), Gantt: I ติดตั้ง, P กฟภ.ตรวจ, T IEC, H ส่งมอบ, G ยื่นขนานไฟ, S First Sync, ส้ม = สัปดาห์กำหนดรอบ, % งานสูงเพราะงานติดตั้งหนัก 90% ให้ดู Milestone คู่กัน
A6: สถานี | J6: ผู้รับผิดชอบ | N6: วันที่จริง / นัด (ลิงก์จาก ‘อัปเดตรายสัปดาห์’) | Y6: แผน (คำนวณ) | AI6: ผล | AT6: ตัวช่วย | BH6: =CHOOSE(MONTH(BH7),"ม.ค.","ก.พ.","มี.ค.","เม.ย.","พ.ค.","มิ.ย.","ก.ค.","ส.ค.","ก.ย.","ต.ค.","พ.ย.","ธ.ค.")&" "&RIGHT(YEAR(BH7)+543,2) -> ต.ค. 69 | BI6: =IF(MONTH(BI7)<>MONTH(BH7),CHOOSE(MONTH(BI7),"ม.ค.","ก.พ.","มี.ค.","เม.ย.","พ.ค.","มิ.ย.","ก.ค.","ส.ค.","ก.ย.","ต.ค.","พ.ย.","ธ.ค.")&" "&RIGHT(YEAR(BI7)+543,2),"") -> พ.ย. 69 | BJ6: =IF(MONTH(BJ7)<>MONTH(BI7),CHOOSE(MONTH(BJ7),"ม.ค.","ก.พ.","มี.ค.","เม.ย.","พ.ค.","มิ.ย.","ก.ค.","ส.ค.","ก.ย.","ต.ค.","พ.ย.","ธ.ค.")&" "&RIGHT(YEAR(BJ7)+543,2),"") | BK6: =IF(MONTH(BK7)<>MONTH(BJ7),CHOOSE(MONTH(BK7),"ม.ค.","ก.พ.","มี.ค.","เม.ย.","พ.ค.","มิ.ย.","ก.ค.","ส.ค.","ก.ย.","ต.ค.","พ.ย.","ธ.ค.")&" "&RIGHT(YEAR(BK7)+543,2),"") | BL6: =IF(MONTH(BL7)<>MONTH(BK7),CHOOSE(MONTH(BL7),"ม.ค.","ก.พ.","มี.ค.","เม.ย.","พ.ค.","มิ.ย.","ก.ค.","ส.ค.","ก.ย.","ต.ค.","พ.ย.","ธ.ค.")&" "&RIGHT(YEAR(BL7)+543,2),"") | BM6: =IF(MONTH(BM7)<>MONTH(BL7),CHOOSE(MONTH(BM7),"ม.ค.","ก.พ.","มี.ค.","เม.ย.","พ.ค.","มิ.ย.","ก.ค.","ส.ค.","ก.ย.","ต.ค.","พ.ย.","ธ.ค.")&" "&RIGHT(YEAR(BM7)+543,2),"") | BN6: =IF(MONTH(BN7)<>MONTH(BM7),CHOOSE(MONTH(BN7),"ม.ค.","ก.พ.","มี.ค.","เม.ย.","พ.ค.","มิ.ย.","ก.ค.","ส.ค.","ก.ย.","ต.ค.","พ.ย.","ธ.ค.")&" "&RIGHT(YEAR(BN7)+543,2),"") -> ธ.ค. 69 | BO6: =IF(MONTH(BO7)<>MONTH(BN7),CHOOSE(MONTH(BO7),"ม.ค.","ก.พ.","มี.ค.","เม.ย.","พ.ค.","มิ.ย.","ก.ค.","ส.ค.","ก.ย.","ต.ค.","พ.ย.","ธ.ค.")&" "&RIGHT(YEAR(BO7)+543,2),"") | BP6: =IF(MONTH(BP7)<>MONTH(BO7),CHOOSE(MONTH(BP7),"ม.ค.","ก.พ.","มี.ค.","เม.ย.","พ.ค.","มิ.ย.","ก.ค.","ส.ค.","ก.ย.","ต.ค.","พ.ย.","ธ.ค.")&" "&RIGHT(YEAR(BP7)+543,2),"") | ... DC6: =IF(MONTH(DC7)<>MONTH(DB7),CHOOSE(MONTH(DC7),"ม.ค.","ก.พ.","มี.ค.","เม.ย.","พ.ค.","มิ.ย.","ก.ค.","ส.ค.","ก.ย.","ต.ค.","พ.ย.","ธ.ค.")&" "&RIGHT(YEAR(DC7)+543,2),"")
A7: รหัส | B7: สถานี | C7: สาขา | D7: ภาค | E7: เขต กฟภ. | F7: kWp | G7: รอบ | H7: กำหนดรอบ | I7: COD Baseline | J7: วิศวกร | K7: Admin | L7: ผรม. | M7: พค.2 | N7: ติดตั้ง | O7: กฟภ.ตรวจ | P7: IEC 62446 | Q7: ส่งมอบงวด | R7: ยื่นขนานไฟ | S7: ยื่นแก้ไขล่าสุด | T7: กฟภ.อนุมัติ | U7: ชำระค่าธรรมเนียม | V7: ขอตรวจระบบ | W7: ยื่น พค.2 | X7: First Sync | Y7: ติดตั้ง | Z7: กฟภ.ตรวจ | AA7: IEC 62446 | AB7: ส่งมอบงวด | AC7: ยื่นขนานไฟ | AD7: กฟภ.อนุมัติ | AE7: ชำระค่าธรรมเนียม | AF7: ขอตรวจระบบ | AG7: ยื่น พค.2 | AH7: COD / First Sync | AI7: ส่งมอบงวดช้า (วัน) | AJ7: COD ช้ากว่า Baseline (วัน) | AK7: Milestone เสร็จ | AL7: จาก | AM7: % งาน | AN7: ⚠ ตรวจข้อมูล | AO7: เลื่อนที่อนุมัติ (วัน) | AP7: COD ช้าที่ยังไม่มีเหตุผล (วัน) | AQ7: งานแก้ซ้ำ (ครั้ง) | AR7: % MP ในแอป TCRoof | AS7: แก้ล่าสุดในแอป | AT7: คิวติดตั้ง (kWp สะสม) | AU7: ผรม. kWp/สัปดาห์ | AV7: วันตรวจเร็วสุด | AW7: คิว กฟภ. | AX7: กำลังตรวจเขต | AY7: คิววิศวกร | AZ7: วิศวกร ไซต์/สัปดาห์ | BA7: วัน IEC เร็วสุด | BB7: คิว IEC ผรม. | BC7: ผรม. IEC/สัปดาห์ | BD7: วันทำรายงาน | BE7: รอคิวเขต (วัน) | BF7: รอคิววิศวกร (วัน) | BH7: =GANTT_START -> 46321 | BI7: =BH7+7 -> 46328 | BJ7: =BI7+7 -> 46335 | BK7: =BJ7+7 -> 46342 | BL7: =BK7+7 -> 46349 | BM7: =BL7+7 -> 46356 | BN7: =BM7+7 -> 46363 | BO7: =BN7+7 -> 46370 | BP7: =BO7+7 -> 46377 | ... DC7: =DB7+7 -> 46650
A8: P9-001 | B8: แม่แบบ หลังคาลอนคู่, กันย้อน HV, Inverter < 200 kVA | C8: (ตัวอย่าง) | D8: ตัวอย่าง | E8: ตย.01 | F8: 150.48 | G8: รอบ 9 | H8: =PROJ_START+RD_SPAN -> 46403 | I8: =H8+33 -> 46436 | J8: วศ.01 | K8: Admin | L8: 01 | M8: N | N8: =IF(ISNUMBER(อัปเดตรายสัปดาห์!$AF8),อัปเดตรายสัปดาห์!$AF8,"") | O8: =IF(ISNUMBER(อัปเดตรายสัปดาห์!$AH8),อัปเดตรายสัปดาห์!$AH8,"") | P8: =IF(ISNUMBER(อัปเดตรายสัปดาห์!$AG8),อัปเดตรายสัปดาห์!$AG8,IF(AND(ISNUMBER(TCRoof!$AC$8),N(TCRoof!$AC$8)<=ASOF),TCRoof!$AC$8,"")) | Q8: =IF(ISNUMBER(อัปเดตรายสัปดาห์!$AL8),อัปเดตรายสัปดาห์!$AL8,"") | R8: =IF(ISNUMBER(อัปเดตรายสัปดาห์!$Q8),อัปเดตรายสัปดาห์!$Q8,"") | S8: =IF(ISNUMBER(อัปเดตรายสัปดาห์!$R8),อัปเดตรายสัปดาห์!$R8,"") | T8: =IF(ISNUMBER(อัปเดตรายสัปดาห์!$S8),อัปเดตรายสัปดาห์!$S8,IF(อัปเดตรายสัปดาห์!$S8="Y",ASOF,"")) | U8: =IF(ISNUMBER(อัปเดตรายสัปดาห์!$T8),อัปเดตรายสัปดาห์!$T8,IF(อัปเดตรายสัปดาห์!$T8="Y",ASOF,"")) | V8: =IF(ISNUMBER(อัปเดตรายสัปดาห์!$U8),อัปเดตรายสัปดาห์!$U8,IF(อัปเดตรายสัปดาห์!$U8="Y",ASOF,"")) | W8: =IF(ISNUMBER(อัปเดตรายสัปดาห์!$N8),อัปเดตรายสัปดาห์!$N8,"") | X8: =IF(ISNUMBER(อัปเดตรายสัปดาห์!$V8),อัปเดตรายสัปดาห์!$V8,IF(AND(ISNUMBER(TCRoof!$AD$8),N(TCRoof!$AD$8)<=ASOF),TCRoof!$AD$8,"")) | Y8: =IF(N8<>"",N8,WORKDAY((ASOF+LEAD_INST+7*INT((AT8-0.01)/MAX(1,AU8)))-1,1,HOLIDAYS)) -> 46349 | Z8: =IF(O8<>"",O8,WORKDAY((MAX(AV8+7*INT((AW8-1)/MAX(1,AX8)),AV8+7*INT((AY8-1)/MAX(1,AZ8))))-1,1,HOLIDAYS)) -> 46356 | AA8: =IF(P8<>"",P8,WORKDAY((BA8+7*INT((BB8-1)/MAX(1,BC8)))-1,1,HOLIDAYS)) -> 46359 | AB8: =IF(Q8<>"",Q8,WORKDAY((MAX(AA8+BD8,ASOF+1))-1,1,HOLIDAYS)) -> 46367 | AC8: =IF(R8<>"",R8,WORKDAY((MAX(Y8,ASOF)+LAG_GRID)-1,1,HOLIDAYS)) -> 46356 | AD8: =IF(T8<>"",T8,WORKDAY((MAX(WORKDAY(MAX(AC8,N(S8)),REVIEW_WD,HOLIDAYS),ASOF+1))-1,1,HOLIDAYS)) -> 46379 | AE8: =IF(U8<>"",U8,WORKDAY((MAX(AD8,ASOF)+FEE_DAYS)-1,1,HOLIDAYS)) -> 46386 | AF8: =IF(V8<>"",V8,WORKDAY((MAX(AA8,Z8,AE8,IF(AG8="",0,AG8+REVIEW_PK2),ASOF)+LAG_INSREQ)-1,1,HOLIDAYS)) -> 46391 | AG8: =IF(M8<>"Y","",IF(W8<>"",W8,WORKDAY((MAX(Y8,ASOF)+LAG_GRID)-1,1,HOLIDAYS))) | AH8: =IF(X8<>"",X8,WORKDAY(AF8,INSPECT_WD,HOLIDAYS)) -> 46433 | AI8: =IF(H8="","",AB8-H8) -> -36 | AJ8: =IF(I8="","",AH8-I8) -> -3 | AK8: =IF(AND(ISNUMBER(N8),N(N8)<=ASOF),1,0)+IF(AND(ISNUMBER(O8),N(O8)<=ASOF),1,0)+IF(AND(ISNUMBER(P8),N(P8)<=ASOF),1,0)+IF(AND(ISNUMBER(Q8),N(Q8)<=ASOF),1,0)+IF(AND(ISNUMBER(R8),N(R8)<=ASOF),1,0)+IF(AND(ISNUMBER(U8),N(U8)<=ASOF),1,0)+IF(AND(ISNUMBER(X8),N(X8)<=ASOF),1,0) -> 0 | AL8: 7 | AM8: ='P9-001'!$J$4 -> 0 | AN8: =TRIM(IF(AND(ISNUMBER(O8),NOT(ISNUMBER(N8))),"กฟภ.ตรวจก่อนติดตั้ง, ","")&IF(AND(ISNUMBER(P8),NOT(ISNUMBER(N8))),"IEC ก่อนติดตั้ง, ","")&IF(AND(ISNUMBER(Q8),NOT(ISNUMBER(N8))),"ส่งมอบก่อนติดตั้ง, ","")&IF(AND(ISNUMBER(Q8),ISNUMBER(P8),N(Q8)<N(P8)),"ส่งมอบก่อน IEC, ","")&IF(AND(ISNUMBER(อัปเดตรายสัปดาห์!$AG8),ISNUMBER(TCRoof!$AC$8),ABS(N(อัปเดตรายสัปดาห์!$AG8)-N(TCRoof!$AC$8))>3),"IEC Excel≠แอป, ","")&IF(AND(ISNUMBER(อัปเดตรายสัปดาห์!$V8),ISNUMBER(TCRoof!$AD$8),ABS(N(อัปเดตรายสัปดาห์!$V8)-N(TCRoof!$AD$8))>3),"COD Excel≠แอป, ","")&IF(AND(ISNUMBER(อัปเดตรายสัปดาห์!$AF8),ISNUMBER(TCRoof!$AB$8),ABS(N(อัปเดตรายสัปดาห์!$AF8)-N(TCRoof!$AB$8))>3),"ติดตั้ง Excel≠แอป, ","")&IF(AND(ISNUMBER(N8),N(N8)>ASOF,OR(WEEKDAY(N(N8),2)>5,COUNTIF(HOLIDAYS,N(N8))>0)),"นัดดับไฟตรงวันหยุด, ","")&IF(AND(ISNUMBER(O8),N(O8)>ASOF,OR(WEEKDAY(N(O8),2)>5,COUNTIF(HOLIDAYS,N(O8))>0)),"นัด กฟภ.ตรงวันหยุด, ","")&IF(AND(ISNUMBER(P8),N(P8)>ASOF,OR(WEEKDAY(N(P8),2)>5,COUNTIF(HOLIDAYS,N(P8))>0)),"นัด IECตรงวันหยุด, ","")&IF(AND(ISNUMBER(X8),N(X8)>ASOF,OR(WEEKDAY(N(X8),2)>5,COUNTIF(HOLIDAYS,N(X8))>0)),"นัด Syncตรงวันหยุด, ","")) | AO8: =SUMIFS(CR_COD,CR_ST,A8,CR_STAT,"อนุมัติ")+SUMIFS(CR_COD,CR_ST,"ทั้งเฟส",CR_STAT,"อนุมัติ")+SUMIFS(CR_COD,CR_ST,"ผรม. "&L8,CR_STAT,"อนุมัติ")+SUMIFS(CR_COD,CR_ST,"เขต "&E8,CR_STAT,"อนุมัติ") -> 0 | AP8: =IF(NOT(ISNUMBER(AJ8)),"",MAX(0,AJ8-AO8)) -> 0 | AQ8: =COUNTIF(RW_ST,A8) -> 0 | AR8: =IF(ISNUMBER(TCRoof!$I$8),TCRoof!$I$8,"") | AS8: =IF(ISNUMBER(TCRoof!$H$8),TCRoof!$H$8,"") | AT8: =IF(N8<>"","",SUMIFS($F$8:$F$27,$L$8:$L$27,L8,$N$8:$N$27,"",$H$8:$H$27,"<"&H8)+SUMIFS($F$8:$F$27,$L$8:$L$27,L8,$N$8:$N$27,"",$H$8:$H$27,H8,$A$8:$A$27,"<="&A8)+SUMIFS($F$8:$F$27,$L$8:$L$27,L8,$N$8:$N$27,">"&ASOF)) -> 150.48 | AU8: =IFERROR(VLOOKUP(L8,TEAM_TBL,2,0)*VLOOKUP(L8,TEAM_TBL,3,0),150) -> 150 | AV8: =IF(O8<>"","",MAX(Y8+LAG_PEA,ASOF+LAG_PEA)) -> 46356 | AW8: =IF(O8<>"","",COUNTIFS($E$8:$E$27,E8,$AV$8:$AV$27,"<"&AV8)+COUNTIFS($E$8:$E$27,E8,$AV$8:$AV$27,AV8,$A$8:$A$27,"<"&A8)+COUNTIFS($E$8:$E$27,E8,$O$8:$O$27,">"&ASOF)+1) -> 1 | AX8: =IFERROR(VLOOKUP(E8,ZONE_TBL,2,0),CAP_PEA) -> 3 | AY8: =IF(O8<>"","",COUNTIFS($J$8:$J$27,J8,$AV$8:$AV$27,"<"&AV8)+COUNTIFS($J$8:$J$27,J8,$AV$8:$AV$27,AV8,$A$8:$A$27,"<"&A8)+COUNTIFS($J$8:$J$27,J8,$O$8:$O$27,">"&ASOF)+1) -> 1 | AZ8: =IFERROR(VLOOKUP(J8,ENG_TBL,2,0),ENG_CAP) -> 3 | BA8: =IF(P8<>"","",MAX(Z8+LAG_IEC,ASOF+1)) -> 46359 | BB8: =IF(P8<>"","",COUNTIFS($L$8:$L$27,L8,$BA$8:$BA$27,"<"&BA8)+COUNTIFS($L$8:$L$27,L8,$BA$8:$BA$27,BA8,$A$8:$A$27,"<"&A8)+COUNTIFS($L$8:$L$27,L8,$P$8:$P$27,">"&ASOF)+1) -> 1 | BC8: =IFERROR(VLOOKUP(L8,TEAM_TBL,4,0)*VLOOKUP(L8,TEAM_TBL,5,0),3) -> 3 | BD8: =IFERROR(VLOOKUP(L8,TEAM_TBL,6,0),LAG_HO) -> 7 | BE8: =IF(ISNUMBER(AW8),7*INT((AW8-1)/MAX(1,AX8)),"") -> 0 | BF8: =IF(ISNUMBER(AY8),7*INT((AY8-1)/MAX(1,AZ8)),"") -> 0 | BH8: =IF(AND($Y8<>"",$Y8>=BH$7,$Y8<BH$7+7),"I","")&IF(AND($Z8<>"",$Z8>=BH$7,$Z8<BH$7+7),"P","")&IF(AND($AA8<>"",$AA8>=BH$7,$AA8<BH$7+7),"T","")&IF(AND($AB8<>"",$AB8>=BH$7,$AB8<BH$7+7),"H","")&IF(AND($AC8<>"",$AC8>=BH$7,$AC8<BH$7+7),"G","")&IF(AND($AH8<>"",$AH8>=BH$7,$AH8<BH$7+7),"S","") | BI8: =IF(AND($Y8<>"",$Y8>=BI$7,$Y8<BI$7+7),"I","")&IF(AND($Z8<>"",$Z8>=BI$7,$Z8<BI$7+7),"P","")&IF(AND($AA8<>"",$AA8>=BI$7,$AA8<BI$7+7),"T","")&IF(AND($AB8<>"",$AB8>=BI$7,$AB8<BI$7+7),"H","")&IF(AND($AC8<>"",$AC8>=BI$7,$AC8<BI$7+7),"G","")&IF(AND($AH8<>"",$AH8>=BI$7,$AH8<BI$7+7),"S","") | BJ8: =IF(AND($Y8<>"",$Y8>=BJ$7,$Y8<BJ$7+7),"I","")&IF(AND($Z8<>"",$Z8>=BJ$7,$Z8<BJ$7+7),"P","")&IF(AND($AA8<>"",$AA8>=BJ$7,$AA8<BJ$7+7),"T","")&IF(AND($AB8<>"",$AB8>=BJ$7,$AB8<BJ$7+7),"H","")&IF(AND($AC8<>"",$AC8>=BJ$7,$AC8<BJ$7+7),"G","")&IF(AND($AH8<>"",$AH8>=BJ$7,$AH8<BJ$7+7),"S","") | BK8: =IF(AND($Y8<>"",$Y8>=BK$7,$Y8<BK$7+7),"I","")&IF(AND($Z8<>"",$Z8>=BK$7,$Z8<BK$7+7),"P","")&IF(AND($AA8<>"",$AA8>=BK$7,$AA8<BK$7+7),"T","")&IF(AND($AB8<>"",$AB8>=BK$7,$AB8<BK$7+7),"H","")&IF(AND($AC8<>"",$AC8>=BK$7,$AC8<BK$7+7),"G","")&IF(AND($AH8<>"",$AH8>=BK$7,$AH8<BK$7+7),"S","") | BL8: =IF(AND($Y8<>"",$Y8>=BL$7,$Y8<BL$7+7),"I","")&IF(AND($Z8<>"",$Z8>=BL$7,$Z8<BL$7+7),"P","")&IF(AND($AA8<>"",$AA8>=BL$7,$AA8<BL$7+7),"T","")&IF(AND($AB8<>"",$AB8>=BL$7,$AB8<BL$7+7),"H","")&IF(AND($AC8<>"",$AC8>=BL$7,$AC8<BL$7+7),"G","")&IF(AND($AH8<>"",$AH8>=BL$7,$AH8<BL$7+7),"S","") -> I | BM8: =IF(AND($Y8<>"",$Y8>=BM$7,$Y8<BM$7+7),"I","")&IF(AND($Z8<>"",$Z8>=BM$7,$Z8<BM$7+7),"P","")&IF(AND($AA8<>"",$AA8>=BM$7,$AA8<BM$7+7),"T","")&IF(AND($AB8<>"",$AB8>=BM$7,$AB8<BM$7+7),"H","")&IF(AND($AC8<>"",$AC8>=BM$7,$AC8<BM$7+7),"G","")&IF(AND($AH8<>"",$AH8>=BM$7,$AH8<BM$7+7),"S","") -> PTG | BN8: =IF(AND($Y8<>"",$Y8>=BN$7,$Y8<BN$7+7),"I","")&IF(AND($Z8<>"",$Z8>=BN$7,$Z8<BN$7+7),"P","")&IF(AND($AA8<>"",$AA8>=BN$7,$AA8<BN$7+7),"T","")&IF(AND($AB8<>"",$AB8>=BN$7,$AB8<BN$7+7),"H","")&IF(AND($AC8<>"",$AC8>=BN$7,$AC8<BN$7+7),"G","")&IF(AND($AH8<>"",$AH8>=BN$7,$AH8<BN$7+7),"S","") -> H | BO8: =IF(AND($Y8<>"",$Y8>=BO$7,$Y8<BO$7+7),"I","")&IF(AND($Z8<>"",$Z8>=BO$7,$Z8<BO$7+7),"P","")&IF(AND($AA8<>"",$AA8>=BO$7,$AA8<BO$7+7),"T","")&IF(AND($AB8<>"",$AB8>=BO$7,$AB8<BO$7+7),"H","")&IF(AND($AC8<>"",$AC8>=BO$7,$AC8<BO$7+7),"G","")&IF(AND($AH8<>"",$AH8>=BO$7,$AH8<BO$7+7),"S","") | ... DC8: =IF(AND($Y8<>"",$Y8>=DC$7,$Y8<DC$7+7),"I","")&IF(AND($Z8<>"",$Z8>=DC$7,$Z8<DC$7+7),"P","")&IF(AND($AA8<>"",$AA8>=DC$7,$AA8<DC$7+7),"T","")&IF(AND($AB8<>"",$AB8>=DC$7,$AB8<DC$7+7),"H","")&IF(AND($AC8<>"",$AC8>=DC$7,$AC8<DC$7+7),"G","")&IF(AND($AH8<>"",$AH8>=DC$7,$AH8<DC$7+7),"S","")
A9: P9-002 | B9: แม่แบบ หลังคาลอนคู่, กันย้อน HV, Inverter ≥ 200 kVA | C9: (ตัวอย่าง) | D9: ตัวอย่าง | E9: ตย.02 | F9: 280.44 | G9: รอบ 9 | H9: =PROJ_START+RD_SPAN -> 46403 | I9: =H9+33 -> 46436 | J9: วศ.02 | K9: Admin | L9: 02 | M9: Y | N9: =IF(ISNUMBER(อัปเดตรายสัปดาห์!$AF9),อัปเดตรายสัปดาห์!$AF9,"") | O9: =IF(ISNUMBER(อัปเดตรายสัปดาห์!$AH9),อัปเดตรายสัปดาห์!$AH9,"") | P9: =IF(ISNUMBER(อัปเดตรายสัปดาห์!$AG9),อัปเดตรายสัปดาห์!$AG9,IF(AND(ISNUMBER(TCRoof!$AC$9),N(TCRoof!$AC$9)<=ASOF),TCRoof!$AC$9,"")) | Q9: =IF(ISNUMBER(อัปเดตรายสัปดาห์!$AL9),อัปเดตรายสัปดาห์!$AL9,"") | R9: =IF(ISNUMBER(อัปเดตรายสัปดาห์!$Q9),อัปเดตรายสัปดาห์!$Q9,"") | S9: =IF(ISNUMBER(อัปเดตรายสัปดาห์!$R9),อัปเดตรายสัปดาห์!$R9,"") | T9: =IF(ISNUMBER(อัปเดตรายสัปดาห์!$S9),อัปเดตรายสัปดาห์!$S9,IF(อัปเดตรายสัปดาห์!$S9="Y",ASOF,"")) | U9: =IF(ISNUMBER(อัปเดตรายสัปดาห์!$T9),อัปเดตรายสัปดาห์!$T9,IF(อัปเดตรายสัปดาห์!$T9="Y",ASOF,"")) | V9: =IF(ISNUMBER(อัปเดตรายสัปดาห์!$U9),อัปเดตรายสัปดาห์!$U9,IF(อัปเดตรายสัปดาห์!$U9="Y",ASOF,"")) | W9: =IF(ISNUMBER(อัปเดตรายสัปดาห์!$N9),อัปเดตรายสัปดาห์!$N9,"") | X9: =IF(ISNUMBER(อัปเดตรายสัปดาห์!$V9),อัปเดตรายสัปดาห์!$V9,IF(AND(ISNUMBER(TCRoof!$AD$9),N(TCRoof!$AD$9)<=ASOF),TCRoof!$AD$9,"")) | Y9: =IF(N9<>"",N9,WORKDAY((ASOF+LEAD_INST+7*INT((AT9-0.01)/MAX(1,AU9)))-1,1,HOLIDAYS)) -> 46349 | Z9: =IF(O9<>"",O9,WORKDAY((MAX(AV9+7*INT((AW9-1)/MAX(1,AX9)),AV9+7*INT((AY9-1)/MAX(1,AZ9))))-1,1,HOLIDAYS)) -> 46356 | AA9: =IF(P9<>"",P9,WORKDAY((BA9+7*INT((BB9-1)/MAX(1,BC9)))-1,1,HOLIDAYS)) -> 46359 | AB9: =IF(Q9<>"",Q9,WORKDAY((MAX(AA9+BD9,ASOF+1))-1,1,HOLIDAYS)) -> 46367 | AC9: =IF(R9<>"",R9,WORKDAY((MAX(Y9,ASOF)+LAG_GRID)-1,1,HOLIDAYS)) -> 46356 | AD9: =IF(T9<>"",T9,WORKDAY((MAX(WORKDAY(MAX(AC9,N(S9)),REVIEW_WD,HOLIDAYS),ASOF+1))-1,1,HOLIDAYS)) -> 46379 | AE9: =IF(U9<>"",U9,WORKDAY((MAX(AD9,ASOF)+FEE_DAYS)-1,1,HOLIDAYS)) -> 46386 | AF9: =IF(V9<>"",V9,WORKDAY((MAX(AA9,Z9,AE9,IF(AG9="",0,AG9+REVIEW_PK2),ASOF)+LAG_INSREQ)-1,1,HOLIDAYS)) -> 46391 | AG9: =IF(M9<>"Y","",IF(W9<>"",W9,WORKDAY((MAX(Y9,ASOF)+LAG_GRID)-1,1,HOLIDAYS))) -> 46356 | AH9: =IF(X9<>"",X9,WORKDAY(AF9,INSPECT_WD,HOLIDAYS)) -> 46433 | AI9: =IF(H9="","",AB9-H9) -> -36 | AJ9: =IF(I9="","",AH9-I9) -> -3 | AK9: =IF(AND(ISNUMBER(N9),N(N9)<=ASOF),1,0)+IF(AND(ISNUMBER(O9),N(O9)<=ASOF),1,0)+IF(AND(ISNUMBER(P9),N(P9)<=ASOF),1,0)+IF(AND(ISNUMBER(Q9),N(Q9)<=ASOF),1,0)+IF(AND(ISNUMBER(R9),N(R9)<=ASOF),1,0)+IF(AND(ISNUMBER(U9),N(U9)<=ASOF),1,0)+IF(AND(ISNUMBER(X9),N(X9)<=ASOF),1,0)+IF(AND(ISNUMBER(W9),N(W9)<=ASOF),1,0) -> 0 | AL9: 8 | AM9: ='P9-002'!$J$4 -> 0 | AN9: =TRIM(IF(AND(ISNUMBER(O9),NOT(ISNUMBER(N9))),"กฟภ.ตรวจก่อนติดตั้ง, ","")&IF(AND(ISNUMBER(P9),NOT(ISNUMBER(N9))),"IEC ก่อนติดตั้ง, ","")&IF(AND(ISNUMBER(Q9),NOT(ISNUMBER(N9))),"ส่งมอบก่อนติดตั้ง, ","")&IF(AND(ISNUMBER(Q9),ISNUMBER(P9),N(Q9)<N(P9)),"ส่งมอบก่อน IEC, ","")&IF(AND(ISNUMBER(อัปเดตรายสัปดาห์!$AG9),ISNUMBER(TCRoof!$AC$9),ABS(N(อัปเดตรายสัปดาห์!$AG9)-N(TCRoof!$AC$9))>3),"IEC Excel≠แอป, ","")&IF(AND(ISNUMBER(อัปเดตรายสัปดาห์!$V9),ISNUMBER(TCRoof!$AD$9),ABS(N(อัปเดตรายสัปดาห์!$V9)-N(TCRoof!$AD$9))>3),"COD Excel≠แอป, ","")&IF(AND(ISNUMBER(อัปเดตรายสัปดาห์!$AF9),ISNUMBER(TCRoof!$AB$9),ABS(N(อัปเดตรายสัปดาห์!$AF9)-N(TCRoof!$AB$9))>3),"ติดตั้ง Excel≠แอป, ","")&IF(AND(ISNUMBER(N9),N(N9)>ASOF,OR(WEEKDAY(N(N9),2)>5,COUNTIF(HOLIDAYS,N(N9))>0)),"นัดดับไฟตรงวันหยุด, ","")&IF(AND(ISNUMBER(O9),N(O9)>ASOF,OR(WEEKDAY(N(O9),2)>5,COUNTIF(HOLIDAYS,N(O9))>0)),"นัด กฟภ.ตรงวันหยุด, ","")&IF(AND(ISNUMBER(P9),N(P9)>ASOF,OR(WEEKDAY(N(P9),2)>5,COUNTIF(HOLIDAYS,N(P9))>0)),"นัด IECตรงวันหยุด, ","")&IF(AND(ISNUMBER(X9),N(X9)>ASOF,OR(WEEKDAY(N(X9),2)>5,COUNTIF(HOLIDAYS,N(X9))>0)),"นัด Syncตรงวันหยุด, ","")) | AO9: =SUMIFS(CR_COD,CR_ST,A9,CR_STAT,"อนุมัติ")+SUMIFS(CR_COD,CR_ST,"ทั้งเฟส",CR_STAT,"อนุมัติ")+SUMIFS(CR_COD,CR_ST,"ผรม. "&L9,CR_STAT,"อนุมัติ")+SUMIFS(CR_COD,CR_ST,"เขต "&E9,CR_STAT,"อนุมัติ") -> 0 | AP9: =IF(NOT(ISNUMBER(AJ9)),"",MAX(0,AJ9-AO9)) -> 0 | AQ9: =COUNTIF(RW_ST,A9) -> 0 | AR9: =IF(ISNUMBER(TCRoof!$I$9),TCRoof!$I$9,"") | AS9: =IF(ISNUMBER(TCRoof!$H$9),TCRoof!$H$9,"") | AT9: =IF(N9<>"","",SUMIFS($F$8:$F$27,$L$8:$L$27,L9,$N$8:$N$27,"",$H$8:$H$27,"<"&H9)+SUMIFS($F$8:$F$27,$L$8:$L$27,L9,$N$8:$N$27,"",$H$8:$H$27,H9,$A$8:$A$27,"<="&A9)+SUMIFS($F$8:$F$27,$L$8:$L$27,L9,$N$8:$N$27,">"&ASOF)) -> 280.44 | AU9: =IFERROR(VLOOKUP(L9,TEAM_TBL,2,0)*VLOOKUP(L9,TEAM_TBL,3,0),150) -> 150 | AV9: =IF(O9<>"","",MAX(Y9+LAG_PEA,ASOF+LAG_PEA)) -> 46356 | AW9: =IF(O9<>"","",COUNTIFS($E$8:$E$27,E9,$AV$8:$AV$27,"<"&AV9)+COUNTIFS($E$8:$E$27,E9,$AV$8:$AV$27,AV9,$A$8:$A$27,"<"&A9)+COUNTIFS($E$8:$E$27,E9,$O$8:$O$27,">"&ASOF)+1) -> 1 | AX9: =IFERROR(VLOOKUP(E9,ZONE_TBL,2,0),CAP_PEA) -> 3 | AY9: =IF(O9<>"","",COUNTIFS($J$8:$J$27,J9,$AV$8:$AV$27,"<"&AV9)+COUNTIFS($J$8:$J$27,J9,$AV$8:$AV$27,AV9,$A$8:$A$27,"<"&A9)+COUNTIFS($J$8:$J$27,J9,$O$8:$O$27,">"&ASOF)+1) -> 1 | AZ9: =IFERROR(VLOOKUP(J9,ENG_TBL,2,0),ENG_CAP) -> 3 | BA9: =IF(P9<>"","",MAX(Z9+LAG_IEC,ASOF+1)) -> 46359 | BB9: =IF(P9<>"","",COUNTIFS($L$8:$L$27,L9,$BA$8:$BA$27,"<"&BA9)+COUNTIFS($L$8:$L$27,L9,$BA$8:$BA$27,BA9,$A$8:$A$27,"<"&A9)+COUNTIFS($L$8:$L$27,L9,$P$8:$P$27,">"&ASOF)+1) -> 1 | BC9: =IFERROR(VLOOKUP(L9,TEAM_TBL,4,0)*VLOOKUP(L9,TEAM_TBL,5,0),3) -> 3 | BD9: =IFERROR(VLOOKUP(L9,TEAM_TBL,6,0),LAG_HO) -> 7 | BE9: =IF(ISNUMBER(AW9),7*INT((AW9-1)/MAX(1,AX9)),"") -> 0 | BF9: =IF(ISNUMBER(AY9),7*INT((AY9-1)/MAX(1,AZ9)),"") -> 0 | BH9: =IF(AND($Y9<>"",$Y9>=BH$7,$Y9<BH$7+7),"I","")&IF(AND($Z9<>"",$Z9>=BH$7,$Z9<BH$7+7),"P","")&IF(AND($AA9<>"",$AA9>=BH$7,$AA9<BH$7+7),"T","")&IF(AND($AB9<>"",$AB9>=BH$7,$AB9<BH$7+7),"H","")&IF(AND($AC9<>"",$AC9>=BH$7,$AC9<BH$7+7),"G","")&IF(AND($AH9<>"",$AH9>=BH$7,$AH9<BH$7+7),"S","") | BI9: =IF(AND($Y9<>"",$Y9>=BI$7,$Y9<BI$7+7),"I","")&IF(AND($Z9<>"",$Z9>=BI$7,$Z9<BI$7+7),"P","")&IF(AND($AA9<>"",$AA9>=BI$7,$AA9<BI$7+7),"T","")&IF(AND($AB9<>"",$AB9>=BI$7,$AB9<BI$7+7),"H","")&IF(AND($AC9<>"",$AC9>=BI$7,$AC9<BI$7+7),"G","")&IF(AND($AH9<>"",$AH9>=BI$7,$AH9<BI$7+7),"S","") | BJ9: =IF(AND($Y9<>"",$Y9>=BJ$7,$Y9<BJ$7+7),"I","")&IF(AND($Z9<>"",$Z9>=BJ$7,$Z9<BJ$7+7),"P","")&IF(AND($AA9<>"",$AA9>=BJ$7,$AA9<BJ$7+7),"T","")&IF(AND($AB9<>"",$AB9>=BJ$7,$AB9<BJ$7+7),"H","")&IF(AND($AC9<>"",$AC9>=BJ$7,$AC9<BJ$7+7),"G","")&IF(AND($AH9<>"",$AH9>=BJ$7,$AH9<BJ$7+7),"S","") | BK9: =IF(AND($Y9<>"",$Y9>=BK$7,$Y9<BK$7+7),"I","")&IF(AND($Z9<>"",$Z9>=BK$7,$Z9<BK$7+7),"P","")&IF(AND($AA9<>"",$AA9>=BK$7,$AA9<BK$7+7),"T","")&IF(AND($AB9<>"",$AB9>=BK$7,$AB9<BK$7+7),"H","")&IF(AND($AC9<>"",$AC9>=BK$7,$AC9<BK$7+7),"G","")&IF(AND($AH9<>"",$AH9>=BK$7,$AH9<BK$7+7),"S","") | BL9: =IF(AND($Y9<>"",$Y9>=BL$7,$Y9<BL$7+7),"I","")&IF(AND($Z9<>"",$Z9>=BL$7,$Z9<BL$7+7),"P","")&IF(AND($AA9<>"",$AA9>=BL$7,$AA9<BL$7+7),"T","")&IF(AND($AB9<>"",$AB9>=BL$7,$AB9<BL$7+7),"H","")&IF(AND($AC9<>"",$AC9>=BL$7,$AC9<BL$7+7),"G","")&IF(AND($AH9<>"",$AH9>=BL$7,$AH9<BL$7+7),"S","") -> I | BM9: =IF(AND($Y9<>"",$Y9>=BM$7,$Y9<BM$7+7),"I","")&IF(AND($Z9<>"",$Z9>=BM$7,$Z9<BM$7+7),"P","")&IF(AND($AA9<>"",$AA9>=BM$7,$AA9<BM$7+7),"T","")&IF(AND($AB9<>"",$AB9>=BM$7,$AB9<BM$7+7),"H","")&IF(AND($AC9<>"",$AC9>=BM$7,$AC9<BM$7+7),"G","")&IF(AND($AH9<>"",$AH9>=BM$7,$AH9<BM$7+7),"S","") -> PTG | BN9: =IF(AND($Y9<>"",$Y9>=BN$7,$Y9<BN$7+7),"I","")&IF(AND($Z9<>"",$Z9>=BN$7,$Z9<BN$7+7),"P","")&IF(AND($AA9<>"",$AA9>=BN$7,$AA9<BN$7+7),"T","")&IF(AND($AB9<>"",$AB9>=BN$7,$AB9<BN$7+7),"H","")&IF(AND($AC9<>"",$AC9>=BN$7,$AC9<BN$7+7),"G","")&IF(AND($AH9<>"",$AH9>=BN$7,$AH9<BN$7+7),"S","") -> H | BO9: =IF(AND($Y9<>"",$Y9>=BO$7,$Y9<BO$7+7),"I","")&IF(AND($Z9<>"",$Z9>=BO$7,$Z9<BO$7+7),"P","")&IF(AND($AA9<>"",$AA9>=BO$7,$AA9<BO$7+7),"T","")&IF(AND($AB9<>"",$AB9>=BO$7,$AB9<BO$7+7),"H","")&IF(AND($AC9<>"",$AC9>=BO$7,$AC9<BO$7+7),"G","")&IF(AND($AH9<>"",$AH9>=BO$7,$AH9<BO$7+7),"S","") | ... DC9: =IF(AND($Y9<>"",$Y9>=DC$7,$Y9<DC$7+7),"I","")&IF(AND($Z9<>"",$Z9>=DC$7,$Z9<DC$7+7),"P","")&IF(AND($AA9<>"",$AA9>=DC$7,$AA9<DC$7+7),"T","")&IF(AND($AB9<>"",$AB9>=DC$7,$AB9<DC$7+7),"H","")&IF(AND($AC9<>"",$AC9>=DC$7,$AC9<DC$7+7),"G","")&IF(AND($AH9<>"",$AH9>=DC$7,$AH9<DC$7+7),"S","")
A10: P9-003 | B10: แม่แบบ หลังคาลอนคู่, กันย้อน LV, Inverter < 200 kVA | C10: (ตัวอย่าง) | D10: ตัวอย่าง | E10: ตย.03 | F10: 150.48 | G10: รอบ 9 | H10: =PROJ_START+RD_SPAN -> 46403 | I10: =H10+33 -> 46436 | J10: วศ.03 | K10: Admin | L10: 03 | M10: N | N10: =IF(ISNUMBER(อัปเดตรายสัปดาห์!$AF10),อัปเดตรายสัปดาห์!$AF10,"") | O10: =IF(ISNUMBER(อัปเดตรายสัปดาห์!$AH10),อัปเดตรายสัปดาห์!$AH10,"") | P10: =IF(ISNUMBER(อัปเดตรายสัปดาห์!$AG10),อัปเดตรายสัปดาห์!$AG10,IF(AND(ISNUMBER(TCRoof!$AC$10),N(TCRoof!$AC$10)<=ASOF),TCRoof!$AC$10,"")) | Q10: =IF(ISNUMBER(อัปเดตรายสัปดาห์!$AL10),อัปเดตรายสัปดาห์!$AL10,"") | R10: =IF(ISNUMBER(อัปเดตรายสัปดาห์!$Q10),อัปเดตรายสัปดาห์!$Q10,"") | S10: =IF(ISNUMBER(อัปเดตรายสัปดาห์!$R10),อัปเดตรายสัปดาห์!$R10,"") | T10: =IF(ISNUMBER(อัปเดตรายสัปดาห์!$S10),อัปเดตรายสัปดาห์!$S10,IF(อัปเดตรายสัปดาห์!$S10="Y",ASOF,"")) | U10: =IF(ISNUMBER(อัปเดตรายสัปดาห์!$T10),อัปเดตรายสัปดาห์!$T10,IF(อัปเดตรายสัปดาห์!$T10="Y",ASOF,"")) | V10: =IF(ISNUMBER(อัปเดตรายสัปดาห์!$U10),อัปเดตรายสัปดาห์!$U10,IF(อัปเดตรายสัปดาห์!$U10="Y",ASOF,"")) | W10: =IF(ISNUMBER(อัปเดตรายสัปดาห์!$N10),อัปเดตรายสัปดาห์!$N10,"") | X10: =IF(ISNUMBER(อัปเดตรายสัปดาห์!$V10),อัปเดตรายสัปดาห์!$V10,IF(AND(ISNUMBER(TCRoof!$AD$10),N(TCRoof!$AD$10)<=ASOF),TCRoof!$AD$10,"")) | Y10: =IF(N10<>"",N10,WORKDAY((ASOF+LEAD_INST+7*INT((AT10-0.01)/MAX(1,AU10)))-1,1,HOLIDAYS)) -> 46349 | Z10: =IF(O10<>"",O10,WORKDAY((MAX(AV10+7*INT((AW10-1)/MAX(1,AX10)),AV10+7*INT((AY10-1)/MAX(1,AZ10))))-1,1,HOLIDAYS)) -> 46356 | AA10: =IF(P10<>"",P10,WORKDAY((BA10+7*INT((BB10-1)/MAX(1,BC10)))-1,1,HOLIDAYS)) -> 46359 | AB10: =IF(Q10<>"",Q10,WORKDAY((MAX(AA10+BD10,ASOF+1))-1,1,HOLIDAYS)) -> 46367 | AC10: =IF(R10<>"",R10,WORKDAY((MAX(Y10,ASOF)+LAG_GRID)-1,1,HOLIDAYS)) -> 46356 | AD10: =IF(T10<>"",T10,WORKDAY((MAX(WORKDAY(MAX(AC10,N(S10)),REVIEW_WD,HOLIDAYS),ASOF+1))-1,1,HOLIDAYS)) -> 46379 | AE10: =IF(U10<>"",U10,WORKDAY((MAX(AD10,ASOF)+FEE_DAYS)-1,1,HOLIDAYS)) -> 46386 | AF10: =IF(V10<>"",V10,WORKDAY((MAX(AA10,Z10,AE10,IF(AG10="",0,AG10+REVIEW_PK2),ASOF)+LAG_INSREQ)-1,1,HOLIDAYS)) -> 46391 | AG10: =IF(M10<>"Y","",IF(W10<>"",W10,WORKDAY((MAX(Y10,ASOF)+LAG_GRID)-1,1,HOLIDAYS))) | AH10: =IF(X10<>"",X10,WORKDAY(AF10,INSPECT_WD,HOLIDAYS)) -> 46433 | AI10: =IF(H10="","",AB10-H10) -> -36 | AJ10: =IF(I10="","",AH10-I10) -> -3 | AK10: =IF(AND(ISNUMBER(N10),N(N10)<=ASOF),1,0)+IF(AND(ISNUMBER(O10),N(O10)<=ASOF),1,0)+IF(AND(ISNUMBER(P10),N(P10)<=ASOF),1,0)+IF(AND(ISNUMBER(Q10),N(Q10)<=ASOF),1,0)+IF(AND(ISNUMBER(R10),N(R10)<=ASOF),1,0)+IF(AND(ISNUMBER(U10),N(U10)<=ASOF),1,0)+IF(AND(ISNUMBER(X10),N(X10)<=ASOF),1,0) -> 0 | AL10: 7 | AM10: ='P9-003'!$J$4 -> 0 | AN10: =TRIM(IF(AND(ISNUMBER(O10),NOT(ISNUMBER(N10))),"กฟภ.ตรวจก่อนติดตั้ง, ","")&IF(AND(ISNUMBER(P10),NOT(ISNUMBER(N10))),"IEC ก่อนติดตั้ง, ","")&IF(AND(ISNUMBER(Q10),NOT(ISNUMBER(N10))),"ส่งมอบก่อนติดตั้ง, ","")&IF(AND(ISNUMBER(Q10),ISNUMBER(P10),N(Q10)<N(P10)),"ส่งมอบก่อน IEC, ","")&IF(AND(ISNUMBER(อัปเดตรายสัปดาห์!$AG10),ISNUMBER(TCRoof!$AC$10),ABS(N(อัปเดตรายสัปดาห์!$AG10)-N(TCRoof!$AC$10))>3),"IEC Excel≠แอป, ","")&IF(AND(ISNUMBER(อัปเดตรายสัปดาห์!$V10),ISNUMBER(TCRoof!$AD$10),ABS(N(อัปเดตรายสัปดาห์!$V10)-N(TCRoof!$AD$10))>3),"COD Excel≠แอป, ","")&IF(AND(ISNUMBER(อัปเดตรายสัปดาห์!$AF10),ISNUMBER(TCRoof!$AB$10),ABS(N(อัปเดตรายสัปดาห์!$AF10)-N(TCRoof!$AB$10))>3),"ติดตั้ง Excel≠แอป, ","")&IF(AND(ISNUMBER(N10),N(N10)>ASOF,OR(WEEKDAY(N(N10),2)>5,COUNTIF(HOLIDAYS,N(N10))>0)),"นัดดับไฟตรงวันหยุด, ","")&IF(AND(ISNUMBER(O10),N(O10)>ASOF,OR(WEEKDAY(N(O10),2)>5,COUNTIF(HOLIDAYS,N(O10))>0)),"นัด กฟภ.ตรงวันหยุด, ","")&IF(AND(ISNUMBER(P10),N(P10)>ASOF,OR(WEEKDAY(N(P10),2)>5,COUNTIF(HOLIDAYS,N(P10))>0)),"นัด IECตรงวันหยุด, ","")&IF(AND(ISNUMBER(X10),N(X10)>ASOF,OR(WEEKDAY(N(X10),2)>5,COUNTIF(HOLIDAYS,N(X10))>0)),"นัด Syncตรงวันหยุด, ","")) | AO10: =SUMIFS(CR_COD,CR_ST,A10,CR_STAT,"อนุมัติ")+SUMIFS(CR_COD,CR_ST,"ทั้งเฟส",CR_STAT,"อนุมัติ")+SUMIFS(CR_COD,CR_ST,"ผรม. "&L10,CR_STAT,"อนุมัติ")+SUMIFS(CR_COD,CR_ST,"เขต "&E10,CR_STAT,"อนุมัติ") -> 0 | AP10: =IF(NOT(ISNUMBER(AJ10)),"",MAX(0,AJ10-AO10)) -> 0 | AQ10: =COUNTIF(RW_ST,A10) -> 0 | AR10: =IF(ISNUMBER(TCRoof!$I$10),TCRoof!$I$10,"") | AS10: =IF(ISNUMBER(TCRoof!$H$10),TCRoof!$H$10,"") | AT10: =IF(N10<>"","",SUMIFS($F$8:$F$27,$L$8:$L$27,L10,$N$8:$N$27,"",$H$8:$H$27,"<"&H10)+SUMIFS($F$8:$F$27,$L$8:$L$27,L10,$N$8:$N$27,"",$H$8:$H$27,H10,$A$8:$A$27,"<="&A10)+SUMIFS($F$8:$F$27,$L$8:$L$27,L10,$N$8:$N$27,">"&ASOF)) -> 150.48 | AU10: =IFERROR(VLOOKUP(L10,TEAM_TBL,2,0)*VLOOKUP(L10,TEAM_TBL,3,0),150) -> 150 | AV10: =IF(O10<>"","",MAX(Y10+LAG_PEA,ASOF+LAG_PEA)) -> 46356 | AW10: =IF(O10<>"","",COUNTIFS($E$8:$E$27,E10,$AV$8:$AV$27,"<"&AV10)+COUNTIFS($E$8:$E$27,E10,$AV$8:$AV$27,AV10,$A$8:$A$27,"<"&A10)+COUNTIFS($E$8:$E$27,E10,$O$8:$O$27,">"&ASOF)+1) -> 1 | AX10: =IFERROR(VLOOKUP(E10,ZONE_TBL,2,0),CAP_PEA) -> 3 | AY10: =IF(O10<>"","",COUNTIFS($J$8:$J$27,J10,$AV$8:$AV$27,"<"&AV10)+COUNTIFS($J$8:$J$27,J10,$AV$8:$AV$27,AV10,$A$8:$A$27,"<"&A10)+COUNTIFS($J$8:$J$27,J10,$O$8:$O$27,">"&ASOF)+1) -> 1 | AZ10: =IFERROR(VLOOKUP(J10,ENG_TBL,2,0),ENG_CAP) -> 3 | BA10: =IF(P10<>"","",MAX(Z10+LAG_IEC,ASOF+1)) -> 46359 | BB10: =IF(P10<>"","",COUNTIFS($L$8:$L$27,L10,$BA$8:$BA$27,"<"&BA10)+COUNTIFS($L$8:$L$27,L10,$BA$8:$BA$27,BA10,$A$8:$A$27,"<"&A10)+COUNTIFS($L$8:$L$27,L10,$P$8:$P$27,">"&ASOF)+1) -> 1 | BC10: =IFERROR(VLOOKUP(L10,TEAM_TBL,4,0)*VLOOKUP(L10,TEAM_TBL,5,0),3) -> 3 | BD10: =IFERROR(VLOOKUP(L10,TEAM_TBL,6,0),LAG_HO) -> 7 | BE10: =IF(ISNUMBER(AW10),7*INT((AW10-1)/MAX(1,AX10)),"") -> 0 | BF10: =IF(ISNUMBER(AY10),7*INT((AY10-1)/MAX(1,AZ10)),"") -> 0 | BH10: =IF(AND($Y10<>"",$Y10>=BH$7,$Y10<BH$7+7),"I","")&IF(AND($Z10<>"",$Z10>=BH$7,$Z10<BH$7+7),"P","")&IF(AND($AA10<>"",$AA10>=BH$7,$AA10<BH$7+7),"T","")&IF(AND($AB10<>"",$AB10>=BH$7,$AB10<BH$7+7),"H","")&IF(AND($AC10<>"",$AC10>=BH$7,$AC10<BH$7+7),"G","")&IF(AND($AH10<>"",$AH10>=BH$7,$AH10<BH$7+7),"S","") | BI10: =IF(AND($Y10<>"",$Y10>=BI$7,$Y10<BI$7+7),"I","")&IF(AND($Z10<>"",$Z10>=BI$7,$Z10<BI$7+7),"P","")&IF(AND($AA10<>"",$AA10>=BI$7,$AA10<BI$7+7),"T","")&IF(AND($AB10<>"",$AB10>=BI$7,$AB10<BI$7+7),"H","")&IF(AND($AC10<>"",$AC10>=BI$7,$AC10<BI$7+7),"G","")&IF(AND($AH10<>"",$AH10>=BI$7,$AH10<BI$7+7),"S","") | BJ10: =IF(AND($Y10<>"",$Y10>=BJ$7,$Y10<BJ$7+7),"I","")&IF(AND($Z10<>"",$Z10>=BJ$7,$Z10<BJ$7+7),"P","")&IF(AND($AA10<>"",$AA10>=BJ$7,$AA10<BJ$7+7),"T","")&IF(AND($AB10<>"",$AB10>=BJ$7,$AB10<BJ$7+7),"H","")&IF(AND($AC10<>"",$AC10>=BJ$7,$AC10<BJ$7+7),"G","")&IF(AND($AH10<>"",$AH10>=BJ$7,$AH10<BJ$7+7),"S","") | BK10: =IF(AND($Y10<>"",$Y10>=BK$7,$Y10<BK$7+7),"I","")&IF(AND($Z10<>"",$Z10>=BK$7,$Z10<BK$7+7),"P","")&IF(AND($AA10<>"",$AA10>=BK$7,$AA10<BK$7+7),"T","")&IF(AND($AB10<>"",$AB10>=BK$7,$AB10<BK$7+7),"H","")&IF(AND($AC10<>"",$AC10>=BK$7,$AC10<BK$7+7),"G","")&IF(AND($AH10<>"",$AH10>=BK$7,$AH10<BK$7+7),"S","") | BL10: =IF(AND($Y10<>"",$Y10>=BL$7,$Y10<BL$7+7),"I","")&IF(AND($Z10<>"",$Z10>=BL$7,$Z10<BL$7+7),"P","")&IF(AND($AA10<>"",$AA10>=BL$7,$AA10<BL$7+7),"T","")&IF(AND($AB10<>"",$AB10>=BL$7,$AB10<BL$7+7),"H","")&IF(AND($AC10<>"",$AC10>=BL$7,$AC10<BL$7+7),"G","")&IF(AND($AH10<>"",$AH10>=BL$7,$AH10<BL$7+7),"S","") -> I | BM10: =IF(AND($Y10<>"",$Y10>=BM$7,$Y10<BM$7+7),"I","")&IF(AND($Z10<>"",$Z10>=BM$7,$Z10<BM$7+7),"P","")&IF(AND($AA10<>"",$AA10>=BM$7,$AA10<BM$7+7),"T","")&IF(AND($AB10<>"",$AB10>=BM$7,$AB10<BM$7+7),"H","")&IF(AND($AC10<>"",$AC10>=BM$7,$AC10<BM$7+7),"G","")&IF(AND($AH10<>"",$AH10>=BM$7,$AH10<BM$7+7),"S","") -> PTG | BN10: =IF(AND($Y10<>"",$Y10>=BN$7,$Y10<BN$7+7),"I","")&IF(AND($Z10<>"",$Z10>=BN$7,$Z10<BN$7+7),"P","")&IF(AND($AA10<>"",$AA10>=BN$7,$AA10<BN$7+7),"T","")&IF(AND($AB10<>"",$AB10>=BN$7,$AB10<BN$7+7),"H","")&IF(AND($AC10<>"",$AC10>=BN$7,$AC10<BN$7+7),"G","")&IF(AND($AH10<>"",$AH10>=BN$7,$AH10<BN$7+7),"S","") -> H | BO10: =IF(AND($Y10<>"",$Y10>=BO$7,$Y10<BO$7+7),"I","")&IF(AND($Z10<>"",$Z10>=BO$7,$Z10<BO$7+7),"P","")&IF(AND($AA10<>"",$AA10>=BO$7,$AA10<BO$7+7),"T","")&IF(AND($AB10<>"",$AB10>=BO$7,$AB10<BO$7+7),"H","")&IF(AND($AC10<>"",$AC10>=BO$7,$AC10<BO$7+7),"G","")&IF(AND($AH10<>"",$AH10>=BO$7,$AH10<BO$7+7),"S","") | ... DC10: =IF(AND($Y10<>"",$Y10>=DC$7,$Y10<DC$7+7),"I","")&IF(AND($Z10<>"",$Z10>=DC$7,$Z10<DC$7+7),"P","")&IF(AND($AA10<>"",$AA10>=DC$7,$AA10<DC$7+7),"T","")&IF(AND($AB10<>"",$AB10>=DC$7,$AB10<DC$7+7),"H","")&IF(AND($AC10<>"",$AC10>=DC$7,$AC10<DC$7+7),"G","")&IF(AND($AH10<>"",$AH10>=DC$7,$AH10<DC$7+7),"S","")
A11: P9-004 | B11: แม่แบบ หลังคาลอนคู่, กันย้อน LV, Inverter ≥ 200 kVA | C11: (ตัวอย่าง) | D11: ตัวอย่าง | E11: ตย.04 | F11: 280.44 | G11: รอบ 9 | H11: =PROJ_START+RD_SPAN -> 46403 | I11: =H11+33 -> 46436 | J11: วศ.04 | K11: Admin | L11: 04 | M11: Y | N11: =IF(ISNUMBER(อัปเดตรายสัปดาห์!$AF11),อัปเดตรายสัปดาห์!$AF11,"") | O11: =IF(ISNUMBER(อัปเดตรายสัปดาห์!$AH11),อัปเดตรายสัปดาห์!$AH11,"") | P11: =IF(ISNUMBER(อัปเดตรายสัปดาห์!$AG11),อัปเดตรายสัปดาห์!$AG11,IF(AND(ISNUMBER(TCRoof!$AC$11),N(TCRoof!$AC$11)<=ASOF),TCRoof!$AC$11,"")) | Q11: =IF(ISNUMBER(อัปเดตรายสัปดาห์!$AL11),อัปเดตรายสัปดาห์!$AL11,"") | R11: =IF(ISNUMBER(อัปเดตรายสัปดาห์!$Q11),อัปเดตรายสัปดาห์!$Q11,"") | S11: =IF(ISNUMBER(อัปเดตรายสัปดาห์!$R11),อัปเดตรายสัปดาห์!$R11,"") | T11: =IF(ISNUMBER(อัปเดตรายสัปดาห์!$S11),อัปเดตรายสัปดาห์!$S11,IF(อัปเดตรายสัปดาห์!$S11="Y",ASOF,"")) | U11: =IF(ISNUMBER(อัปเดตรายสัปดาห์!$T11),อัปเดตรายสัปดาห์!$T11,IF(อัปเดตรายสัปดาห์!$T11="Y",ASOF,"")) | V11: =IF(ISNUMBER(อัปเดตรายสัปดาห์!$U11),อัปเดตรายสัปดาห์!$U11,IF(อัปเดตรายสัปดาห์!$U11="Y",ASOF,"")) | W11: =IF(ISNUMBER(อัปเดตรายสัปดาห์!$N11),อัปเดตรายสัปดาห์!$N11,"") | X11: =IF(ISNUMBER(อัปเดตรายสัปดาห์!$V11),อัปเดตรายสัปดาห์!$V11,IF(AND(ISNUMBER(TCRoof!$AD$11),N(TCRoof!$AD$11)<=ASOF),TCRoof!$AD$11,"")) | Y11: =IF(N11<>"",N11,WORKDAY((ASOF+LEAD_INST+7*INT((AT11-0.01)/MAX(1,AU11)))-1,1,HOLIDAYS)) -> 46349 | Z11: =IF(O11<>"",O11,WORKDAY((MAX(AV11+7*INT((AW11-1)/MAX(1,AX11)),AV11+7*INT((AY11-1)/MAX(1,AZ11))))-1,1,HOLIDAYS)) -> 46356 | AA11: =IF(P11<>"",P11,WORKDAY((BA11+7*INT((BB11-1)/MAX(1,BC11)))-1,1,HOLIDAYS)) -> 46359 | AB11: =IF(Q11<>"",Q11,WORKDAY((MAX(AA11+BD11,ASOF+1))-1,1,HOLIDAYS)) -> 46367 | AC11: =IF(R11<>"",R11,WORKDAY((MAX(Y11,ASOF)+LAG_GRID)-1,1,HOLIDAYS)) -> 46356 | AD11: =IF(T11<>"",T11,WORKDAY((MAX(WORKDAY(MAX(AC11,N(S11)),REVIEW_WD,HOLIDAYS),ASOF+1))-1,1,HOLIDAYS)) -> 46379 | AE11: =IF(U11<>"",U11,WORKDAY((MAX(AD11,ASOF)+FEE_DAYS)-1,1,HOLIDAYS)) -> 46386 | AF11: =IF(V11<>"",V11,WORKDAY((MAX(AA11,Z11,AE11,IF(AG11="",0,AG11+REVIEW_PK2),ASOF)+LAG_INSREQ)-1,1,HOLIDAYS)) -> 46391 | AG11: =IF(M11<>"Y","",IF(W11<>"",W11,WORKDAY((MAX(Y11,ASOF)+LAG_GRID)-1,1,HOLIDAYS))) -> 46356 | AH11: =IF(X11<>"",X11,WORKDAY(AF11,INSPECT_WD,HOLIDAYS)) -> 46433 | AI11: =IF(H11="","",AB11-H11) -> -36 | AJ11: =IF(I11="","",AH11-I11) -> -3 | AK11: =IF(AND(ISNUMBER(N11),N(N11)<=ASOF),1,0)+IF(AND(ISNUMBER(O11),N(O11)<=ASOF),1,0)+IF(AND(ISNUMBER(P11),N(P11)<=ASOF),1,0)+IF(AND(ISNUMBER(Q11),N(Q11)<=ASOF),1,0)+IF(AND(ISNUMBER(R11),N(R11)<=ASOF),1,0)+IF(AND(ISNUMBER(U11),N(U11)<=ASOF),1,0)+IF(AND(ISNUMBER(X11),N(X11)<=ASOF),1,0)+IF(AND(ISNUMBER(W11),N(W11)<=ASOF),1,0) -> 0 | AL11: 8 | AM11: ='P9-004'!$J$4 -> 0 | AN11: =TRIM(IF(AND(ISNUMBER(O11),NOT(ISNUMBER(N11))),"กฟภ.ตรวจก่อนติดตั้ง, ","")&IF(AND(ISNUMBER(P11),NOT(ISNUMBER(N11))),"IEC ก่อนติดตั้ง, ","")&IF(AND(ISNUMBER(Q11),NOT(ISNUMBER(N11))),"ส่งมอบก่อนติดตั้ง, ","")&IF(AND(ISNUMBER(Q11),ISNUMBER(P11),N(Q11)<N(P11)),"ส่งมอบก่อน IEC, ","")&IF(AND(ISNUMBER(อัปเดตรายสัปดาห์!$AG11),ISNUMBER(TCRoof!$AC$11),ABS(N(อัปเดตรายสัปดาห์!$AG11)-N(TCRoof!$AC$11))>3),"IEC Excel≠แอป, ","")&IF(AND(ISNUMBER(อัปเดตรายสัปดาห์!$V11),ISNUMBER(TCRoof!$AD$11),ABS(N(อัปเดตรายสัปดาห์!$V11)-N(TCRoof!$AD$11))>3),"COD Excel≠แอป, ","")&IF(AND(ISNUMBER(อัปเดตรายสัปดาห์!$AF11),ISNUMBER(TCRoof!$AB$11),ABS(N(อัปเดตรายสัปดาห์!$AF11)-N(TCRoof!$AB$11))>3),"ติดตั้ง Excel≠แอป, ","")&IF(AND(ISNUMBER(N11),N(N11)>ASOF,OR(WEEKDAY(N(N11),2)>5,COUNTIF(HOLIDAYS,N(N11))>0)),"นัดดับไฟตรงวันหยุด, ","")&IF(AND(ISNUMBER(O11),N(O11)>ASOF,OR(WEEKDAY(N(O11),2)>5,COUNTIF(HOLIDAYS,N(O11))>0)),"นัด กฟภ.ตรงวันหยุด, ","")&IF(AND(ISNUMBER(P11),N(P11)>ASOF,OR(WEEKDAY(N(P11),2)>5,COUNTIF(HOLIDAYS,N(P11))>0)),"นัด IECตรงวันหยุด, ","")&IF(AND(ISNUMBER(X11),N(X11)>ASOF,OR(WEEKDAY(N(X11),2)>5,COUNTIF(HOLIDAYS,N(X11))>0)),"นัด Syncตรงวันหยุด, ","")) | AO11: =SUMIFS(CR_COD,CR_ST,A11,CR_STAT,"อนุมัติ")+SUMIFS(CR_COD,CR_ST,"ทั้งเฟส",CR_STAT,"อนุมัติ")+SUMIFS(CR_COD,CR_ST,"ผรม. "&L11,CR_STAT,"อนุมัติ")+SUMIFS(CR_COD,CR_ST,"เขต "&E11,CR_STAT,"อนุมัติ") -> 0 | AP11: =IF(NOT(ISNUMBER(AJ11)),"",MAX(0,AJ11-AO11)) -> 0 | AQ11: =COUNTIF(RW_ST,A11) -> 0 | AR11: =IF(ISNUMBER(TCRoof!$I$11),TCRoof!$I$11,"") | AS11: =IF(ISNUMBER(TCRoof!$H$11),TCRoof!$H$11,"") | AT11: =IF(N11<>"","",SUMIFS($F$8:$F$27,$L$8:$L$27,L11,$N$8:$N$27,"",$H$8:$H$27,"<"&H11)+SUMIFS($F$8:$F$27,$L$8:$L$27,L11,$N$8:$N$27,"",$H$8:$H$27,H11,$A$8:$A$27,"<="&A11)+SUMIFS($F$8:$F$27,$L$8:$L$27,L11,$N$8:$N$27,">"&ASOF)) -> 280.44 | AU11: =IFERROR(VLOOKUP(L11,TEAM_TBL,2,0)*VLOOKUP(L11,TEAM_TBL,3,0),150) -> 150 | AV11: =IF(O11<>"","",MAX(Y11+LAG_PEA,ASOF+LAG_PEA)) -> 46356 | AW11: =IF(O11<>"","",COUNTIFS($E$8:$E$27,E11,$AV$8:$AV$27,"<"&AV11)+COUNTIFS($E$8:$E$27,E11,$AV$8:$AV$27,AV11,$A$8:$A$27,"<"&A11)+COUNTIFS($E$8:$E$27,E11,$O$8:$O$27,">"&ASOF)+1) -> 1 | AX11: =IFERROR(VLOOKUP(E11,ZONE_TBL,2,0),CAP_PEA) -> 3 | AY11: =IF(O11<>"","",COUNTIFS($J$8:$J$27,J11,$AV$8:$AV$27,"<"&AV11)+COUNTIFS($J$8:$J$27,J11,$AV$8:$AV$27,AV11,$A$8:$A$27,"<"&A11)+COUNTIFS($J$8:$J$27,J11,$O$8:$O$27,">"&ASOF)+1) -> 1 | AZ11: =IFERROR(VLOOKUP(J11,ENG_TBL,2,0),ENG_CAP) -> 3 | BA11: =IF(P11<>"","",MAX(Z11+LAG_IEC,ASOF+1)) -> 46359 | BB11: =IF(P11<>"","",COUNTIFS($L$8:$L$27,L11,$BA$8:$BA$27,"<"&BA11)+COUNTIFS($L$8:$L$27,L11,$BA$8:$BA$27,BA11,$A$8:$A$27,"<"&A11)+COUNTIFS($L$8:$L$27,L11,$P$8:$P$27,">"&ASOF)+1) -> 1 | BC11: =IFERROR(VLOOKUP(L11,TEAM_TBL,4,0)*VLOOKUP(L11,TEAM_TBL,5,0),3) -> 3 | BD11: =IFERROR(VLOOKUP(L11,TEAM_TBL,6,0),LAG_HO) -> 7 | BE11: =IF(ISNUMBER(AW11),7*INT((AW11-1)/MAX(1,AX11)),"") -> 0 | BF11: =IF(ISNUMBER(AY11),7*INT((AY11-1)/MAX(1,AZ11)),"") -> 0 | BH11: =IF(AND($Y11<>"",$Y11>=BH$7,$Y11<BH$7+7),"I","")&IF(AND($Z11<>"",$Z11>=BH$7,$Z11<BH$7+7),"P","")&IF(AND($AA11<>"",$AA11>=BH$7,$AA11<BH$7+7),"T","")&IF(AND($AB11<>"",$AB11>=BH$7,$AB11<BH$7+7),"H","")&IF(AND($AC11<>"",$AC11>=BH$7,$AC11<BH$7+7),"G","")&IF(AND($AH11<>"",$AH11>=BH$7,$AH11<BH$7+7),"S","") | BI11: =IF(AND($Y11<>"",$Y11>=BI$7,$Y11<BI$7+7),"I","")&IF(AND($Z11<>"",$Z11>=BI$7,$Z11<BI$7+7),"P","")&IF(AND($AA11<>"",$AA11>=BI$7,$AA11<BI$7+7),"T","")&IF(AND($AB11<>"",$AB11>=BI$7,$AB11<BI$7+7),"H","")&IF(AND($AC11<>"",$AC11>=BI$7,$AC11<BI$7+7),"G","")&IF(AND($AH11<>"",$AH11>=BI$7,$AH11<BI$7+7),"S","") | BJ11: =IF(AND($Y11<>"",$Y11>=BJ$7,$Y11<BJ$7+7),"I","")&IF(AND($Z11<>"",$Z11>=BJ$7,$Z11<BJ$7+7),"P","")&IF(AND($AA11<>"",$AA11>=BJ$7,$AA11<BJ$7+7),"T","")&IF(AND($AB11<>"",$AB11>=BJ$7,$AB11<BJ$7+7),"H","")&IF(AND($AC11<>"",$AC11>=BJ$7,$AC11<BJ$7+7),"G","")&IF(AND($AH11<>"",$AH11>=BJ$7,$AH11<BJ$7+7),"S","") | BK11: =IF(AND($Y11<>"",$Y11>=BK$7,$Y11<BK$7+7),"I","")&IF(AND($Z11<>"",$Z11>=BK$7,$Z11<BK$7+7),"P","")&IF(AND($AA11<>"",$AA11>=BK$7,$AA11<BK$7+7),"T","")&IF(AND($AB11<>"",$AB11>=BK$7,$AB11<BK$7+7),"H","")&IF(AND($AC11<>"",$AC11>=BK$7,$AC11<BK$7+7),"G","")&IF(AND($AH11<>"",$AH11>=BK$7,$AH11<BK$7+7),"S","") | BL11: =IF(AND($Y11<>"",$Y11>=BL$7,$Y11<BL$7+7),"I","")&IF(AND($Z11<>"",$Z11>=BL$7,$Z11<BL$7+7),"P","")&IF(AND($AA11<>"",$AA11>=BL$7,$AA11<BL$7+7),"T","")&IF(AND($AB11<>"",$AB11>=BL$7,$AB11<BL$7+7),"H","")&IF(AND($AC11<>"",$AC11>=BL$7,$AC11<BL$7+7),"G","")&IF(AND($AH11<>"",$AH11>=BL$7,$AH11<BL$7+7),"S","") -> I | BM11: =IF(AND($Y11<>"",$Y11>=BM$7,$Y11<BM$7+7),"I","")&IF(AND($Z11<>"",$Z11>=BM$7,$Z11<BM$7+7),"P","")&IF(AND($AA11<>"",$AA11>=BM$7,$AA11<BM$7+7),"T","")&IF(AND($AB11<>"",$AB11>=BM$7,$AB11<BM$7+7),"H","")&IF(AND($AC11<>"",$AC11>=BM$7,$AC11<BM$7+7),"G","")&IF(AND($AH11<>"",$AH11>=BM$7,$AH11<BM$7+7),"S","") -> PTG | BN11: =IF(AND($Y11<>"",$Y11>=BN$7,$Y11<BN$7+7),"I","")&IF(AND($Z11<>"",$Z11>=BN$7,$Z11<BN$7+7),"P","")&IF(AND($AA11<>"",$AA11>=BN$7,$AA11<BN$7+7),"T","")&IF(AND($AB11<>"",$AB11>=BN$7,$AB11<BN$7+7),"H","")&IF(AND($AC11<>"",$AC11>=BN$7,$AC11<BN$7+7),"G","")&IF(AND($AH11<>"",$AH11>=BN$7,$AH11<BN$7+7),"S","") -> H | BO11: =IF(AND($Y11<>"",$Y11>=BO$7,$Y11<BO$7+7),"I","")&IF(AND($Z11<>"",$Z11>=BO$7,$Z11<BO$7+7),"P","")&IF(AND($AA11<>"",$AA11>=BO$7,$AA11<BO$7+7),"T","")&IF(AND($AB11<>"",$AB11>=BO$7,$AB11<BO$7+7),"H","")&IF(AND($AC11<>"",$AC11>=BO$7,$AC11<BO$7+7),"G","")&IF(AND($AH11<>"",$AH11>=BO$7,$AH11<BO$7+7),"S","") | ... DC11: =IF(AND($Y11<>"",$Y11>=DC$7,$Y11<DC$7+7),"I","")&IF(AND($Z11<>"",$Z11>=DC$7,$Z11<DC$7+7),"P","")&IF(AND($AA11<>"",$AA11>=DC$7,$AA11<DC$7+7),"T","")&IF(AND($AB11<>"",$AB11>=DC$7,$AB11<DC$7+7),"H","")&IF(AND($AC11<>"",$AC11>=DC$7,$AC11<DC$7+7),"G","")&IF(AND($AH11<>"",$AH11>=DC$7,$AH11<DC$7+7),"S","")
A12: P9-005 | B12: แม่แบบ หลังคาเมทัลชีท, กันย้อน HV, Inverter < 200 kVA | C12: (ตัวอย่าง) | D12: ตัวอย่าง | E12: ตย.05 | F12: 150.48 | G12: รอบ 9 | H12: =PROJ_START+RD_SPAN -> 46403 | I12: =H12+33 -> 46436 | J12: วศ.05 | K12: Admin | L12: 05 | M12: N | N12: =IF(ISNUMBER(อัปเดตรายสัปดาห์!$AF12),อัปเดตรายสัปดาห์!$AF12,"") | O12: =IF(ISNUMBER(อัปเดตรายสัปดาห์!$AH12),อัปเดตรายสัปดาห์!$AH12,"") | P12: =IF(ISNUMBER(อัปเดตรายสัปดาห์!$AG12),อัปเดตรายสัปดาห์!$AG12,IF(AND(ISNUMBER(TCRoof!$AC$12),N(TCRoof!$AC$12)<=ASOF),TCRoof!$AC$12,"")) | Q12: =IF(ISNUMBER(อัปเดตรายสัปดาห์!$AL12),อัปเดตรายสัปดาห์!$AL12,"") | R12: =IF(ISNUMBER(อัปเดตรายสัปดาห์!$Q12),อัปเดตรายสัปดาห์!$Q12,"") | S12: =IF(ISNUMBER(อัปเดตรายสัปดาห์!$R12),อัปเดตรายสัปดาห์!$R12,"") | T12: =IF(ISNUMBER(อัปเดตรายสัปดาห์!$S12),อัปเดตรายสัปดาห์!$S12,IF(อัปเดตรายสัปดาห์!$S12="Y",ASOF,"")) | U12: =IF(ISNUMBER(อัปเดตรายสัปดาห์!$T12),อัปเดตรายสัปดาห์!$T12,IF(อัปเดตรายสัปดาห์!$T12="Y",ASOF,"")) | V12: =IF(ISNUMBER(อัปเดตรายสัปดาห์!$U12),อัปเดตรายสัปดาห์!$U12,IF(อัปเดตรายสัปดาห์!$U12="Y",ASOF,"")) | W12: =IF(ISNUMBER(อัปเดตรายสัปดาห์!$N12),อัปเดตรายสัปดาห์!$N12,"") | X12: =IF(ISNUMBER(อัปเดตรายสัปดาห์!$V12),อัปเดตรายสัปดาห์!$V12,IF(AND(ISNUMBER(TCRoof!$AD$12),N(TCRoof!$AD$12)<=ASOF),TCRoof!$AD$12,"")) | Y12: =IF(N12<>"",N12,WORKDAY((ASOF+LEAD_INST+7*INT((AT12-0.01)/MAX(1,AU12)))-1,1,HOLIDAYS)) -> 46349 | Z12: =IF(O12<>"",O12,WORKDAY((MAX(AV12+7*INT((AW12-1)/MAX(1,AX12)),AV12+7*INT((AY12-1)/MAX(1,AZ12))))-1,1,HOLIDAYS)) -> 46356 | AA12: =IF(P12<>"",P12,WORKDAY((BA12+7*INT((BB12-1)/MAX(1,BC12)))-1,1,HOLIDAYS)) -> 46359 | AB12: =IF(Q12<>"",Q12,WORKDAY((MAX(AA12+BD12,ASOF+1))-1,1,HOLIDAYS)) -> 46367 | AC12: =IF(R12<>"",R12,WORKDAY((MAX(Y12,ASOF)+LAG_GRID)-1,1,HOLIDAYS)) -> 46356 | AD12: =IF(T12<>"",T12,WORKDAY((MAX(WORKDAY(MAX(AC12,N(S12)),REVIEW_WD,HOLIDAYS),ASOF+1))-1,1,HOLIDAYS)) -> 46379 | AE12: =IF(U12<>"",U12,WORKDAY((MAX(AD12,ASOF)+FEE_DAYS)-1,1,HOLIDAYS)) -> 46386 | AF12: =IF(V12<>"",V12,WORKDAY((MAX(AA12,Z12,AE12,IF(AG12="",0,AG12+REVIEW_PK2),ASOF)+LAG_INSREQ)-1,1,HOLIDAYS)) -> 46391 | AG12: =IF(M12<>"Y","",IF(W12<>"",W12,WORKDAY((MAX(Y12,ASOF)+LAG_GRID)-1,1,HOLIDAYS))) | AH12: =IF(X12<>"",X12,WORKDAY(AF12,INSPECT_WD,HOLIDAYS)) -> 46433 | AI12: =IF(H12="","",AB12-H12) -> -36 | AJ12: =IF(I12="","",AH12-I12) -> -3 | AK12: =IF(AND(ISNUMBER(N12),N(N12)<=ASOF),1,0)+IF(AND(ISNUMBER(O12),N(O12)<=ASOF),1,0)+IF(AND(ISNUMBER(P12),N(P12)<=ASOF),1,0)+IF(AND(ISNUMBER(Q12),N(Q12)<=ASOF),1,0)+IF(AND(ISNUMBER(R12),N(R12)<=ASOF),1,0)+IF(AND(ISNUMBER(U12),N(U12)<=ASOF),1,0)+IF(AND(ISNUMBER(X12),N(X12)<=ASOF),1,0) -> 0 | AL12: 7 | AM12: ='P9-005'!$J$4 -> 0 | AN12: =TRIM(IF(AND(ISNUMBER(O12),NOT(ISNUMBER(N12))),"กฟภ.ตรวจก่อนติดตั้ง, ","")&IF(AND(ISNUMBER(P12),NOT(ISNUMBER(N12))),"IEC ก่อนติดตั้ง, ","")&IF(AND(ISNUMBER(Q12),NOT(ISNUMBER(N12))),"ส่งมอบก่อนติดตั้ง, ","")&IF(AND(ISNUMBER(Q12),ISNUMBER(P12),N(Q12)<N(P12)),"ส่งมอบก่อน IEC, ","")&IF(AND(ISNUMBER(อัปเดตรายสัปดาห์!$AG12),ISNUMBER(TCRoof!$AC$12),ABS(N(อัปเดตรายสัปดาห์!$AG12)-N(TCRoof!$AC$12))>3),"IEC Excel≠แอป, ","")&IF(AND(ISNUMBER(อัปเดตรายสัปดาห์!$V12),ISNUMBER(TCRoof!$AD$12),ABS(N(อัปเดตรายสัปดาห์!$V12)-N(TCRoof!$AD$12))>3),"COD Excel≠แอป, ","")&IF(AND(ISNUMBER(อัปเดตรายสัปดาห์!$AF12),ISNUMBER(TCRoof!$AB$12),ABS(N(อัปเดตรายสัปดาห์!$AF12)-N(TCRoof!$AB$12))>3),"ติดตั้ง Excel≠แอป, ","")&IF(AND(ISNUMBER(N12),N(N12)>ASOF,OR(WEEKDAY(N(N12),2)>5,COUNTIF(HOLIDAYS,N(N12))>0)),"นัดดับไฟตรงวันหยุด, ","")&IF(AND(ISNUMBER(O12),N(O12)>ASOF,OR(WEEKDAY(N(O12),2)>5,COUNTIF(HOLIDAYS,N(O12))>0)),"นัด กฟภ.ตรงวันหยุด, ","")&IF(AND(ISNUMBER(P12),N(P12)>ASOF,OR(WEEKDAY(N(P12),2)>5,COUNTIF(HOLIDAYS,N(P12))>0)),"นัด IECตรงวันหยุด, ","")&IF(AND(ISNUMBER(X12),N(X12)>ASOF,OR(WEEKDAY(N(X12),2)>5,COUNTIF(HOLIDAYS,N(X12))>0)),"นัด Syncตรงวันหยุด, ","")) | AO12: =SUMIFS(CR_COD,CR_ST,A12,CR_STAT,"อนุมัติ")+SUMIFS(CR_COD,CR_ST,"ทั้งเฟส",CR_STAT,"อนุมัติ")+SUMIFS(CR_COD,CR_ST,"ผรม. "&L12,CR_STAT,"อนุมัติ")+SUMIFS(CR_COD,CR_ST,"เขต "&E12,CR_STAT,"อนุมัติ") -> 0 | AP12: =IF(NOT(ISNUMBER(AJ12)),"",MAX(0,AJ12-AO12)) -> 0 | AQ12: =COUNTIF(RW_ST,A12) -> 0 | AR12: =IF(ISNUMBER(TCRoof!$I$12),TCRoof!$I$12,"") | AS12: =IF(ISNUMBER(TCRoof!$H$12),TCRoof!$H$12,"") | AT12: =IF(N12<>"","",SUMIFS($F$8:$F$27,$L$8:$L$27,L12,$N$8:$N$27,"",$H$8:$H$27,"<"&H12)+SUMIFS($F$8:$F$27,$L$8:$L$27,L12,$N$8:$N$27,"",$H$8:$H$27,H12,$A$8:$A$27,"<="&A12)+SUMIFS($F$8:$F$27,$L$8:$L$27,L12,$N$8:$N$27,">"&ASOF)) -> 150.48 | AU12: =IFERROR(VLOOKUP(L12,TEAM_TBL,2,0)*VLOOKUP(L12,TEAM_TBL,3,0),150) -> 150 | AV12: =IF(O12<>"","",MAX(Y12+LAG_PEA,ASOF+LAG_PEA)) -> 46356 | AW12: =IF(O12<>"","",COUNTIFS($E$8:$E$27,E12,$AV$8:$AV$27,"<"&AV12)+COUNTIFS($E$8:$E$27,E12,$AV$8:$AV$27,AV12,$A$8:$A$27,"<"&A12)+COUNTIFS($E$8:$E$27,E12,$O$8:$O$27,">"&ASOF)+1) -> 1 | AX12: =IFERROR(VLOOKUP(E12,ZONE_TBL,2,0),CAP_PEA) -> 3 | AY12: =IF(O12<>"","",COUNTIFS($J$8:$J$27,J12,$AV$8:$AV$27,"<"&AV12)+COUNTIFS($J$8:$J$27,J12,$AV$8:$AV$27,AV12,$A$8:$A$27,"<"&A12)+COUNTIFS($J$8:$J$27,J12,$O$8:$O$27,">"&ASOF)+1) -> 1 | AZ12: =IFERROR(VLOOKUP(J12,ENG_TBL,2,0),ENG_CAP) -> 3 | BA12: =IF(P12<>"","",MAX(Z12+LAG_IEC,ASOF+1)) -> 46359 | BB12: =IF(P12<>"","",COUNTIFS($L$8:$L$27,L12,$BA$8:$BA$27,"<"&BA12)+COUNTIFS($L$8:$L$27,L12,$BA$8:$BA$27,BA12,$A$8:$A$27,"<"&A12)+COUNTIFS($L$8:$L$27,L12,$P$8:$P$27,">"&ASOF)+1) -> 1 | BC12: =IFERROR(VLOOKUP(L12,TEAM_TBL,4,0)*VLOOKUP(L12,TEAM_TBL,5,0),3) -> 3 | BD12: =IFERROR(VLOOKUP(L12,TEAM_TBL,6,0),LAG_HO) -> 7 | BE12: =IF(ISNUMBER(AW12),7*INT((AW12-1)/MAX(1,AX12)),"") -> 0 | BF12: =IF(ISNUMBER(AY12),7*INT((AY12-1)/MAX(1,AZ12)),"") -> 0 | BH12: =IF(AND($Y12<>"",$Y12>=BH$7,$Y12<BH$7+7),"I","")&IF(AND($Z12<>"",$Z12>=BH$7,$Z12<BH$7+7),"P","")&IF(AND($AA12<>"",$AA12>=BH$7,$AA12<BH$7+7),"T","")&IF(AND($AB12<>"",$AB12>=BH$7,$AB12<BH$7+7),"H","")&IF(AND($AC12<>"",$AC12>=BH$7,$AC12<BH$7+7),"G","")&IF(AND($AH12<>"",$AH12>=BH$7,$AH12<BH$7+7),"S","") | BI12: =IF(AND($Y12<>"",$Y12>=BI$7,$Y12<BI$7+7),"I","")&IF(AND($Z12<>"",$Z12>=BI$7,$Z12<BI$7+7),"P","")&IF(AND($AA12<>"",$AA12>=BI$7,$AA12<BI$7+7),"T","")&IF(AND($AB12<>"",$AB12>=BI$7,$AB12<BI$7+7),"H","")&IF(AND($AC12<>"",$AC12>=BI$7,$AC12<BI$7+7),"G","")&IF(AND($AH12<>"",$AH12>=BI$7,$AH12<BI$7+7),"S","") | BJ12: =IF(AND($Y12<>"",$Y12>=BJ$7,$Y12<BJ$7+7),"I","")&IF(AND($Z12<>"",$Z12>=BJ$7,$Z12<BJ$7+7),"P","")&IF(AND($AA12<>"",$AA12>=BJ$7,$AA12<BJ$7+7),"T","")&IF(AND($AB12<>"",$AB12>=BJ$7,$AB12<BJ$7+7),"H","")&IF(AND($AC12<>"",$AC12>=BJ$7,$AC12<BJ$7+7),"G","")&IF(AND($AH12<>"",$AH12>=BJ$7,$AH12<BJ$7+7),"S","") | BK12: =IF(AND($Y12<>"",$Y12>=BK$7,$Y12<BK$7+7),"I","")&IF(AND($Z12<>"",$Z12>=BK$7,$Z12<BK$7+7),"P","")&IF(AND($AA12<>"",$AA12>=BK$7,$AA12<BK$7+7),"T","")&IF(AND($AB12<>"",$AB12>=BK$7,$AB12<BK$7+7),"H","")&IF(AND($AC12<>"",$AC12>=BK$7,$AC12<BK$7+7),"G","")&IF(AND($AH12<>"",$AH12>=BK$7,$AH12<BK$7+7),"S","") | BL12: =IF(AND($Y12<>"",$Y12>=BL$7,$Y12<BL$7+7),"I","")&IF(AND($Z12<>"",$Z12>=BL$7,$Z12<BL$7+7),"P","")&IF(AND($AA12<>"",$AA12>=BL$7,$AA12<BL$7+7),"T","")&IF(AND($AB12<>"",$AB12>=BL$7,$AB12<BL$7+7),"H","")&IF(AND($AC12<>"",$AC12>=BL$7,$AC12<BL$7+7),"G","")&IF(AND($AH12<>"",$AH12>=BL$7,$AH12<BL$7+7),"S","") -> I | BM12: =IF(AND($Y12<>"",$Y12>=BM$7,$Y12<BM$7+7),"I","")&IF(AND($Z12<>"",$Z12>=BM$7,$Z12<BM$7+7),"P","")&IF(AND($AA12<>"",$AA12>=BM$7,$AA12<BM$7+7),"T","")&IF(AND($AB12<>"",$AB12>=BM$7,$AB12<BM$7+7),"H","")&IF(AND($AC12<>"",$AC12>=BM$7,$AC12<BM$7+7),"G","")&IF(AND($AH12<>"",$AH12>=BM$7,$AH12<BM$7+7),"S","") -> PTG | BN12: =IF(AND($Y12<>"",$Y12>=BN$7,$Y12<BN$7+7),"I","")&IF(AND($Z12<>"",$Z12>=BN$7,$Z12<BN$7+7),"P","")&IF(AND($AA12<>"",$AA12>=BN$7,$AA12<BN$7+7),"T","")&IF(AND($AB12<>"",$AB12>=BN$7,$AB12<BN$7+7),"H","")&IF(AND($AC12<>"",$AC12>=BN$7,$AC12<BN$7+7),"G","")&IF(AND($AH12<>"",$AH12>=BN$7,$AH12<BN$7+7),"S","") -> H | BO12: =IF(AND($Y12<>"",$Y12>=BO$7,$Y12<BO$7+7),"I","")&IF(AND($Z12<>"",$Z12>=BO$7,$Z12<BO$7+7),"P","")&IF(AND($AA12<>"",$AA12>=BO$7,$AA12<BO$7+7),"T","")&IF(AND($AB12<>"",$AB12>=BO$7,$AB12<BO$7+7),"H","")&IF(AND($AC12<>"",$AC12>=BO$7,$AC12<BO$7+7),"G","")&IF(AND($AH12<>"",$AH12>=BO$7,$AH12<BO$7+7),"S","") | ... DC12: =IF(AND($Y12<>"",$Y12>=DC$7,$Y12<DC$7+7),"I","")&IF(AND($Z12<>"",$Z12>=DC$7,$Z12<DC$7+7),"P","")&IF(AND($AA12<>"",$AA12>=DC$7,$AA12<DC$7+7),"T","")&IF(AND($AB12<>"",$AB12>=DC$7,$AB12<DC$7+7),"H","")&IF(AND($AC12<>"",$AC12>=DC$7,$AC12<DC$7+7),"G","")&IF(AND($AH12<>"",$AH12>=DC$7,$AH12<DC$7+7),"S","")
A13: P9-006 | B13: แม่แบบ หลังคาเมทัลชีท, กันย้อน HV, Inverter ≥ 200 kVA | C13: (ตัวอย่าง) | D13: ตัวอย่าง | E13: ตย.06 | F13: 280.44 | G13: รอบ 9 | H13: =PROJ_START+RD_SPAN -> 46403 | I13: =H13+33 -> 46436 | J13: วศ.06 | K13: Admin | L13: 06 | M13: Y | N13: =IF(ISNUMBER(อัปเดตรายสัปดาห์!$AF13),อัปเดตรายสัปดาห์!$AF13,"") | O13: =IF(ISNUMBER(อัปเดตรายสัปดาห์!$AH13),อัปเดตรายสัปดาห์!$AH13,"") | P13: =IF(ISNUMBER(อัปเดตรายสัปดาห์!$AG13),อัปเดตรายสัปดาห์!$AG13,IF(AND(ISNUMBER(TCRoof!$AC$13),N(TCRoof!$AC$13)<=ASOF),TCRoof!$AC$13,"")) | Q13: =IF(ISNUMBER(อัปเดตรายสัปดาห์!$AL13),อัปเดตรายสัปดาห์!$AL13,"") | R13: =IF(ISNUMBER(อัปเดตรายสัปดาห์!$Q13),อัปเดตรายสัปดาห์!$Q13,"") | S13: =IF(ISNUMBER(อัปเดตรายสัปดาห์!$R13),อัปเดตรายสัปดาห์!$R13,"") | T13: =IF(ISNUMBER(อัปเดตรายสัปดาห์!$S13),อัปเดตรายสัปดาห์!$S13,IF(อัปเดตรายสัปดาห์!$S13="Y",ASOF,"")) | U13: =IF(ISNUMBER(อัปเดตรายสัปดาห์!$T13),อัปเดตรายสัปดาห์!$T13,IF(อัปเดตรายสัปดาห์!$T13="Y",ASOF,"")) | V13: =IF(ISNUMBER(อัปเดตรายสัปดาห์!$U13),อัปเดตรายสัปดาห์!$U13,IF(อัปเดตรายสัปดาห์!$U13="Y",ASOF,"")) | W13: =IF(ISNUMBER(อัปเดตรายสัปดาห์!$N13),อัปเดตรายสัปดาห์!$N13,"") | X13: =IF(ISNUMBER(อัปเดตรายสัปดาห์!$V13),อัปเดตรายสัปดาห์!$V13,IF(AND(ISNUMBER(TCRoof!$AD$13),N(TCRoof!$AD$13)<=ASOF),TCRoof!$AD$13,"")) | Y13: =IF(N13<>"",N13,WORKDAY((ASOF+LEAD_INST+7*INT((AT13-0.01)/MAX(1,AU13)))-1,1,HOLIDAYS)) -> 46349 | Z13: =IF(O13<>"",O13,WORKDAY((MAX(AV13+7*INT((AW13-1)/MAX(1,AX13)),AV13+7*INT((AY13-1)/MAX(1,AZ13))))-1,1,HOLIDAYS)) -> 46356 | AA13: =IF(P13<>"",P13,WORKDAY((BA13+7*INT((BB13-1)/MAX(1,BC13)))-1,1,HOLIDAYS)) -> 46359 | AB13: =IF(Q13<>"",Q13,WORKDAY((MAX(AA13+BD13,ASOF+1))-1,1,HOLIDAYS)) -> 46367 | AC13: =IF(R13<>"",R13,WORKDAY((MAX(Y13,ASOF)+LAG_GRID)-1,1,HOLIDAYS)) -> 46356 | AD13: =IF(T13<>"",T13,WORKDAY((MAX(WORKDAY(MAX(AC13,N(S13)),REVIEW_WD,HOLIDAYS),ASOF+1))-1,1,HOLIDAYS)) -> 46379 | AE13: =IF(U13<>"",U13,WORKDAY((MAX(AD13,ASOF)+FEE_DAYS)-1,1,HOLIDAYS)) -> 46386 | AF13: =IF(V13<>"",V13,WORKDAY((MAX(AA13,Z13,AE13,IF(AG13="",0,AG13+REVIEW_PK2),ASOF)+LAG_INSREQ)-1,1,HOLIDAYS)) -> 46391 | AG13: =IF(M13<>"Y","",IF(W13<>"",W13,WORKDAY((MAX(Y13,ASOF)+LAG_GRID)-1,1,HOLIDAYS))) -> 46356 | AH13: =IF(X13<>"",X13,WORKDAY(AF13,INSPECT_WD,HOLIDAYS)) -> 46433 | AI13: =IF(H13="","",AB13-H13) -> -36 | AJ13: =IF(I13="","",AH13-I13) -> -3 | AK13: =IF(AND(ISNUMBER(N13),N(N13)<=ASOF),1,0)+IF(AND(ISNUMBER(O13),N(O13)<=ASOF),1,0)+IF(AND(ISNUMBER(P13),N(P13)<=ASOF),1,0)+IF(AND(ISNUMBER(Q13),N(Q13)<=ASOF),1,0)+IF(AND(ISNUMBER(R13),N(R13)<=ASOF),1,0)+IF(AND(ISNUMBER(U13),N(U13)<=ASOF),1,0)+IF(AND(ISNUMBER(X13),N(X13)<=ASOF),1,0)+IF(AND(ISNUMBER(W13),N(W13)<=ASOF),1,0) -> 0 | AL13: 8 | AM13: ='P9-006'!$J$4 -> 0 | AN13: =TRIM(IF(AND(ISNUMBER(O13),NOT(ISNUMBER(N13))),"กฟภ.ตรวจก่อนติดตั้ง, ","")&IF(AND(ISNUMBER(P13),NOT(ISNUMBER(N13))),"IEC ก่อนติดตั้ง, ","")&IF(AND(ISNUMBER(Q13),NOT(ISNUMBER(N13))),"ส่งมอบก่อนติดตั้ง, ","")&IF(AND(ISNUMBER(Q13),ISNUMBER(P13),N(Q13)<N(P13)),"ส่งมอบก่อน IEC, ","")&IF(AND(ISNUMBER(อัปเดตรายสัปดาห์!$AG13),ISNUMBER(TCRoof!$AC$13),ABS(N(อัปเดตรายสัปดาห์!$AG13)-N(TCRoof!$AC$13))>3),"IEC Excel≠แอป, ","")&IF(AND(ISNUMBER(อัปเดตรายสัปดาห์!$V13),ISNUMBER(TCRoof!$AD$13),ABS(N(อัปเดตรายสัปดาห์!$V13)-N(TCRoof!$AD$13))>3),"COD Excel≠แอป, ","")&IF(AND(ISNUMBER(อัปเดตรายสัปดาห์!$AF13),ISNUMBER(TCRoof!$AB$13),ABS(N(อัปเดตรายสัปดาห์!$AF13)-N(TCRoof!$AB$13))>3),"ติดตั้ง Excel≠แอป, ","")&IF(AND(ISNUMBER(N13),N(N13)>ASOF,OR(WEEKDAY(N(N13),2)>5,COUNTIF(HOLIDAYS,N(N13))>0)),"นัดดับไฟตรงวันหยุด, ","")&IF(AND(ISNUMBER(O13),N(O13)>ASOF,OR(WEEKDAY(N(O13),2)>5,COUNTIF(HOLIDAYS,N(O13))>0)),"นัด กฟภ.ตรงวันหยุด, ","")&IF(AND(ISNUMBER(P13),N(P13)>ASOF,OR(WEEKDAY(N(P13),2)>5,COUNTIF(HOLIDAYS,N(P13))>0)),"นัด IECตรงวันหยุด, ","")&IF(AND(ISNUMBER(X13),N(X13)>ASOF,OR(WEEKDAY(N(X13),2)>5,COUNTIF(HOLIDAYS,N(X13))>0)),"นัด Syncตรงวันหยุด, ","")) | AO13: =SUMIFS(CR_COD,CR_ST,A13,CR_STAT,"อนุมัติ")+SUMIFS(CR_COD,CR_ST,"ทั้งเฟส",CR_STAT,"อนุมัติ")+SUMIFS(CR_COD,CR_ST,"ผรม. "&L13,CR_STAT,"อนุมัติ")+SUMIFS(CR_COD,CR_ST,"เขต "&E13,CR_STAT,"อนุมัติ") -> 0 | AP13: =IF(NOT(ISNUMBER(AJ13)),"",MAX(0,AJ13-AO13)) -> 0 | AQ13: =COUNTIF(RW_ST,A13) -> 0 | AR13: =IF(ISNUMBER(TCRoof!$I$13),TCRoof!$I$13,"") | AS13: =IF(ISNUMBER(TCRoof!$H$13),TCRoof!$H$13,"") | AT13: =IF(N13<>"","",SUMIFS($F$8:$F$27,$L$8:$L$27,L13,$N$8:$N$27,"",$H$8:$H$27,"<"&H13)+SUMIFS($F$8:$F$27,$L$8:$L$27,L13,$N$8:$N$27,"",$H$8:$H$27,H13,$A$8:$A$27,"<="&A13)+SUMIFS($F$8:$F$27,$L$8:$L$27,L13,$N$8:$N$27,">"&ASOF)) -> 280.44 | AU13: =IFERROR(VLOOKUP(L13,TEAM_TBL,2,0)*VLOOKUP(L13,TEAM_TBL,3,0),150) -> 150 | AV13: =IF(O13<>"","",MAX(Y13+LAG_PEA,ASOF+LAG_PEA)) -> 46356 | AW13: =IF(O13<>"","",COUNTIFS($E$8:$E$27,E13,$AV$8:$AV$27,"<"&AV13)+COUNTIFS($E$8:$E$27,E13,$AV$8:$AV$27,AV13,$A$8:$A$27,"<"&A13)+COUNTIFS($E$8:$E$27,E13,$O$8:$O$27,">"&ASOF)+1) -> 1 | AX13: =IFERROR(VLOOKUP(E13,ZONE_TBL,2,0),CAP_PEA) -> 3 | AY13: =IF(O13<>"","",COUNTIFS($J$8:$J$27,J13,$AV$8:$AV$27,"<"&AV13)+COUNTIFS($J$8:$J$27,J13,$AV$8:$AV$27,AV13,$A$8:$A$27,"<"&A13)+COUNTIFS($J$8:$J$27,J13,$O$8:$O$27,">"&ASOF)+1) -> 1 | AZ13: =IFERROR(VLOOKUP(J13,ENG_TBL,2,0),ENG_CAP) -> 3 | BA13: =IF(P13<>"","",MAX(Z13+LAG_IEC,ASOF+1)) -> 46359 | BB13: =IF(P13<>"","",COUNTIFS($L$8:$L$27,L13,$BA$8:$BA$27,"<"&BA13)+COUNTIFS($L$8:$L$27,L13,$BA$8:$BA$27,BA13,$A$8:$A$27,"<"&A13)+COUNTIFS($L$8:$L$27,L13,$P$8:$P$27,">"&ASOF)+1) -> 1 | BC13: =IFERROR(VLOOKUP(L13,TEAM_TBL,4,0)*VLOOKUP(L13,TEAM_TBL,5,0),3) -> 3 | BD13: =IFERROR(VLOOKUP(L13,TEAM_TBL,6,0),LAG_HO) -> 7 | BE13: =IF(ISNUMBER(AW13),7*INT((AW13-1)/MAX(1,AX13)),"") -> 0 | BF13: =IF(ISNUMBER(AY13),7*INT((AY13-1)/MAX(1,AZ13)),"") -> 0 | BH13: =IF(AND($Y13<>"",$Y13>=BH$7,$Y13<BH$7+7),"I","")&IF(AND($Z13<>"",$Z13>=BH$7,$Z13<BH$7+7),"P","")&IF(AND($AA13<>"",$AA13>=BH$7,$AA13<BH$7+7),"T","")&IF(AND($AB13<>"",$AB13>=BH$7,$AB13<BH$7+7),"H","")&IF(AND($AC13<>"",$AC13>=BH$7,$AC13<BH$7+7),"G","")&IF(AND($AH13<>"",$AH13>=BH$7,$AH13<BH$7+7),"S","") | BI13: =IF(AND($Y13<>"",$Y13>=BI$7,$Y13<BI$7+7),"I","")&IF(AND($Z13<>"",$Z13>=BI$7,$Z13<BI$7+7),"P","")&IF(AND($AA13<>"",$AA13>=BI$7,$AA13<BI$7+7),"T","")&IF(AND($AB13<>"",$AB13>=BI$7,$AB13<BI$7+7),"H","")&IF(AND($AC13<>"",$AC13>=BI$7,$AC13<BI$7+7),"G","")&IF(AND($AH13<>"",$AH13>=BI$7,$AH13<BI$7+7),"S","") | BJ13: =IF(AND($Y13<>"",$Y13>=BJ$7,$Y13<BJ$7+7),"I","")&IF(AND($Z13<>"",$Z13>=BJ$7,$Z13<BJ$7+7),"P","")&IF(AND($AA13<>"",$AA13>=BJ$7,$AA13<BJ$7+7),"T","")&IF(AND($AB13<>"",$AB13>=BJ$7,$AB13<BJ$7+7),"H","")&IF(AND($AC13<>"",$AC13>=BJ$7,$AC13<BJ$7+7),"G","")&IF(AND($AH13<>"",$AH13>=BJ$7,$AH13<BJ$7+7),"S","") | BK13: =IF(AND($Y13<>"",$Y13>=BK$7,$Y13<BK$7+7),"I","")&IF(AND($Z13<>"",$Z13>=BK$7,$Z13<BK$7+7),"P","")&IF(AND($AA13<>"",$AA13>=BK$7,$AA13<BK$7+7),"T","")&IF(AND($AB13<>"",$AB13>=BK$7,$AB13<BK$7+7),"H","")&IF(AND($AC13<>"",$AC13>=BK$7,$AC13<BK$7+7),"G","")&IF(AND($AH13<>"",$AH13>=BK$7,$AH13<BK$7+7),"S","") | BL13: =IF(AND($Y13<>"",$Y13>=BL$7,$Y13<BL$7+7),"I","")&IF(AND($Z13<>"",$Z13>=BL$7,$Z13<BL$7+7),"P","")&IF(AND($AA13<>"",$AA13>=BL$7,$AA13<BL$7+7),"T","")&IF(AND($AB13<>"",$AB13>=BL$7,$AB13<BL$7+7),"H","")&IF(AND($AC13<>"",$AC13>=BL$7,$AC13<BL$7+7),"G","")&IF(AND($AH13<>"",$AH13>=BL$7,$AH13<BL$7+7),"S","") -> I | BM13: =IF(AND($Y13<>"",$Y13>=BM$7,$Y13<BM$7+7),"I","")&IF(AND($Z13<>"",$Z13>=BM$7,$Z13<BM$7+7),"P","")&IF(AND($AA13<>"",$AA13>=BM$7,$AA13<BM$7+7),"T","")&IF(AND($AB13<>"",$AB13>=BM$7,$AB13<BM$7+7),"H","")&IF(AND($AC13<>"",$AC13>=BM$7,$AC13<BM$7+7),"G","")&IF(AND($AH13<>"",$AH13>=BM$7,$AH13<BM$7+7),"S","") -> PTG | BN13: =IF(AND($Y13<>"",$Y13>=BN$7,$Y13<BN$7+7),"I","")&IF(AND($Z13<>"",$Z13>=BN$7,$Z13<BN$7+7),"P","")&IF(AND($AA13<>"",$AA13>=BN$7,$AA13<BN$7+7),"T","")&IF(AND($AB13<>"",$AB13>=BN$7,$AB13<BN$7+7),"H","")&IF(AND($AC13<>"",$AC13>=BN$7,$AC13<BN$7+7),"G","")&IF(AND($AH13<>"",$AH13>=BN$7,$AH13<BN$7+7),"S","") -> H | BO13: =IF(AND($Y13<>"",$Y13>=BO$7,$Y13<BO$7+7),"I","")&IF(AND($Z13<>"",$Z13>=BO$7,$Z13<BO$7+7),"P","")&IF(AND($AA13<>"",$AA13>=BO$7,$AA13<BO$7+7),"T","")&IF(AND($AB13<>"",$AB13>=BO$7,$AB13<BO$7+7),"H","")&IF(AND($AC13<>"",$AC13>=BO$7,$AC13<BO$7+7),"G","")&IF(AND($AH13<>"",$AH13>=BO$7,$AH13<BO$7+7),"S","") | ... DC13: =IF(AND($Y13<>"",$Y13>=DC$7,$Y13<DC$7+7),"I","")&IF(AND($Z13<>"",$Z13>=DC$7,$Z13<DC$7+7),"P","")&IF(AND($AA13<>"",$AA13>=DC$7,$AA13<DC$7+7),"T","")&IF(AND($AB13<>"",$AB13>=DC$7,$AB13<DC$7+7),"H","")&IF(AND($AC13<>"",$AC13>=DC$7,$AC13<DC$7+7),"G","")&IF(AND($AH13<>"",$AH13>=DC$7,$AH13<DC$7+7),"S","")
A14: P9-007 | B14: แม่แบบ หลังคาเมทัลชีท, กันย้อน LV, Inverter < 200 kVA | C14: (ตัวอย่าง) | D14: ตัวอย่าง | E14: ตย.07 | F14: 150.48 | G14: รอบ 9 | H14: =PROJ_START+RD_SPAN -> 46403 | I14: =H14+33 -> 46436 | J14: วศ.07 | K14: Admin | L14: 07 | M14: N | N14: =IF(ISNUMBER(อัปเดตรายสัปดาห์!$AF14),อัปเดตรายสัปดาห์!$AF14,"") | O14: =IF(ISNUMBER(อัปเดตรายสัปดาห์!$AH14),อัปเดตรายสัปดาห์!$AH14,"") | P14: =IF(ISNUMBER(อัปเดตรายสัปดาห์!$AG14),อัปเดตรายสัปดาห์!$AG14,IF(AND(ISNUMBER(TCRoof!$AC$14),N(TCRoof!$AC$14)<=ASOF),TCRoof!$AC$14,"")) | Q14: =IF(ISNUMBER(อัปเดตรายสัปดาห์!$AL14),อัปเดตรายสัปดาห์!$AL14,"") | R14: =IF(ISNUMBER(อัปเดตรายสัปดาห์!$Q14),อัปเดตรายสัปดาห์!$Q14,"") | S14: =IF(ISNUMBER(อัปเดตรายสัปดาห์!$R14),อัปเดตรายสัปดาห์!$R14,"") | T14: =IF(ISNUMBER(อัปเดตรายสัปดาห์!$S14),อัปเดตรายสัปดาห์!$S14,IF(อัปเดตรายสัปดาห์!$S14="Y",ASOF,"")) | U14: =IF(ISNUMBER(อัปเดตรายสัปดาห์!$T14),อัปเดตรายสัปดาห์!$T14,IF(อัปเดตรายสัปดาห์!$T14="Y",ASOF,"")) | V14: =IF(ISNUMBER(อัปเดตรายสัปดาห์!$U14),อัปเดตรายสัปดาห์!$U14,IF(อัปเดตรายสัปดาห์!$U14="Y",ASOF,"")) | W14: =IF(ISNUMBER(อัปเดตรายสัปดาห์!$N14),อัปเดตรายสัปดาห์!$N14,"") | X14: =IF(ISNUMBER(อัปเดตรายสัปดาห์!$V14),อัปเดตรายสัปดาห์!$V14,IF(AND(ISNUMBER(TCRoof!$AD$14),N(TCRoof!$AD$14)<=ASOF),TCRoof!$AD$14,"")) | Y14: =IF(N14<>"",N14,WORKDAY((ASOF+LEAD_INST+7*INT((AT14-0.01)/MAX(1,AU14)))-1,1,HOLIDAYS)) -> 46349 | Z14: =IF(O14<>"",O14,WORKDAY((MAX(AV14+7*INT((AW14-1)/MAX(1,AX14)),AV14+7*INT((AY14-1)/MAX(1,AZ14))))-1,1,HOLIDAYS)) -> 46356 | AA14: =IF(P14<>"",P14,WORKDAY((BA14+7*INT((BB14-1)/MAX(1,BC14)))-1,1,HOLIDAYS)) -> 46359 | AB14: =IF(Q14<>"",Q14,WORKDAY((MAX(AA14+BD14,ASOF+1))-1,1,HOLIDAYS)) -> 46367 | AC14: =IF(R14<>"",R14,WORKDAY((MAX(Y14,ASOF)+LAG_GRID)-1,1,HOLIDAYS)) -> 46356 | AD14: =IF(T14<>"",T14,WORKDAY((MAX(WORKDAY(MAX(AC14,N(S14)),REVIEW_WD,HOLIDAYS),ASOF+1))-1,1,HOLIDAYS)) -> 46379 | AE14: =IF(U14<>"",U14,WORKDAY((MAX(AD14,ASOF)+FEE_DAYS)-1,1,HOLIDAYS)) -> 46386 | AF14: =IF(V14<>"",V14,WORKDAY((MAX(AA14,Z14,AE14,IF(AG14="",0,AG14+REVIEW_PK2),ASOF)+LAG_INSREQ)-1,1,HOLIDAYS)) -> 46391 | AG14: =IF(M14<>"Y","",IF(W14<>"",W14,WORKDAY((MAX(Y14,ASOF)+LAG_GRID)-1,1,HOLIDAYS))) | AH14: =IF(X14<>"",X14,WORKDAY(AF14,INSPECT_WD,HOLIDAYS)) -> 46433 | AI14: =IF(H14="","",AB14-H14) -> -36 | AJ14: =IF(I14="","",AH14-I14) -> -3 | AK14: =IF(AND(ISNUMBER(N14),N(N14)<=ASOF),1,0)+IF(AND(ISNUMBER(O14),N(O14)<=ASOF),1,0)+IF(AND(ISNUMBER(P14),N(P14)<=ASOF),1,0)+IF(AND(ISNUMBER(Q14),N(Q14)<=ASOF),1,0)+IF(AND(ISNUMBER(R14),N(R14)<=ASOF),1,0)+IF(AND(ISNUMBER(U14),N(U14)<=ASOF),1,0)+IF(AND(ISNUMBER(X14),N(X14)<=ASOF),1,0) -> 0 | AL14: 7 | AM14: ='P9-007'!$J$4 -> 0 | AN14: =TRIM(IF(AND(ISNUMBER(O14),NOT(ISNUMBER(N14))),"กฟภ.ตรวจก่อนติดตั้ง, ","")&IF(AND(ISNUMBER(P14),NOT(ISNUMBER(N14))),"IEC ก่อนติดตั้ง, ","")&IF(AND(ISNUMBER(Q14),NOT(ISNUMBER(N14))),"ส่งมอบก่อนติดตั้ง, ","")&IF(AND(ISNUMBER(Q14),ISNUMBER(P14),N(Q14)<N(P14)),"ส่งมอบก่อน IEC, ","")&IF(AND(ISNUMBER(อัปเดตรายสัปดาห์!$AG14),ISNUMBER(TCRoof!$AC$14),ABS(N(อัปเดตรายสัปดาห์!$AG14)-N(TCRoof!$AC$14))>3),"IEC Excel≠แอป, ","")&IF(AND(ISNUMBER(อัปเดตรายสัปดาห์!$V14),ISNUMBER(TCRoof!$AD$14),ABS(N(อัปเดตรายสัปดาห์!$V14)-N(TCRoof!$AD$14))>3),"COD Excel≠แอป, ","")&IF(AND(ISNUMBER(อัปเดตรายสัปดาห์!$AF14),ISNUMBER(TCRoof!$AB$14),ABS(N(อัปเดตรายสัปดาห์!$AF14)-N(TCRoof!$AB$14))>3),"ติดตั้ง Excel≠แอป, ","")&IF(AND(ISNUMBER(N14),N(N14)>ASOF,OR(WEEKDAY(N(N14),2)>5,COUNTIF(HOLIDAYS,N(N14))>0)),"นัดดับไฟตรงวันหยุด, ","")&IF(AND(ISNUMBER(O14),N(O14)>ASOF,OR(WEEKDAY(N(O14),2)>5,COUNTIF(HOLIDAYS,N(O14))>0)),"นัด กฟภ.ตรงวันหยุด, ","")&IF(AND(ISNUMBER(P14),N(P14)>ASOF,OR(WEEKDAY(N(P14),2)>5,COUNTIF(HOLIDAYS,N(P14))>0)),"นัด IECตรงวันหยุด, ","")&IF(AND(ISNUMBER(X14),N(X14)>ASOF,OR(WEEKDAY(N(X14),2)>5,COUNTIF(HOLIDAYS,N(X14))>0)),"นัด Syncตรงวันหยุด, ","")) | AO14: =SUMIFS(CR_COD,CR_ST,A14,CR_STAT,"อนุมัติ")+SUMIFS(CR_COD,CR_ST,"ทั้งเฟส",CR_STAT,"อนุมัติ")+SUMIFS(CR_COD,CR_ST,"ผรม. "&L14,CR_STAT,"อนุมัติ")+SUMIFS(CR_COD,CR_ST,"เขต "&E14,CR_STAT,"อนุมัติ") -> 0 | AP14: =IF(NOT(ISNUMBER(AJ14)),"",MAX(0,AJ14-AO14)) -> 0 | AQ14: =COUNTIF(RW_ST,A14) -> 0 | AR14: =IF(ISNUMBER(TCRoof!$I$14),TCRoof!$I$14,"") | AS14: =IF(ISNUMBER(TCRoof!$H$14),TCRoof!$H$14,"") | AT14: =IF(N14<>"","",SUMIFS($F$8:$F$27,$L$8:$L$27,L14,$N$8:$N$27,"",$H$8:$H$27,"<"&H14)+SUMIFS($F$8:$F$27,$L$8:$L$27,L14,$N$8:$N$27,"",$H$8:$H$27,H14,$A$8:$A$27,"<="&A14)+SUMIFS($F$8:$F$27,$L$8:$L$27,L14,$N$8:$N$27,">"&ASOF)) -> 150.48 | AU14: =IFERROR(VLOOKUP(L14,TEAM_TBL,2,0)*VLOOKUP(L14,TEAM_TBL,3,0),150) -> 150 | AV14: =IF(O14<>"","",MAX(Y14+LAG_PEA,ASOF+LAG_PEA)) -> 46356 | AW14: =IF(O14<>"","",COUNTIFS($E$8:$E$27,E14,$AV$8:$AV$27,"<"&AV14)+COUNTIFS($E$8:$E$27,E14,$AV$8:$AV$27,AV14,$A$8:$A$27,"<"&A14)+COUNTIFS($E$8:$E$27,E14,$O$8:$O$27,">"&ASOF)+1) -> 1 | AX14: =IFERROR(VLOOKUP(E14,ZONE_TBL,2,0),CAP_PEA) -> 3 | AY14: =IF(O14<>"","",COUNTIFS($J$8:$J$27,J14,$AV$8:$AV$27,"<"&AV14)+COUNTIFS($J$8:$J$27,J14,$AV$8:$AV$27,AV14,$A$8:$A$27,"<"&A14)+COUNTIFS($J$8:$J$27,J14,$O$8:$O$27,">"&ASOF)+1) -> 1 | AZ14: =IFERROR(VLOOKUP(J14,ENG_TBL,2,0),ENG_CAP) -> 3 | BA14: =IF(P14<>"","",MAX(Z14+LAG_IEC,ASOF+1)) -> 46359 | BB14: =IF(P14<>"","",COUNTIFS($L$8:$L$27,L14,$BA$8:$BA$27,"<"&BA14)+COUNTIFS($L$8:$L$27,L14,$BA$8:$BA$27,BA14,$A$8:$A$27,"<"&A14)+COUNTIFS($L$8:$L$27,L14,$P$8:$P$27,">"&ASOF)+1) -> 1 | BC14: =IFERROR(VLOOKUP(L14,TEAM_TBL,4,0)*VLOOKUP(L14,TEAM_TBL,5,0),3) -> 3 | BD14: =IFERROR(VLOOKUP(L14,TEAM_TBL,6,0),LAG_HO) -> 7 | BE14: =IF(ISNUMBER(AW14),7*INT((AW14-1)/MAX(1,AX14)),"") -> 0 | BF14: =IF(ISNUMBER(AY14),7*INT((AY14-1)/MAX(1,AZ14)),"") -> 0 | BH14: =IF(AND($Y14<>"",$Y14>=BH$7,$Y14<BH$7+7),"I","")&IF(AND($Z14<>"",$Z14>=BH$7,$Z14<BH$7+7),"P","")&IF(AND($AA14<>"",$AA14>=BH$7,$AA14<BH$7+7),"T","")&IF(AND($AB14<>"",$AB14>=BH$7,$AB14<BH$7+7),"H","")&IF(AND($AC14<>"",$AC14>=BH$7,$AC14<BH$7+7),"G","")&IF(AND($AH14<>"",$AH14>=BH$7,$AH14<BH$7+7),"S","") | BI14: =IF(AND($Y14<>"",$Y14>=BI$7,$Y14<BI$7+7),"I","")&IF(AND($Z14<>"",$Z14>=BI$7,$Z14<BI$7+7),"P","")&IF(AND($AA14<>"",$AA14>=BI$7,$AA14<BI$7+7),"T","")&IF(AND($AB14<>"",$AB14>=BI$7,$AB14<BI$7+7),"H","")&IF(AND($AC14<>"",$AC14>=BI$7,$AC14<BI$7+7),"G","")&IF(AND($AH14<>"",$AH14>=BI$7,$AH14<BI$7+7),"S","") | BJ14: =IF(AND($Y14<>"",$Y14>=BJ$7,$Y14<BJ$7+7),"I","")&IF(AND($Z14<>"",$Z14>=BJ$7,$Z14<BJ$7+7),"P","")&IF(AND($AA14<>"",$AA14>=BJ$7,$AA14<BJ$7+7),"T","")&IF(AND($AB14<>"",$AB14>=BJ$7,$AB14<BJ$7+7),"H","")&IF(AND($AC14<>"",$AC14>=BJ$7,$AC14<BJ$7+7),"G","")&IF(AND($AH14<>"",$AH14>=BJ$7,$AH14<BJ$7+7),"S","") | BK14: =IF(AND($Y14<>"",$Y14>=BK$7,$Y14<BK$7+7),"I","")&IF(AND($Z14<>"",$Z14>=BK$7,$Z14<BK$7+7),"P","")&IF(AND($AA14<>"",$AA14>=BK$7,$AA14<BK$7+7),"T","")&IF(AND($AB14<>"",$AB14>=BK$7,$AB14<BK$7+7),"H","")&IF(AND($AC14<>"",$AC14>=BK$7,$AC14<BK$7+7),"G","")&IF(AND($AH14<>"",$AH14>=BK$7,$AH14<BK$7+7),"S","") | BL14: =IF(AND($Y14<>"",$Y14>=BL$7,$Y14<BL$7+7),"I","")&IF(AND($Z14<>"",$Z14>=BL$7,$Z14<BL$7+7),"P","")&IF(AND($AA14<>"",$AA14>=BL$7,$AA14<BL$7+7),"T","")&IF(AND($AB14<>"",$AB14>=BL$7,$AB14<BL$7+7),"H","")&IF(AND($AC14<>"",$AC14>=BL$7,$AC14<BL$7+7),"G","")&IF(AND($AH14<>"",$AH14>=BL$7,$AH14<BL$7+7),"S","") -> I | BM14: =IF(AND($Y14<>"",$Y14>=BM$7,$Y14<BM$7+7),"I","")&IF(AND($Z14<>"",$Z14>=BM$7,$Z14<BM$7+7),"P","")&IF(AND($AA14<>"",$AA14>=BM$7,$AA14<BM$7+7),"T","")&IF(AND($AB14<>"",$AB14>=BM$7,$AB14<BM$7+7),"H","")&IF(AND($AC14<>"",$AC14>=BM$7,$AC14<BM$7+7),"G","")&IF(AND($AH14<>"",$AH14>=BM$7,$AH14<BM$7+7),"S","") -> PTG | BN14: =IF(AND($Y14<>"",$Y14>=BN$7,$Y14<BN$7+7),"I","")&IF(AND($Z14<>"",$Z14>=BN$7,$Z14<BN$7+7),"P","")&IF(AND($AA14<>"",$AA14>=BN$7,$AA14<BN$7+7),"T","")&IF(AND($AB14<>"",$AB14>=BN$7,$AB14<BN$7+7),"H","")&IF(AND($AC14<>"",$AC14>=BN$7,$AC14<BN$7+7),"G","")&IF(AND($AH14<>"",$AH14>=BN$7,$AH14<BN$7+7),"S","") -> H | BO14: =IF(AND($Y14<>"",$Y14>=BO$7,$Y14<BO$7+7),"I","")&IF(AND($Z14<>"",$Z14>=BO$7,$Z14<BO$7+7),"P","")&IF(AND($AA14<>"",$AA14>=BO$7,$AA14<BO$7+7),"T","")&IF(AND($AB14<>"",$AB14>=BO$7,$AB14<BO$7+7),"H","")&IF(AND($AC14<>"",$AC14>=BO$7,$AC14<BO$7+7),"G","")&IF(AND($AH14<>"",$AH14>=BO$7,$AH14<BO$7+7),"S","") | ... DC14: =IF(AND($Y14<>"",$Y14>=DC$7,$Y14<DC$7+7),"I","")&IF(AND($Z14<>"",$Z14>=DC$7,$Z14<DC$7+7),"P","")&IF(AND($AA14<>"",$AA14>=DC$7,$AA14<DC$7+7),"T","")&IF(AND($AB14<>"",$AB14>=DC$7,$AB14<DC$7+7),"H","")&IF(AND($AC14<>"",$AC14>=DC$7,$AC14<DC$7+7),"G","")&IF(AND($AH14<>"",$AH14>=DC$7,$AH14<DC$7+7),"S","")
A15: P9-008 | B15: แม่แบบ หลังคาเมทัลชีท, กันย้อน LV, Inverter ≥ 200 kVA | C15: (ตัวอย่าง) | D15: ตัวอย่าง | E15: ตย.08 | F15: 280.44 | G15: รอบ 9 | H15: =PROJ_START+RD_SPAN -> 46403 | I15: =H15+33 -> 46436 | J15: วศ.08 | K15: Admin | L15: 08 | M15: Y | N15: =IF(ISNUMBER(อัปเดตรายสัปดาห์!$AF15),อัปเดตรายสัปดาห์!$AF15,"") | O15: =IF(ISNUMBER(อัปเดตรายสัปดาห์!$AH15),อัปเดตรายสัปดาห์!$AH15,"") | P15: =IF(ISNUMBER(อัปเดตรายสัปดาห์!$AG15),อัปเดตรายสัปดาห์!$AG15,IF(AND(ISNUMBER(TCRoof!$AC$15),N(TCRoof!$AC$15)<=ASOF),TCRoof!$AC$15,"")) | Q15: =IF(ISNUMBER(อัปเดตรายสัปดาห์!$AL15),อัปเดตรายสัปดาห์!$AL15,"") | R15: =IF(ISNUMBER(อัปเดตรายสัปดาห์!$Q15),อัปเดตรายสัปดาห์!$Q15,"") | S15: =IF(ISNUMBER(อัปเดตรายสัปดาห์!$R15),อัปเดตรายสัปดาห์!$R15,"") | T15: =IF(ISNUMBER(อัปเดตรายสัปดาห์!$S15),อัปเดตรายสัปดาห์!$S15,IF(อัปเดตรายสัปดาห์!$S15="Y",ASOF,"")) | U15: =IF(ISNUMBER(อัปเดตรายสัปดาห์!$T15),อัปเดตรายสัปดาห์!$T15,IF(อัปเดตรายสัปดาห์!$T15="Y",ASOF,"")) | V15: =IF(ISNUMBER(อัปเดตรายสัปดาห์!$U15),อัปเดตรายสัปดาห์!$U15,IF(อัปเดตรายสัปดาห์!$U15="Y",ASOF,"")) | W15: =IF(ISNUMBER(อัปเดตรายสัปดาห์!$N15),อัปเดตรายสัปดาห์!$N15,"") | X15: =IF(ISNUMBER(อัปเดตรายสัปดาห์!$V15),อัปเดตรายสัปดาห์!$V15,IF(AND(ISNUMBER(TCRoof!$AD$15),N(TCRoof!$AD$15)<=ASOF),TCRoof!$AD$15,"")) | Y15: =IF(N15<>"",N15,WORKDAY((ASOF+LEAD_INST+7*INT((AT15-0.01)/MAX(1,AU15)))-1,1,HOLIDAYS)) -> 46349 | Z15: =IF(O15<>"",O15,WORKDAY((MAX(AV15+7*INT((AW15-1)/MAX(1,AX15)),AV15+7*INT((AY15-1)/MAX(1,AZ15))))-1,1,HOLIDAYS)) -> 46356 | AA15: =IF(P15<>"",P15,WORKDAY((BA15+7*INT((BB15-1)/MAX(1,BC15)))-1,1,HOLIDAYS)) -> 46359 | AB15: =IF(Q15<>"",Q15,WORKDAY((MAX(AA15+BD15,ASOF+1))-1,1,HOLIDAYS)) -> 46367 | AC15: =IF(R15<>"",R15,WORKDAY((MAX(Y15,ASOF)+LAG_GRID)-1,1,HOLIDAYS)) -> 46356 | AD15: =IF(T15<>"",T15,WORKDAY((MAX(WORKDAY(MAX(AC15,N(S15)),REVIEW_WD,HOLIDAYS),ASOF+1))-1,1,HOLIDAYS)) -> 46379 | AE15: =IF(U15<>"",U15,WORKDAY((MAX(AD15,ASOF)+FEE_DAYS)-1,1,HOLIDAYS)) -> 46386 | AF15: =IF(V15<>"",V15,WORKDAY((MAX(AA15,Z15,AE15,IF(AG15="",0,AG15+REVIEW_PK2),ASOF)+LAG_INSREQ)-1,1,HOLIDAYS)) -> 46391 | AG15: =IF(M15<>"Y","",IF(W15<>"",W15,WORKDAY((MAX(Y15,ASOF)+LAG_GRID)-1,1,HOLIDAYS))) -> 46356 | AH15: =IF(X15<>"",X15,WORKDAY(AF15,INSPECT_WD,HOLIDAYS)) -> 46433 | AI15: =IF(H15="","",AB15-H15) -> -36 | AJ15: =IF(I15="","",AH15-I15) -> -3 | AK15: =IF(AND(ISNUMBER(N15),N(N15)<=ASOF),1,0)+IF(AND(ISNUMBER(O15),N(O15)<=ASOF),1,0)+IF(AND(ISNUMBER(P15),N(P15)<=ASOF),1,0)+IF(AND(ISNUMBER(Q15),N(Q15)<=ASOF),1,0)+IF(AND(ISNUMBER(R15),N(R15)<=ASOF),1,0)+IF(AND(ISNUMBER(U15),N(U15)<=ASOF),1,0)+IF(AND(ISNUMBER(X15),N(X15)<=ASOF),1,0)+IF(AND(ISNUMBER(W15),N(W15)<=ASOF),1,0) -> 0 | AL15: 8 | AM15: ='P9-008'!$J$4 -> 0 | AN15: =TRIM(IF(AND(ISNUMBER(O15),NOT(ISNUMBER(N15))),"กฟภ.ตรวจก่อนติดตั้ง, ","")&IF(AND(ISNUMBER(P15),NOT(ISNUMBER(N15))),"IEC ก่อนติดตั้ง, ","")&IF(AND(ISNUMBER(Q15),NOT(ISNUMBER(N15))),"ส่งมอบก่อนติดตั้ง, ","")&IF(AND(ISNUMBER(Q15),ISNUMBER(P15),N(Q15)<N(P15)),"ส่งมอบก่อน IEC, ","")&IF(AND(ISNUMBER(อัปเดตรายสัปดาห์!$AG15),ISNUMBER(TCRoof!$AC$15),ABS(N(อัปเดตรายสัปดาห์!$AG15)-N(TCRoof!$AC$15))>3),"IEC Excel≠แอป, ","")&IF(AND(ISNUMBER(อัปเดตรายสัปดาห์!$V15),ISNUMBER(TCRoof!$AD$15),ABS(N(อัปเดตรายสัปดาห์!$V15)-N(TCRoof!$AD$15))>3),"COD Excel≠แอป, ","")&IF(AND(ISNUMBER(อัปเดตรายสัปดาห์!$AF15),ISNUMBER(TCRoof!$AB$15),ABS(N(อัปเดตรายสัปดาห์!$AF15)-N(TCRoof!$AB$15))>3),"ติดตั้ง Excel≠แอป, ","")&IF(AND(ISNUMBER(N15),N(N15)>ASOF,OR(WEEKDAY(N(N15),2)>5,COUNTIF(HOLIDAYS,N(N15))>0)),"นัดดับไฟตรงวันหยุด, ","")&IF(AND(ISNUMBER(O15),N(O15)>ASOF,OR(WEEKDAY(N(O15),2)>5,COUNTIF(HOLIDAYS,N(O15))>0)),"นัด กฟภ.ตรงวันหยุด, ","")&IF(AND(ISNUMBER(P15),N(P15)>ASOF,OR(WEEKDAY(N(P15),2)>5,COUNTIF(HOLIDAYS,N(P15))>0)),"นัด IECตรงวันหยุด, ","")&IF(AND(ISNUMBER(X15),N(X15)>ASOF,OR(WEEKDAY(N(X15),2)>5,COUNTIF(HOLIDAYS,N(X15))>0)),"นัด Syncตรงวันหยุด, ","")) | AO15: =SUMIFS(CR_COD,CR_ST,A15,CR_STAT,"อนุมัติ")+SUMIFS(CR_COD,CR_ST,"ทั้งเฟส",CR_STAT,"อนุมัติ")+SUMIFS(CR_COD,CR_ST,"ผรม. "&L15,CR_STAT,"อนุมัติ")+SUMIFS(CR_COD,CR_ST,"เขต "&E15,CR_STAT,"อนุมัติ") -> 0 | AP15: =IF(NOT(ISNUMBER(AJ15)),"",MAX(0,AJ15-AO15)) -> 0 | AQ15: =COUNTIF(RW_ST,A15) -> 0 | AR15: =IF(ISNUMBER(TCRoof!$I$15),TCRoof!$I$15,"") | AS15: =IF(ISNUMBER(TCRoof!$H$15),TCRoof!$H$15,"") | AT15: =IF(N15<>"","",SUMIFS($F$8:$F$27,$L$8:$L$27,L15,$N$8:$N$27,"",$H$8:$H$27,"<"&H15)+SUMIFS($F$8:$F$27,$L$8:$L$27,L15,$N$8:$N$27,"",$H$8:$H$27,H15,$A$8:$A$27,"<="&A15)+SUMIFS($F$8:$F$27,$L$8:$L$27,L15,$N$8:$N$27,">"&ASOF)) -> 280.44 | AU15: =IFERROR(VLOOKUP(L15,TEAM_TBL,2,0)*VLOOKUP(L15,TEAM_TBL,3,0),150) -> 150 | AV15: =IF(O15<>"","",MAX(Y15+LAG_PEA,ASOF+LAG_PEA)) -> 46356 | AW15: =IF(O15<>"","",COUNTIFS($E$8:$E$27,E15,$AV$8:$AV$27,"<"&AV15)+COUNTIFS($E$8:$E$27,E15,$AV$8:$AV$27,AV15,$A$8:$A$27,"<"&A15)+COUNTIFS($E$8:$E$27,E15,$O$8:$O$27,">"&ASOF)+1) -> 1 | AX15: =IFERROR(VLOOKUP(E15,ZONE_TBL,2,0),CAP_PEA) -> 3 | AY15: =IF(O15<>"","",COUNTIFS($J$8:$J$27,J15,$AV$8:$AV$27,"<"&AV15)+COUNTIFS($J$8:$J$27,J15,$AV$8:$AV$27,AV15,$A$8:$A$27,"<"&A15)+COUNTIFS($J$8:$J$27,J15,$O$8:$O$27,">"&ASOF)+1) -> 1 | AZ15: =IFERROR(VLOOKUP(J15,ENG_TBL,2,0),ENG_CAP) -> 3 | BA15: =IF(P15<>"","",MAX(Z15+LAG_IEC,ASOF+1)) -> 46359 | BB15: =IF(P15<>"","",COUNTIFS($L$8:$L$27,L15,$BA$8:$BA$27,"<"&BA15)+COUNTIFS($L$8:$L$27,L15,$BA$8:$BA$27,BA15,$A$8:$A$27,"<"&A15)+COUNTIFS($L$8:$L$27,L15,$P$8:$P$27,">"&ASOF)+1) -> 1 | BC15: =IFERROR(VLOOKUP(L15,TEAM_TBL,4,0)*VLOOKUP(L15,TEAM_TBL,5,0),3) -> 3 | BD15: =IFERROR(VLOOKUP(L15,TEAM_TBL,6,0),LAG_HO) -> 7 | BE15: =IF(ISNUMBER(AW15),7*INT((AW15-1)/MAX(1,AX15)),"") -> 0 | BF15: =IF(ISNUMBER(AY15),7*INT((AY15-1)/MAX(1,AZ15)),"") -> 0 | BH15: =IF(AND($Y15<>"",$Y15>=BH$7,$Y15<BH$7+7),"I","")&IF(AND($Z15<>"",$Z15>=BH$7,$Z15<BH$7+7),"P","")&IF(AND($AA15<>"",$AA15>=BH$7,$AA15<BH$7+7),"T","")&IF(AND($AB15<>"",$AB15>=BH$7,$AB15<BH$7+7),"H","")&IF(AND($AC15<>"",$AC15>=BH$7,$AC15<BH$7+7),"G","")&IF(AND($AH15<>"",$AH15>=BH$7,$AH15<BH$7+7),"S","") | BI15: =IF(AND($Y15<>"",$Y15>=BI$7,$Y15<BI$7+7),"I","")&IF(AND($Z15<>"",$Z15>=BI$7,$Z15<BI$7+7),"P","")&IF(AND($AA15<>"",$AA15>=BI$7,$AA15<BI$7+7),"T","")&IF(AND($AB15<>"",$AB15>=BI$7,$AB15<BI$7+7),"H","")&IF(AND($AC15<>"",$AC15>=BI$7,$AC15<BI$7+7),"G","")&IF(AND($AH15<>"",$AH15>=BI$7,$AH15<BI$7+7),"S","") | BJ15: =IF(AND($Y15<>"",$Y15>=BJ$7,$Y15<BJ$7+7),"I","")&IF(AND($Z15<>"",$Z15>=BJ$7,$Z15<BJ$7+7),"P","")&IF(AND($AA15<>"",$AA15>=BJ$7,$AA15<BJ$7+7),"T","")&IF(AND($AB15<>"",$AB15>=BJ$7,$AB15<BJ$7+7),"H","")&IF(AND($AC15<>"",$AC15>=BJ$7,$AC15<BJ$7+7),"G","")&IF(AND($AH15<>"",$AH15>=BJ$7,$AH15<BJ$7+7),"S","") | BK15: =IF(AND($Y15<>"",$Y15>=BK$7,$Y15<BK$7+7),"I","")&IF(AND($Z15<>"",$Z15>=BK$7,$Z15<BK$7+7),"P","")&IF(AND($AA15<>"",$AA15>=BK$7,$AA15<BK$7+7),"T","")&IF(AND($AB15<>"",$AB15>=BK$7,$AB15<BK$7+7),"H","")&IF(AND($AC15<>"",$AC15>=BK$7,$AC15<BK$7+7),"G","")&IF(AND($AH15<>"",$AH15>=BK$7,$AH15<BK$7+7),"S","") | BL15: =IF(AND($Y15<>"",$Y15>=BL$7,$Y15<BL$7+7),"I","")&IF(AND($Z15<>"",$Z15>=BL$7,$Z15<BL$7+7),"P","")&IF(AND($AA15<>"",$AA15>=BL$7,$AA15<BL$7+7),"T","")&IF(AND($AB15<>"",$AB15>=BL$7,$AB15<BL$7+7),"H","")&IF(AND($AC15<>"",$AC15>=BL$7,$AC15<BL$7+7),"G","")&IF(AND($AH15<>"",$AH15>=BL$7,$AH15<BL$7+7),"S","") -> I | BM15: =IF(AND($Y15<>"",$Y15>=BM$7,$Y15<BM$7+7),"I","")&IF(AND($Z15<>"",$Z15>=BM$7,$Z15<BM$7+7),"P","")&IF(AND($AA15<>"",$AA15>=BM$7,$AA15<BM$7+7),"T","")&IF(AND($AB15<>"",$AB15>=BM$7,$AB15<BM$7+7),"H","")&IF(AND($AC15<>"",$AC15>=BM$7,$AC15<BM$7+7),"G","")&IF(AND($AH15<>"",$AH15>=BM$7,$AH15<BM$7+7),"S","") -> PTG | BN15: =IF(AND($Y15<>"",$Y15>=BN$7,$Y15<BN$7+7),"I","")&IF(AND($Z15<>"",$Z15>=BN$7,$Z15<BN$7+7),"P","")&IF(AND($AA15<>"",$AA15>=BN$7,$AA15<BN$7+7),"T","")&IF(AND($AB15<>"",$AB15>=BN$7,$AB15<BN$7+7),"H","")&IF(AND($AC15<>"",$AC15>=BN$7,$AC15<BN$7+7),"G","")&IF(AND($AH15<>"",$AH15>=BN$7,$AH15<BN$7+7),"S","") -> H | BO15: =IF(AND($Y15<>"",$Y15>=BO$7,$Y15<BO$7+7),"I","")&IF(AND($Z15<>"",$Z15>=BO$7,$Z15<BO$7+7),"P","")&IF(AND($AA15<>"",$AA15>=BO$7,$AA15<BO$7+7),"T","")&IF(AND($AB15<>"",$AB15>=BO$7,$AB15<BO$7+7),"H","")&IF(AND($AC15<>"",$AC15>=BO$7,$AC15<BO$7+7),"G","")&IF(AND($AH15<>"",$AH15>=BO$7,$AH15<BO$7+7),"S","") | ... DC15: =IF(AND($Y15<>"",$Y15>=DC$7,$Y15<DC$7+7),"I","")&IF(AND($Z15<>"",$Z15>=DC$7,$Z15<DC$7+7),"P","")&IF(AND($AA15<>"",$AA15>=DC$7,$AA15<DC$7+7),"T","")&IF(AND($AB15<>"",$AB15>=DC$7,$AB15<DC$7+7),"H","")&IF(AND($AC15<>"",$AC15>=DC$7,$AC15<DC$7+7),"G","")&IF(AND($AH15<>"",$AH15>=DC$7,$AH15<DC$7+7),"S","")
A16: P9-009 | B16: แม่แบบ ถังน้ำใส, กันย้อน HV, Inverter < 200 kVA | C16: (ตัวอย่าง) | D16: ตัวอย่าง | E16: ตย.09 | F16: 150.48 | G16: รอบ 9 | H16: =PROJ_START+RD_SPAN -> 46403 | I16: =H16+33 -> 46436 | J16: วศ.09 | K16: Admin | L16: 09 | M16: N | N16: =IF(ISNUMBER(อัปเดตรายสัปดาห์!$AF16),อัปเดตรายสัปดาห์!$AF16,"") | O16: =IF(ISNUMBER(อัปเดตรายสัปดาห์!$AH16),อัปเดตรายสัปดาห์!$AH16,"") | P16: =IF(ISNUMBER(อัปเดตรายสัปดาห์!$AG16),อัปเดตรายสัปดาห์!$AG16,IF(AND(ISNUMBER(TCRoof!$AC$16),N(TCRoof!$AC$16)<=ASOF),TCRoof!$AC$16,"")) | Q16: =IF(ISNUMBER(อัปเดตรายสัปดาห์!$AL16),อัปเดตรายสัปดาห์!$AL16,"") | R16: =IF(ISNUMBER(อัปเดตรายสัปดาห์!$Q16),อัปเดตรายสัปดาห์!$Q16,"") | S16: =IF(ISNUMBER(อัปเดตรายสัปดาห์!$R16),อัปเดตรายสัปดาห์!$R16,"") | T16: =IF(ISNUMBER(อัปเดตรายสัปดาห์!$S16),อัปเดตรายสัปดาห์!$S16,IF(อัปเดตรายสัปดาห์!$S16="Y",ASOF,"")) | U16: =IF(ISNUMBER(อัปเดตรายสัปดาห์!$T16),อัปเดตรายสัปดาห์!$T16,IF(อัปเดตรายสัปดาห์!$T16="Y",ASOF,"")) | V16: =IF(ISNUMBER(อัปเดตรายสัปดาห์!$U16),อัปเดตรายสัปดาห์!$U16,IF(อัปเดตรายสัปดาห์!$U16="Y",ASOF,"")) | W16: =IF(ISNUMBER(อัปเดตรายสัปดาห์!$N16),อัปเดตรายสัปดาห์!$N16,"") | X16: =IF(ISNUMBER(อัปเดตรายสัปดาห์!$V16),อัปเดตรายสัปดาห์!$V16,IF(AND(ISNUMBER(TCRoof!$AD$16),N(TCRoof!$AD$16)<=ASOF),TCRoof!$AD$16,"")) | Y16: =IF(N16<>"",N16,WORKDAY((ASOF+LEAD_INST+7*INT((AT16-0.01)/MAX(1,AU16)))-1,1,HOLIDAYS)) -> 46349 | Z16: =IF(O16<>"",O16,WORKDAY((MAX(AV16+7*INT((AW16-1)/MAX(1,AX16)),AV16+7*INT((AY16-1)/MAX(1,AZ16))))-1,1,HOLIDAYS)) -> 46356 | AA16: =IF(P16<>"",P16,WORKDAY((BA16+7*INT((BB16-1)/MAX(1,BC16)))-1,1,HOLIDAYS)) -> 46359 | AB16: =IF(Q16<>"",Q16,WORKDAY((MAX(AA16+BD16,ASOF+1))-1,1,HOLIDAYS)) -> 46367 | AC16: =IF(R16<>"",R16,WORKDAY((MAX(Y16,ASOF)+LAG_GRID)-1,1,HOLIDAYS)) -> 46356 | AD16: =IF(T16<>"",T16,WORKDAY((MAX(WORKDAY(MAX(AC16,N(S16)),REVIEW_WD,HOLIDAYS),ASOF+1))-1,1,HOLIDAYS)) -> 46379 | AE16: =IF(U16<>"",U16,WORKDAY((MAX(AD16,ASOF)+FEE_DAYS)-1,1,HOLIDAYS)) -> 46386 | AF16: =IF(V16<>"",V16,WORKDAY((MAX(AA16,Z16,AE16,IF(AG16="",0,AG16+REVIEW_PK2),ASOF)+LAG_INSREQ)-1,1,HOLIDAYS)) -> 46391 | AG16: =IF(M16<>"Y","",IF(W16<>"",W16,WORKDAY((MAX(Y16,ASOF)+LAG_GRID)-1,1,HOLIDAYS))) | AH16: =IF(X16<>"",X16,WORKDAY(AF16,INSPECT_WD,HOLIDAYS)) -> 46433 | AI16: =IF(H16="","",AB16-H16) -> -36 | AJ16: =IF(I16="","",AH16-I16) -> -3 | AK16: =IF(AND(ISNUMBER(N16),N(N16)<=ASOF),1,0)+IF(AND(ISNUMBER(O16),N(O16)<=ASOF),1,0)+IF(AND(ISNUMBER(P16),N(P16)<=ASOF),1,0)+IF(AND(ISNUMBER(Q16),N(Q16)<=ASOF),1,0)+IF(AND(ISNUMBER(R16),N(R16)<=ASOF),1,0)+IF(AND(ISNUMBER(U16),N(U16)<=ASOF),1,0)+IF(AND(ISNUMBER(X16),N(X16)<=ASOF),1,0) -> 0 | AL16: 7 | AM16: ='P9-009'!$J$4 -> 0 | AN16: =TRIM(IF(AND(ISNUMBER(O16),NOT(ISNUMBER(N16))),"กฟภ.ตรวจก่อนติดตั้ง, ","")&IF(AND(ISNUMBER(P16),NOT(ISNUMBER(N16))),"IEC ก่อนติดตั้ง, ","")&IF(AND(ISNUMBER(Q16),NOT(ISNUMBER(N16))),"ส่งมอบก่อนติดตั้ง, ","")&IF(AND(ISNUMBER(Q16),ISNUMBER(P16),N(Q16)<N(P16)),"ส่งมอบก่อน IEC, ","")&IF(AND(ISNUMBER(อัปเดตรายสัปดาห์!$AG16),ISNUMBER(TCRoof!$AC$16),ABS(N(อัปเดตรายสัปดาห์!$AG16)-N(TCRoof!$AC$16))>3),"IEC Excel≠แอป, ","")&IF(AND(ISNUMBER(อัปเดตรายสัปดาห์!$V16),ISNUMBER(TCRoof!$AD$16),ABS(N(อัปเดตรายสัปดาห์!$V16)-N(TCRoof!$AD$16))>3),"COD Excel≠แอป, ","")&IF(AND(ISNUMBER(อัปเดตรายสัปดาห์!$AF16),ISNUMBER(TCRoof!$AB$16),ABS(N(อัปเดตรายสัปดาห์!$AF16)-N(TCRoof!$AB$16))>3),"ติดตั้ง Excel≠แอป, ","")&IF(AND(ISNUMBER(N16),N(N16)>ASOF,OR(WEEKDAY(N(N16),2)>5,COUNTIF(HOLIDAYS,N(N16))>0)),"นัดดับไฟตรงวันหยุด, ","")&IF(AND(ISNUMBER(O16),N(O16)>ASOF,OR(WEEKDAY(N(O16),2)>5,COUNTIF(HOLIDAYS,N(O16))>0)),"นัด กฟภ.ตรงวันหยุด, ","")&IF(AND(ISNUMBER(P16),N(P16)>ASOF,OR(WEEKDAY(N(P16),2)>5,COUNTIF(HOLIDAYS,N(P16))>0)),"นัด IECตรงวันหยุด, ","")&IF(AND(ISNUMBER(X16),N(X16)>ASOF,OR(WEEKDAY(N(X16),2)>5,COUNTIF(HOLIDAYS,N(X16))>0)),"นัด Syncตรงวันหยุด, ","")) | AO16: =SUMIFS(CR_COD,CR_ST,A16,CR_STAT,"อนุมัติ")+SUMIFS(CR_COD,CR_ST,"ทั้งเฟส",CR_STAT,"อนุมัติ")+SUMIFS(CR_COD,CR_ST,"ผรม. "&L16,CR_STAT,"อนุมัติ")+SUMIFS(CR_COD,CR_ST,"เขต "&E16,CR_STAT,"อนุมัติ") -> 0 | AP16: =IF(NOT(ISNUMBER(AJ16)),"",MAX(0,AJ16-AO16)) -> 0 | AQ16: =COUNTIF(RW_ST,A16) -> 0 | AR16: =IF(ISNUMBER(TCRoof!$I$16),TCRoof!$I$16,"") | AS16: =IF(ISNUMBER(TCRoof!$H$16),TCRoof!$H$16,"") | AT16: =IF(N16<>"","",SUMIFS($F$8:$F$27,$L$8:$L$27,L16,$N$8:$N$27,"",$H$8:$H$27,"<"&H16)+SUMIFS($F$8:$F$27,$L$8:$L$27,L16,$N$8:$N$27,"",$H$8:$H$27,H16,$A$8:$A$27,"<="&A16)+SUMIFS($F$8:$F$27,$L$8:$L$27,L16,$N$8:$N$27,">"&ASOF)) -> 150.48 | AU16: =IFERROR(VLOOKUP(L16,TEAM_TBL,2,0)*VLOOKUP(L16,TEAM_TBL,3,0),150) -> 150 | AV16: =IF(O16<>"","",MAX(Y16+LAG_PEA,ASOF+LAG_PEA)) -> 46356 | AW16: =IF(O16<>"","",COUNTIFS($E$8:$E$27,E16,$AV$8:$AV$27,"<"&AV16)+COUNTIFS($E$8:$E$27,E16,$AV$8:$AV$27,AV16,$A$8:$A$27,"<"&A16)+COUNTIFS($E$8:$E$27,E16,$O$8:$O$27,">"&ASOF)+1) -> 1 | AX16: =IFERROR(VLOOKUP(E16,ZONE_TBL,2,0),CAP_PEA) -> 3 | AY16: =IF(O16<>"","",COUNTIFS($J$8:$J$27,J16,$AV$8:$AV$27,"<"&AV16)+COUNTIFS($J$8:$J$27,J16,$AV$8:$AV$27,AV16,$A$8:$A$27,"<"&A16)+COUNTIFS($J$8:$J$27,J16,$O$8:$O$27,">"&ASOF)+1) -> 1 | AZ16: =IFERROR(VLOOKUP(J16,ENG_TBL,2,0),ENG_CAP) -> 3 | BA16: =IF(P16<>"","",MAX(Z16+LAG_IEC,ASOF+1)) -> 46359 | BB16: =IF(P16<>"","",COUNTIFS($L$8:$L$27,L16,$BA$8:$BA$27,"<"&BA16)+COUNTIFS($L$8:$L$27,L16,$BA$8:$BA$27,BA16,$A$8:$A$27,"<"&A16)+COUNTIFS($L$8:$L$27,L16,$P$8:$P$27,">"&ASOF)+1) -> 1 | BC16: =IFERROR(VLOOKUP(L16,TEAM_TBL,4,0)*VLOOKUP(L16,TEAM_TBL,5,0),3) -> 3 | BD16: =IFERROR(VLOOKUP(L16,TEAM_TBL,6,0),LAG_HO) -> 7 | BE16: =IF(ISNUMBER(AW16),7*INT((AW16-1)/MAX(1,AX16)),"") -> 0 | BF16: =IF(ISNUMBER(AY16),7*INT((AY16-1)/MAX(1,AZ16)),"") -> 0 | BH16: =IF(AND($Y16<>"",$Y16>=BH$7,$Y16<BH$7+7),"I","")&IF(AND($Z16<>"",$Z16>=BH$7,$Z16<BH$7+7),"P","")&IF(AND($AA16<>"",$AA16>=BH$7,$AA16<BH$7+7),"T","")&IF(AND($AB16<>"",$AB16>=BH$7,$AB16<BH$7+7),"H","")&IF(AND($AC16<>"",$AC16>=BH$7,$AC16<BH$7+7),"G","")&IF(AND($AH16<>"",$AH16>=BH$7,$AH16<BH$7+7),"S","") | BI16: =IF(AND($Y16<>"",$Y16>=BI$7,$Y16<BI$7+7),"I","")&IF(AND($Z16<>"",$Z16>=BI$7,$Z16<BI$7+7),"P","")&IF(AND($AA16<>"",$AA16>=BI$7,$AA16<BI$7+7),"T","")&IF(AND($AB16<>"",$AB16>=BI$7,$AB16<BI$7+7),"H","")&IF(AND($AC16<>"",$AC16>=BI$7,$AC16<BI$7+7),"G","")&IF(AND($AH16<>"",$AH16>=BI$7,$AH16<BI$7+7),"S","") | BJ16: =IF(AND($Y16<>"",$Y16>=BJ$7,$Y16<BJ$7+7),"I","")&IF(AND($Z16<>"",$Z16>=BJ$7,$Z16<BJ$7+7),"P","")&IF(AND($AA16<>"",$AA16>=BJ$7,$AA16<BJ$7+7),"T","")&IF(AND($AB16<>"",$AB16>=BJ$7,$AB16<BJ$7+7),"H","")&IF(AND($AC16<>"",$AC16>=BJ$7,$AC16<BJ$7+7),"G","")&IF(AND($AH16<>"",$AH16>=BJ$7,$AH16<BJ$7+7),"S","") | BK16: =IF(AND($Y16<>"",$Y16>=BK$7,$Y16<BK$7+7),"I","")&IF(AND($Z16<>"",$Z16>=BK$7,$Z16<BK$7+7),"P","")&IF(AND($AA16<>"",$AA16>=BK$7,$AA16<BK$7+7),"T","")&IF(AND($AB16<>"",$AB16>=BK$7,$AB16<BK$7+7),"H","")&IF(AND($AC16<>"",$AC16>=BK$7,$AC16<BK$7+7),"G","")&IF(AND($AH16<>"",$AH16>=BK$7,$AH16<BK$7+7),"S","") | BL16: =IF(AND($Y16<>"",$Y16>=BL$7,$Y16<BL$7+7),"I","")&IF(AND($Z16<>"",$Z16>=BL$7,$Z16<BL$7+7),"P","")&IF(AND($AA16<>"",$AA16>=BL$7,$AA16<BL$7+7),"T","")&IF(AND($AB16<>"",$AB16>=BL$7,$AB16<BL$7+7),"H","")&IF(AND($AC16<>"",$AC16>=BL$7,$AC16<BL$7+7),"G","")&IF(AND($AH16<>"",$AH16>=BL$7,$AH16<BL$7+7),"S","") -> I | BM16: =IF(AND($Y16<>"",$Y16>=BM$7,$Y16<BM$7+7),"I","")&IF(AND($Z16<>"",$Z16>=BM$7,$Z16<BM$7+7),"P","")&IF(AND($AA16<>"",$AA16>=BM$7,$AA16<BM$7+7),"T","")&IF(AND($AB16<>"",$AB16>=BM$7,$AB16<BM$7+7),"H","")&IF(AND($AC16<>"",$AC16>=BM$7,$AC16<BM$7+7),"G","")&IF(AND($AH16<>"",$AH16>=BM$7,$AH16<BM$7+7),"S","") -> PTG | BN16: =IF(AND($Y16<>"",$Y16>=BN$7,$Y16<BN$7+7),"I","")&IF(AND($Z16<>"",$Z16>=BN$7,$Z16<BN$7+7),"P","")&IF(AND($AA16<>"",$AA16>=BN$7,$AA16<BN$7+7),"T","")&IF(AND($AB16<>"",$AB16>=BN$7,$AB16<BN$7+7),"H","")&IF(AND($AC16<>"",$AC16>=BN$7,$AC16<BN$7+7),"G","")&IF(AND($AH16<>"",$AH16>=BN$7,$AH16<BN$7+7),"S","") -> H | BO16: =IF(AND($Y16<>"",$Y16>=BO$7,$Y16<BO$7+7),"I","")&IF(AND($Z16<>"",$Z16>=BO$7,$Z16<BO$7+7),"P","")&IF(AND($AA16<>"",$AA16>=BO$7,$AA16<BO$7+7),"T","")&IF(AND($AB16<>"",$AB16>=BO$7,$AB16<BO$7+7),"H","")&IF(AND($AC16<>"",$AC16>=BO$7,$AC16<BO$7+7),"G","")&IF(AND($AH16<>"",$AH16>=BO$7,$AH16<BO$7+7),"S","") | ... DC16: =IF(AND($Y16<>"",$Y16>=DC$7,$Y16<DC$7+7),"I","")&IF(AND($Z16<>"",$Z16>=DC$7,$Z16<DC$7+7),"P","")&IF(AND($AA16<>"",$AA16>=DC$7,$AA16<DC$7+7),"T","")&IF(AND($AB16<>"",$AB16>=DC$7,$AB16<DC$7+7),"H","")&IF(AND($AC16<>"",$AC16>=DC$7,$AC16<DC$7+7),"G","")&IF(AND($AH16<>"",$AH16>=DC$7,$AH16<DC$7+7),"S","")
A17: P9-010 | B17: แม่แบบ ถังน้ำใส, กันย้อน HV, Inverter ≥ 200 kVA | C17: (ตัวอย่าง) | D17: ตัวอย่าง | E17: ตย.10 | F17: 280.44 | G17: รอบ 9 | H17: =PROJ_START+RD_SPAN -> 46403 | I17: =H17+33 -> 46436 | J17: วศ.10 | K17: Admin | L17: 10 | M17: Y | N17: =IF(ISNUMBER(อัปเดตรายสัปดาห์!$AF17),อัปเดตรายสัปดาห์!$AF17,"") | O17: =IF(ISNUMBER(อัปเดตรายสัปดาห์!$AH17),อัปเดตรายสัปดาห์!$AH17,"") | P17: =IF(ISNUMBER(อัปเดตรายสัปดาห์!$AG17),อัปเดตรายสัปดาห์!$AG17,IF(AND(ISNUMBER(TCRoof!$AC$17),N(TCRoof!$AC$17)<=ASOF),TCRoof!$AC$17,"")) | Q17: =IF(ISNUMBER(อัปเดตรายสัปดาห์!$AL17),อัปเดตรายสัปดาห์!$AL17,"") | R17: =IF(ISNUMBER(อัปเดตรายสัปดาห์!$Q17),อัปเดตรายสัปดาห์!$Q17,"") | S17: =IF(ISNUMBER(อัปเดตรายสัปดาห์!$R17),อัปเดตรายสัปดาห์!$R17,"") | T17: =IF(ISNUMBER(อัปเดตรายสัปดาห์!$S17),อัปเดตรายสัปดาห์!$S17,IF(อัปเดตรายสัปดาห์!$S17="Y",ASOF,"")) | U17: =IF(ISNUMBER(อัปเดตรายสัปดาห์!$T17),อัปเดตรายสัปดาห์!$T17,IF(อัปเดตรายสัปดาห์!$T17="Y",ASOF,"")) | V17: =IF(ISNUMBER(อัปเดตรายสัปดาห์!$U17),อัปเดตรายสัปดาห์!$U17,IF(อัปเดตรายสัปดาห์!$U17="Y",ASOF,"")) | W17: =IF(ISNUMBER(อัปเดตรายสัปดาห์!$N17),อัปเดตรายสัปดาห์!$N17,"") | X17: =IF(ISNUMBER(อัปเดตรายสัปดาห์!$V17),อัปเดตรายสัปดาห์!$V17,IF(AND(ISNUMBER(TCRoof!$AD$17),N(TCRoof!$AD$17)<=ASOF),TCRoof!$AD$17,"")) | Y17: =IF(N17<>"",N17,WORKDAY((ASOF+LEAD_INST+7*INT((AT17-0.01)/MAX(1,AU17)))-1,1,HOLIDAYS)) -> 46349 | Z17: =IF(O17<>"",O17,WORKDAY((MAX(AV17+7*INT((AW17-1)/MAX(1,AX17)),AV17+7*INT((AY17-1)/MAX(1,AZ17))))-1,1,HOLIDAYS)) -> 46356 | AA17: =IF(P17<>"",P17,WORKDAY((BA17+7*INT((BB17-1)/MAX(1,BC17)))-1,1,HOLIDAYS)) -> 46359 | AB17: =IF(Q17<>"",Q17,WORKDAY((MAX(AA17+BD17,ASOF+1))-1,1,HOLIDAYS)) -> 46367 | AC17: =IF(R17<>"",R17,WORKDAY((MAX(Y17,ASOF)+LAG_GRID)-1,1,HOLIDAYS)) -> 46356 | AD17: =IF(T17<>"",T17,WORKDAY((MAX(WORKDAY(MAX(AC17,N(S17)),REVIEW_WD,HOLIDAYS),ASOF+1))-1,1,HOLIDAYS)) -> 46379 | AE17: =IF(U17<>"",U17,WORKDAY((MAX(AD17,ASOF)+FEE_DAYS)-1,1,HOLIDAYS)) -> 46386 | AF17: =IF(V17<>"",V17,WORKDAY((MAX(AA17,Z17,AE17,IF(AG17="",0,AG17+REVIEW_PK2),ASOF)+LAG_INSREQ)-1,1,HOLIDAYS)) -> 46391 | AG17: =IF(M17<>"Y","",IF(W17<>"",W17,WORKDAY((MAX(Y17,ASOF)+LAG_GRID)-1,1,HOLIDAYS))) -> 46356 | AH17: =IF(X17<>"",X17,WORKDAY(AF17,INSPECT_WD,HOLIDAYS)) -> 46433 | AI17: =IF(H17="","",AB17-H17) -> -36 | AJ17: =IF(I17="","",AH17-I17) -> -3 | AK17: =IF(AND(ISNUMBER(N17),N(N17)<=ASOF),1,0)+IF(AND(ISNUMBER(O17),N(O17)<=ASOF),1,0)+IF(AND(ISNUMBER(P17),N(P17)<=ASOF),1,0)+IF(AND(ISNUMBER(Q17),N(Q17)<=ASOF),1,0)+IF(AND(ISNUMBER(R17),N(R17)<=ASOF),1,0)+IF(AND(ISNUMBER(U17),N(U17)<=ASOF),1,0)+IF(AND(ISNUMBER(X17),N(X17)<=ASOF),1,0)+IF(AND(ISNUMBER(W17),N(W17)<=ASOF),1,0) -> 0 | AL17: 8 | AM17: ='P9-010'!$J$4 -> 0 | AN17: =TRIM(IF(AND(ISNUMBER(O17),NOT(ISNUMBER(N17))),"กฟภ.ตรวจก่อนติดตั้ง, ","")&IF(AND(ISNUMBER(P17),NOT(ISNUMBER(N17))),"IEC ก่อนติดตั้ง, ","")&IF(AND(ISNUMBER(Q17),NOT(ISNUMBER(N17))),"ส่งมอบก่อนติดตั้ง, ","")&IF(AND(ISNUMBER(Q17),ISNUMBER(P17),N(Q17)<N(P17)),"ส่งมอบก่อน IEC, ","")&IF(AND(ISNUMBER(อัปเดตรายสัปดาห์!$AG17),ISNUMBER(TCRoof!$AC$17),ABS(N(อัปเดตรายสัปดาห์!$AG17)-N(TCRoof!$AC$17))>3),"IEC Excel≠แอป, ","")&IF(AND(ISNUMBER(อัปเดตรายสัปดาห์!$V17),ISNUMBER(TCRoof!$AD$17),ABS(N(อัปเดตรายสัปดาห์!$V17)-N(TCRoof!$AD$17))>3),"COD Excel≠แอป, ","")&IF(AND(ISNUMBER(อัปเดตรายสัปดาห์!$AF17),ISNUMBER(TCRoof!$AB$17),ABS(N(อัปเดตรายสัปดาห์!$AF17)-N(TCRoof!$AB$17))>3),"ติดตั้ง Excel≠แอป, ","")&IF(AND(ISNUMBER(N17),N(N17)>ASOF,OR(WEEKDAY(N(N17),2)>5,COUNTIF(HOLIDAYS,N(N17))>0)),"นัดดับไฟตรงวันหยุด, ","")&IF(AND(ISNUMBER(O17),N(O17)>ASOF,OR(WEEKDAY(N(O17),2)>5,COUNTIF(HOLIDAYS,N(O17))>0)),"นัด กฟภ.ตรงวันหยุด, ","")&IF(AND(ISNUMBER(P17),N(P17)>ASOF,OR(WEEKDAY(N(P17),2)>5,COUNTIF(HOLIDAYS,N(P17))>0)),"นัด IECตรงวันหยุด, ","")&IF(AND(ISNUMBER(X17),N(X17)>ASOF,OR(WEEKDAY(N(X17),2)>5,COUNTIF(HOLIDAYS,N(X17))>0)),"นัด Syncตรงวันหยุด, ","")) | AO17: =SUMIFS(CR_COD,CR_ST,A17,CR_STAT,"อนุมัติ")+SUMIFS(CR_COD,CR_ST,"ทั้งเฟส",CR_STAT,"อนุมัติ")+SUMIFS(CR_COD,CR_ST,"ผรม. "&L17,CR_STAT,"อนุมัติ")+SUMIFS(CR_COD,CR_ST,"เขต "&E17,CR_STAT,"อนุมัติ") -> 0 | AP17: =IF(NOT(ISNUMBER(AJ17)),"",MAX(0,AJ17-AO17)) -> 0 | AQ17: =COUNTIF(RW_ST,A17) -> 0 | AR17: =IF(ISNUMBER(TCRoof!$I$17),TCRoof!$I$17,"") | AS17: =IF(ISNUMBER(TCRoof!$H$17),TCRoof!$H$17,"") | AT17: =IF(N17<>"","",SUMIFS($F$8:$F$27,$L$8:$L$27,L17,$N$8:$N$27,"",$H$8:$H$27,"<"&H17)+SUMIFS($F$8:$F$27,$L$8:$L$27,L17,$N$8:$N$27,"",$H$8:$H$27,H17,$A$8:$A$27,"<="&A17)+SUMIFS($F$8:$F$27,$L$8:$L$27,L17,$N$8:$N$27,">"&ASOF)) -> 280.44 | AU17: =IFERROR(VLOOKUP(L17,TEAM_TBL,2,0)*VLOOKUP(L17,TEAM_TBL,3,0),150) -> 150 | AV17: =IF(O17<>"","",MAX(Y17+LAG_PEA,ASOF+LAG_PEA)) -> 46356 | AW17: =IF(O17<>"","",COUNTIFS($E$8:$E$27,E17,$AV$8:$AV$27,"<"&AV17)+COUNTIFS($E$8:$E$27,E17,$AV$8:$AV$27,AV17,$A$8:$A$27,"<"&A17)+COUNTIFS($E$8:$E$27,E17,$O$8:$O$27,">"&ASOF)+1) -> 1 | AX17: =IFERROR(VLOOKUP(E17,ZONE_TBL,2,0),CAP_PEA) -> 3 | AY17: =IF(O17<>"","",COUNTIFS($J$8:$J$27,J17,$AV$8:$AV$27,"<"&AV17)+COUNTIFS($J$8:$J$27,J17,$AV$8:$AV$27,AV17,$A$8:$A$27,"<"&A17)+COUNTIFS($J$8:$J$27,J17,$O$8:$O$27,">"&ASOF)+1) -> 1 | AZ17: =IFERROR(VLOOKUP(J17,ENG_TBL,2,0),ENG_CAP) -> 3 | BA17: =IF(P17<>"","",MAX(Z17+LAG_IEC,ASOF+1)) -> 46359 | BB17: =IF(P17<>"","",COUNTIFS($L$8:$L$27,L17,$BA$8:$BA$27,"<"&BA17)+COUNTIFS($L$8:$L$27,L17,$BA$8:$BA$27,BA17,$A$8:$A$27,"<"&A17)+COUNTIFS($L$8:$L$27,L17,$P$8:$P$27,">"&ASOF)+1) -> 1 | BC17: =IFERROR(VLOOKUP(L17,TEAM_TBL,4,0)*VLOOKUP(L17,TEAM_TBL,5,0),3) -> 3 | BD17: =IFERROR(VLOOKUP(L17,TEAM_TBL,6,0),LAG_HO) -> 7 | BE17: =IF(ISNUMBER(AW17),7*INT((AW17-1)/MAX(1,AX17)),"") -> 0 | BF17: =IF(ISNUMBER(AY17),7*INT((AY17-1)/MAX(1,AZ17)),"") -> 0 | BH17: =IF(AND($Y17<>"",$Y17>=BH$7,$Y17<BH$7+7),"I","")&IF(AND($Z17<>"",$Z17>=BH$7,$Z17<BH$7+7),"P","")&IF(AND($AA17<>"",$AA17>=BH$7,$AA17<BH$7+7),"T","")&IF(AND($AB17<>"",$AB17>=BH$7,$AB17<BH$7+7),"H","")&IF(AND($AC17<>"",$AC17>=BH$7,$AC17<BH$7+7),"G","")&IF(AND($AH17<>"",$AH17>=BH$7,$AH17<BH$7+7),"S","") | BI17: =IF(AND($Y17<>"",$Y17>=BI$7,$Y17<BI$7+7),"I","")&IF(AND($Z17<>"",$Z17>=BI$7,$Z17<BI$7+7),"P","")&IF(AND($AA17<>"",$AA17>=BI$7,$AA17<BI$7+7),"T","")&IF(AND($AB17<>"",$AB17>=BI$7,$AB17<BI$7+7),"H","")&IF(AND($AC17<>"",$AC17>=BI$7,$AC17<BI$7+7),"G","")&IF(AND($AH17<>"",$AH17>=BI$7,$AH17<BI$7+7),"S","") | BJ17: =IF(AND($Y17<>"",$Y17>=BJ$7,$Y17<BJ$7+7),"I","")&IF(AND($Z17<>"",$Z17>=BJ$7,$Z17<BJ$7+7),"P","")&IF(AND($AA17<>"",$AA17>=BJ$7,$AA17<BJ$7+7),"T","")&IF(AND($AB17<>"",$AB17>=BJ$7,$AB17<BJ$7+7),"H","")&IF(AND($AC17<>"",$AC17>=BJ$7,$AC17<BJ$7+7),"G","")&IF(AND($AH17<>"",$AH17>=BJ$7,$AH17<BJ$7+7),"S","") | BK17: =IF(AND($Y17<>"",$Y17>=BK$7,$Y17<BK$7+7),"I","")&IF(AND($Z17<>"",$Z17>=BK$7,$Z17<BK$7+7),"P","")&IF(AND($AA17<>"",$AA17>=BK$7,$AA17<BK$7+7),"T","")&IF(AND($AB17<>"",$AB17>=BK$7,$AB17<BK$7+7),"H","")&IF(AND($AC17<>"",$AC17>=BK$7,$AC17<BK$7+7),"G","")&IF(AND($AH17<>"",$AH17>=BK$7,$AH17<BK$7+7),"S","") | BL17: =IF(AND($Y17<>"",$Y17>=BL$7,$Y17<BL$7+7),"I","")&IF(AND($Z17<>"",$Z17>=BL$7,$Z17<BL$7+7),"P","")&IF(AND($AA17<>"",$AA17>=BL$7,$AA17<BL$7+7),"T","")&IF(AND($AB17<>"",$AB17>=BL$7,$AB17<BL$7+7),"H","")&IF(AND($AC17<>"",$AC17>=BL$7,$AC17<BL$7+7),"G","")&IF(AND($AH17<>"",$AH17>=BL$7,$AH17<BL$7+7),"S","") -> I | BM17: =IF(AND($Y17<>"",$Y17>=BM$7,$Y17<BM$7+7),"I","")&IF(AND($Z17<>"",$Z17>=BM$7,$Z17<BM$7+7),"P","")&IF(AND($AA17<>"",$AA17>=BM$7,$AA17<BM$7+7),"T","")&IF(AND($AB17<>"",$AB17>=BM$7,$AB17<BM$7+7),"H","")&IF(AND($AC17<>"",$AC17>=BM$7,$AC17<BM$7+7),"G","")&IF(AND($AH17<>"",$AH17>=BM$7,$AH17<BM$7+7),"S","") -> PTG | BN17: =IF(AND($Y17<>"",$Y17>=BN$7,$Y17<BN$7+7),"I","")&IF(AND($Z17<>"",$Z17>=BN$7,$Z17<BN$7+7),"P","")&IF(AND($AA17<>"",$AA17>=BN$7,$AA17<BN$7+7),"T","")&IF(AND($AB17<>"",$AB17>=BN$7,$AB17<BN$7+7),"H","")&IF(AND($AC17<>"",$AC17>=BN$7,$AC17<BN$7+7),"G","")&IF(AND($AH17<>"",$AH17>=BN$7,$AH17<BN$7+7),"S","") -> H | BO17: =IF(AND($Y17<>"",$Y17>=BO$7,$Y17<BO$7+7),"I","")&IF(AND($Z17<>"",$Z17>=BO$7,$Z17<BO$7+7),"P","")&IF(AND($AA17<>"",$AA17>=BO$7,$AA17<BO$7+7),"T","")&IF(AND($AB17<>"",$AB17>=BO$7,$AB17<BO$7+7),"H","")&IF(AND($AC17<>"",$AC17>=BO$7,$AC17<BO$7+7),"G","")&IF(AND($AH17<>"",$AH17>=BO$7,$AH17<BO$7+7),"S","") | ... DC17: =IF(AND($Y17<>"",$Y17>=DC$7,$Y17<DC$7+7),"I","")&IF(AND($Z17<>"",$Z17>=DC$7,$Z17<DC$7+7),"P","")&IF(AND($AA17<>"",$AA17>=DC$7,$AA17<DC$7+7),"T","")&IF(AND($AB17<>"",$AB17>=DC$7,$AB17<DC$7+7),"H","")&IF(AND($AC17<>"",$AC17>=DC$7,$AC17<DC$7+7),"G","")&IF(AND($AH17<>"",$AH17>=DC$7,$AH17<DC$7+7),"S","")
A18: P9-011 | B18: แม่แบบ ถังน้ำใส, กันย้อน LV, Inverter < 200 kVA | C18: (ตัวอย่าง) | D18: ตัวอย่าง | E18: ตย.11 | F18: 150.48 | G18: รอบ 9 | H18: =PROJ_START+RD_SPAN -> 46403 | I18: =H18+33 -> 46436 | J18: วศ.11 | K18: Admin | L18: 11 | M18: N | N18: =IF(ISNUMBER(อัปเดตรายสัปดาห์!$AF18),อัปเดตรายสัปดาห์!$AF18,"") | O18: =IF(ISNUMBER(อัปเดตรายสัปดาห์!$AH18),อัปเดตรายสัปดาห์!$AH18,"") | P18: =IF(ISNUMBER(อัปเดตรายสัปดาห์!$AG18),อัปเดตรายสัปดาห์!$AG18,IF(AND(ISNUMBER(TCRoof!$AC$18),N(TCRoof!$AC$18)<=ASOF),TCRoof!$AC$18,"")) | Q18: =IF(ISNUMBER(อัปเดตรายสัปดาห์!$AL18),อัปเดตรายสัปดาห์!$AL18,"") | R18: =IF(ISNUMBER(อัปเดตรายสัปดาห์!$Q18),อัปเดตรายสัปดาห์!$Q18,"") | S18: =IF(ISNUMBER(อัปเดตรายสัปดาห์!$R18),อัปเดตรายสัปดาห์!$R18,"") | T18: =IF(ISNUMBER(อัปเดตรายสัปดาห์!$S18),อัปเดตรายสัปดาห์!$S18,IF(อัปเดตรายสัปดาห์!$S18="Y",ASOF,"")) | U18: =IF(ISNUMBER(อัปเดตรายสัปดาห์!$T18),อัปเดตรายสัปดาห์!$T18,IF(อัปเดตรายสัปดาห์!$T18="Y",ASOF,"")) | V18: =IF(ISNUMBER(อัปเดตรายสัปดาห์!$U18),อัปเดตรายสัปดาห์!$U18,IF(อัปเดตรายสัปดาห์!$U18="Y",ASOF,"")) | W18: =IF(ISNUMBER(อัปเดตรายสัปดาห์!$N18),อัปเดตรายสัปดาห์!$N18,"") | X18: =IF(ISNUMBER(อัปเดตรายสัปดาห์!$V18),อัปเดตรายสัปดาห์!$V18,IF(AND(ISNUMBER(TCRoof!$AD$18),N(TCRoof!$AD$18)<=ASOF),TCRoof!$AD$18,"")) | Y18: =IF(N18<>"",N18,WORKDAY((ASOF+LEAD_INST+7*INT((AT18-0.01)/MAX(1,AU18)))-1,1,HOLIDAYS)) -> 46349 | Z18: =IF(O18<>"",O18,WORKDAY((MAX(AV18+7*INT((AW18-1)/MAX(1,AX18)),AV18+7*INT((AY18-1)/MAX(1,AZ18))))-1,1,HOLIDAYS)) -> 46356 | AA18: =IF(P18<>"",P18,WORKDAY((BA18+7*INT((BB18-1)/MAX(1,BC18)))-1,1,HOLIDAYS)) -> 46359 | AB18: =IF(Q18<>"",Q18,WORKDAY((MAX(AA18+BD18,ASOF+1))-1,1,HOLIDAYS)) -> 46367 | AC18: =IF(R18<>"",R18,WORKDAY((MAX(Y18,ASOF)+LAG_GRID)-1,1,HOLIDAYS)) -> 46356 | AD18: =IF(T18<>"",T18,WORKDAY((MAX(WORKDAY(MAX(AC18,N(S18)),REVIEW_WD,HOLIDAYS),ASOF+1))-1,1,HOLIDAYS)) -> 46379 | AE18: =IF(U18<>"",U18,WORKDAY((MAX(AD18,ASOF)+FEE_DAYS)-1,1,HOLIDAYS)) -> 46386 | AF18: =IF(V18<>"",V18,WORKDAY((MAX(AA18,Z18,AE18,IF(AG18="",0,AG18+REVIEW_PK2),ASOF)+LAG_INSREQ)-1,1,HOLIDAYS)) -> 46391 | AG18: =IF(M18<>"Y","",IF(W18<>"",W18,WORKDAY((MAX(Y18,ASOF)+LAG_GRID)-1,1,HOLIDAYS))) | AH18: =IF(X18<>"",X18,WORKDAY(AF18,INSPECT_WD,HOLIDAYS)) -> 46433 | AI18: =IF(H18="","",AB18-H18) -> -36 | AJ18: =IF(I18="","",AH18-I18) -> -3 | AK18: =IF(AND(ISNUMBER(N18),N(N18)<=ASOF),1,0)+IF(AND(ISNUMBER(O18),N(O18)<=ASOF),1,0)+IF(AND(ISNUMBER(P18),N(P18)<=ASOF),1,0)+IF(AND(ISNUMBER(Q18),N(Q18)<=ASOF),1,0)+IF(AND(ISNUMBER(R18),N(R18)<=ASOF),1,0)+IF(AND(ISNUMBER(U18),N(U18)<=ASOF),1,0)+IF(AND(ISNUMBER(X18),N(X18)<=ASOF),1,0) -> 0 | AL18: 7 | AM18: ='P9-011'!$J$4 -> 0 | AN18: =TRIM(IF(AND(ISNUMBER(O18),NOT(ISNUMBER(N18))),"กฟภ.ตรวจก่อนติดตั้ง, ","")&IF(AND(ISNUMBER(P18),NOT(ISNUMBER(N18))),"IEC ก่อนติดตั้ง, ","")&IF(AND(ISNUMBER(Q18),NOT(ISNUMBER(N18))),"ส่งมอบก่อนติดตั้ง, ","")&IF(AND(ISNUMBER(Q18),ISNUMBER(P18),N(Q18)<N(P18)),"ส่งมอบก่อน IEC, ","")&IF(AND(ISNUMBER(อัปเดตรายสัปดาห์!$AG18),ISNUMBER(TCRoof!$AC$18),ABS(N(อัปเดตรายสัปดาห์!$AG18)-N(TCRoof!$AC$18))>3),"IEC Excel≠แอป, ","")&IF(AND(ISNUMBER(อัปเดตรายสัปดาห์!$V18),ISNUMBER(TCRoof!$AD$18),ABS(N(อัปเดตรายสัปดาห์!$V18)-N(TCRoof!$AD$18))>3),"COD Excel≠แอป, ","")&IF(AND(ISNUMBER(อัปเดตรายสัปดาห์!$AF18),ISNUMBER(TCRoof!$AB$18),ABS(N(อัปเดตรายสัปดาห์!$AF18)-N(TCRoof!$AB$18))>3),"ติดตั้ง Excel≠แอป, ","")&IF(AND(ISNUMBER(N18),N(N18)>ASOF,OR(WEEKDAY(N(N18),2)>5,COUNTIF(HOLIDAYS,N(N18))>0)),"นัดดับไฟตรงวันหยุด, ","")&IF(AND(ISNUMBER(O18),N(O18)>ASOF,OR(WEEKDAY(N(O18),2)>5,COUNTIF(HOLIDAYS,N(O18))>0)),"นัด กฟภ.ตรงวันหยุด, ","")&IF(AND(ISNUMBER(P18),N(P18)>ASOF,OR(WEEKDAY(N(P18),2)>5,COUNTIF(HOLIDAYS,N(P18))>0)),"นัด IECตรงวันหยุด, ","")&IF(AND(ISNUMBER(X18),N(X18)>ASOF,OR(WEEKDAY(N(X18),2)>5,COUNTIF(HOLIDAYS,N(X18))>0)),"นัด Syncตรงวันหยุด, ","")) | AO18: =SUMIFS(CR_COD,CR_ST,A18,CR_STAT,"อนุมัติ")+SUMIFS(CR_COD,CR_ST,"ทั้งเฟส",CR_STAT,"อนุมัติ")+SUMIFS(CR_COD,CR_ST,"ผรม. "&L18,CR_STAT,"อนุมัติ")+SUMIFS(CR_COD,CR_ST,"เขต "&E18,CR_STAT,"อนุมัติ") -> 0 | AP18: =IF(NOT(ISNUMBER(AJ18)),"",MAX(0,AJ18-AO18)) -> 0 | AQ18: =COUNTIF(RW_ST,A18) -> 0 | AR18: =IF(ISNUMBER(TCRoof!$I$18),TCRoof!$I$18,"") | AS18: =IF(ISNUMBER(TCRoof!$H$18),TCRoof!$H$18,"") | AT18: =IF(N18<>"","",SUMIFS($F$8:$F$27,$L$8:$L$27,L18,$N$8:$N$27,"",$H$8:$H$27,"<"&H18)+SUMIFS($F$8:$F$27,$L$8:$L$27,L18,$N$8:$N$27,"",$H$8:$H$27,H18,$A$8:$A$27,"<="&A18)+SUMIFS($F$8:$F$27,$L$8:$L$27,L18,$N$8:$N$27,">"&ASOF)) -> 150.48 | AU18: =IFERROR(VLOOKUP(L18,TEAM_TBL,2,0)*VLOOKUP(L18,TEAM_TBL,3,0),150) -> 150 | AV18: =IF(O18<>"","",MAX(Y18+LAG_PEA,ASOF+LAG_PEA)) -> 46356 | AW18: =IF(O18<>"","",COUNTIFS($E$8:$E$27,E18,$AV$8:$AV$27,"<"&AV18)+COUNTIFS($E$8:$E$27,E18,$AV$8:$AV$27,AV18,$A$8:$A$27,"<"&A18)+COUNTIFS($E$8:$E$27,E18,$O$8:$O$27,">"&ASOF)+1) -> 1 | AX18: =IFERROR(VLOOKUP(E18,ZONE_TBL,2,0),CAP_PEA) -> 3 | AY18: =IF(O18<>"","",COUNTIFS($J$8:$J$27,J18,$AV$8:$AV$27,"<"&AV18)+COUNTIFS($J$8:$J$27,J18,$AV$8:$AV$27,AV18,$A$8:$A$27,"<"&A18)+COUNTIFS($J$8:$J$27,J18,$O$8:$O$27,">"&ASOF)+1) -> 1 | AZ18: =IFERROR(VLOOKUP(J18,ENG_TBL,2,0),ENG_CAP) -> 3 | BA18: =IF(P18<>"","",MAX(Z18+LAG_IEC,ASOF+1)) -> 46359 | BB18: =IF(P18<>"","",COUNTIFS($L$8:$L$27,L18,$BA$8:$BA$27,"<"&BA18)+COUNTIFS($L$8:$L$27,L18,$BA$8:$BA$27,BA18,$A$8:$A$27,"<"&A18)+COUNTIFS($L$8:$L$27,L18,$P$8:$P$27,">"&ASOF)+1) -> 1 | BC18: =IFERROR(VLOOKUP(L18,TEAM_TBL,4,0)*VLOOKUP(L18,TEAM_TBL,5,0),3) -> 3 | BD18: =IFERROR(VLOOKUP(L18,TEAM_TBL,6,0),LAG_HO) -> 7 | BE18: =IF(ISNUMBER(AW18),7*INT((AW18-1)/MAX(1,AX18)),"") -> 0 | BF18: =IF(ISNUMBER(AY18),7*INT((AY18-1)/MAX(1,AZ18)),"") -> 0 | BH18: =IF(AND($Y18<>"",$Y18>=BH$7,$Y18<BH$7+7),"I","")&IF(AND($Z18<>"",$Z18>=BH$7,$Z18<BH$7+7),"P","")&IF(AND($AA18<>"",$AA18>=BH$7,$AA18<BH$7+7),"T","")&IF(AND($AB18<>"",$AB18>=BH$7,$AB18<BH$7+7),"H","")&IF(AND($AC18<>"",$AC18>=BH$7,$AC18<BH$7+7),"G","")&IF(AND($AH18<>"",$AH18>=BH$7,$AH18<BH$7+7),"S","") | BI18: =IF(AND($Y18<>"",$Y18>=BI$7,$Y18<BI$7+7),"I","")&IF(AND($Z18<>"",$Z18>=BI$7,$Z18<BI$7+7),"P","")&IF(AND($AA18<>"",$AA18>=BI$7,$AA18<BI$7+7),"T","")&IF(AND($AB18<>"",$AB18>=BI$7,$AB18<BI$7+7),"H","")&IF(AND($AC18<>"",$AC18>=BI$7,$AC18<BI$7+7),"G","")&IF(AND($AH18<>"",$AH18>=BI$7,$AH18<BI$7+7),"S","") | BJ18: =IF(AND($Y18<>"",$Y18>=BJ$7,$Y18<BJ$7+7),"I","")&IF(AND($Z18<>"",$Z18>=BJ$7,$Z18<BJ$7+7),"P","")&IF(AND($AA18<>"",$AA18>=BJ$7,$AA18<BJ$7+7),"T","")&IF(AND($AB18<>"",$AB18>=BJ$7,$AB18<BJ$7+7),"H","")&IF(AND($AC18<>"",$AC18>=BJ$7,$AC18<BJ$7+7),"G","")&IF(AND($AH18<>"",$AH18>=BJ$7,$AH18<BJ$7+7),"S","") | BK18: =IF(AND($Y18<>"",$Y18>=BK$7,$Y18<BK$7+7),"I","")&IF(AND($Z18<>"",$Z18>=BK$7,$Z18<BK$7+7),"P","")&IF(AND($AA18<>"",$AA18>=BK$7,$AA18<BK$7+7),"T","")&IF(AND($AB18<>"",$AB18>=BK$7,$AB18<BK$7+7),"H","")&IF(AND($AC18<>"",$AC18>=BK$7,$AC18<BK$7+7),"G","")&IF(AND($AH18<>"",$AH18>=BK$7,$AH18<BK$7+7),"S","") | BL18: =IF(AND($Y18<>"",$Y18>=BL$7,$Y18<BL$7+7),"I","")&IF(AND($Z18<>"",$Z18>=BL$7,$Z18<BL$7+7),"P","")&IF(AND($AA18<>"",$AA18>=BL$7,$AA18<BL$7+7),"T","")&IF(AND($AB18<>"",$AB18>=BL$7,$AB18<BL$7+7),"H","")&IF(AND($AC18<>"",$AC18>=BL$7,$AC18<BL$7+7),"G","")&IF(AND($AH18<>"",$AH18>=BL$7,$AH18<BL$7+7),"S","") -> I | BM18: =IF(AND($Y18<>"",$Y18>=BM$7,$Y18<BM$7+7),"I","")&IF(AND($Z18<>"",$Z18>=BM$7,$Z18<BM$7+7),"P","")&IF(AND($AA18<>"",$AA18>=BM$7,$AA18<BM$7+7),"T","")&IF(AND($AB18<>"",$AB18>=BM$7,$AB18<BM$7+7),"H","")&IF(AND($AC18<>"",$AC18>=BM$7,$AC18<BM$7+7),"G","")&IF(AND($AH18<>"",$AH18>=BM$7,$AH18<BM$7+7),"S","") -> PTG | BN18: =IF(AND($Y18<>"",$Y18>=BN$7,$Y18<BN$7+7),"I","")&IF(AND($Z18<>"",$Z18>=BN$7,$Z18<BN$7+7),"P","")&IF(AND($AA18<>"",$AA18>=BN$7,$AA18<BN$7+7),"T","")&IF(AND($AB18<>"",$AB18>=BN$7,$AB18<BN$7+7),"H","")&IF(AND($AC18<>"",$AC18>=BN$7,$AC18<BN$7+7),"G","")&IF(AND($AH18<>"",$AH18>=BN$7,$AH18<BN$7+7),"S","") -> H | BO18: =IF(AND($Y18<>"",$Y18>=BO$7,$Y18<BO$7+7),"I","")&IF(AND($Z18<>"",$Z18>=BO$7,$Z18<BO$7+7),"P","")&IF(AND($AA18<>"",$AA18>=BO$7,$AA18<BO$7+7),"T","")&IF(AND($AB18<>"",$AB18>=BO$7,$AB18<BO$7+7),"H","")&IF(AND($AC18<>"",$AC18>=BO$7,$AC18<BO$7+7),"G","")&IF(AND($AH18<>"",$AH18>=BO$7,$AH18<BO$7+7),"S","") | ... DC18: =IF(AND($Y18<>"",$Y18>=DC$7,$Y18<DC$7+7),"I","")&IF(AND($Z18<>"",$Z18>=DC$7,$Z18<DC$7+7),"P","")&IF(AND($AA18<>"",$AA18>=DC$7,$AA18<DC$7+7),"T","")&IF(AND($AB18<>"",$AB18>=DC$7,$AB18<DC$7+7),"H","")&IF(AND($AC18<>"",$AC18>=DC$7,$AC18<DC$7+7),"G","")&IF(AND($AH18<>"",$AH18>=DC$7,$AH18<DC$7+7),"S","")
A19: P9-012 | B19: แม่แบบ ถังน้ำใส, กันย้อน LV, Inverter ≥ 200 kVA | C19: (ตัวอย่าง) | D19: ตัวอย่าง | E19: ตย.12 | F19: 280.44 | G19: รอบ 9 | H19: =PROJ_START+RD_SPAN -> 46403 | I19: =H19+33 -> 46436 | J19: วศ.12 | K19: Admin | L19: 12 | M19: Y | N19: =IF(ISNUMBER(อัปเดตรายสัปดาห์!$AF19),อัปเดตรายสัปดาห์!$AF19,"") | O19: =IF(ISNUMBER(อัปเดตรายสัปดาห์!$AH19),อัปเดตรายสัปดาห์!$AH19,"") | P19: =IF(ISNUMBER(อัปเดตรายสัปดาห์!$AG19),อัปเดตรายสัปดาห์!$AG19,IF(AND(ISNUMBER(TCRoof!$AC$19),N(TCRoof!$AC$19)<=ASOF),TCRoof!$AC$19,"")) | Q19: =IF(ISNUMBER(อัปเดตรายสัปดาห์!$AL19),อัปเดตรายสัปดาห์!$AL19,"") | R19: =IF(ISNUMBER(อัปเดตรายสัปดาห์!$Q19),อัปเดตรายสัปดาห์!$Q19,"") | S19: =IF(ISNUMBER(อัปเดตรายสัปดาห์!$R19),อัปเดตรายสัปดาห์!$R19,"") | T19: =IF(ISNUMBER(อัปเดตรายสัปดาห์!$S19),อัปเดตรายสัปดาห์!$S19,IF(อัปเดตรายสัปดาห์!$S19="Y",ASOF,"")) | U19: =IF(ISNUMBER(อัปเดตรายสัปดาห์!$T19),อัปเดตรายสัปดาห์!$T19,IF(อัปเดตรายสัปดาห์!$T19="Y",ASOF,"")) | V19: =IF(ISNUMBER(อัปเดตรายสัปดาห์!$U19),อัปเดตรายสัปดาห์!$U19,IF(อัปเดตรายสัปดาห์!$U19="Y",ASOF,"")) | W19: =IF(ISNUMBER(อัปเดตรายสัปดาห์!$N19),อัปเดตรายสัปดาห์!$N19,"") | X19: =IF(ISNUMBER(อัปเดตรายสัปดาห์!$V19),อัปเดตรายสัปดาห์!$V19,IF(AND(ISNUMBER(TCRoof!$AD$19),N(TCRoof!$AD$19)<=ASOF),TCRoof!$AD$19,"")) | Y19: =IF(N19<>"",N19,WORKDAY((ASOF+LEAD_INST+7*INT((AT19-0.01)/MAX(1,AU19)))-1,1,HOLIDAYS)) -> 46349 | Z19: =IF(O19<>"",O19,WORKDAY((MAX(AV19+7*INT((AW19-1)/MAX(1,AX19)),AV19+7*INT((AY19-1)/MAX(1,AZ19))))-1,1,HOLIDAYS)) -> 46356 | AA19: =IF(P19<>"",P19,WORKDAY((BA19+7*INT((BB19-1)/MAX(1,BC19)))-1,1,HOLIDAYS)) -> 46359 | AB19: =IF(Q19<>"",Q19,WORKDAY((MAX(AA19+BD19,ASOF+1))-1,1,HOLIDAYS)) -> 46367 | AC19: =IF(R19<>"",R19,WORKDAY((MAX(Y19,ASOF)+LAG_GRID)-1,1,HOLIDAYS)) -> 46356 | AD19: =IF(T19<>"",T19,WORKDAY((MAX(WORKDAY(MAX(AC19,N(S19)),REVIEW_WD,HOLIDAYS),ASOF+1))-1,1,HOLIDAYS)) -> 46379 | AE19: =IF(U19<>"",U19,WORKDAY((MAX(AD19,ASOF)+FEE_DAYS)-1,1,HOLIDAYS)) -> 46386 | AF19: =IF(V19<>"",V19,WORKDAY((MAX(AA19,Z19,AE19,IF(AG19="",0,AG19+REVIEW_PK2),ASOF)+LAG_INSREQ)-1,1,HOLIDAYS)) -> 46391 | AG19: =IF(M19<>"Y","",IF(W19<>"",W19,WORKDAY((MAX(Y19,ASOF)+LAG_GRID)-1,1,HOLIDAYS))) -> 46356 | AH19: =IF(X19<>"",X19,WORKDAY(AF19,INSPECT_WD,HOLIDAYS)) -> 46433 | AI19: =IF(H19="","",AB19-H19) -> -36 | AJ19: =IF(I19="","",AH19-I19) -> -3 | AK19: =IF(AND(ISNUMBER(N19),N(N19)<=ASOF),1,0)+IF(AND(ISNUMBER(O19),N(O19)<=ASOF),1,0)+IF(AND(ISNUMBER(P19),N(P19)<=ASOF),1,0)+IF(AND(ISNUMBER(Q19),N(Q19)<=ASOF),1,0)+IF(AND(ISNUMBER(R19),N(R19)<=ASOF),1,0)+IF(AND(ISNUMBER(U19),N(U19)<=ASOF),1,0)+IF(AND(ISNUMBER(X19),N(X19)<=ASOF),1,0)+IF(AND(ISNUMBER(W19),N(W19)<=ASOF),1,0) -> 0 | AL19: 8 | AM19: ='P9-012'!$J$4 -> 0 | AN19: =TRIM(IF(AND(ISNUMBER(O19),NOT(ISNUMBER(N19))),"กฟภ.ตรวจก่อนติดตั้ง, ","")&IF(AND(ISNUMBER(P19),NOT(ISNUMBER(N19))),"IEC ก่อนติดตั้ง, ","")&IF(AND(ISNUMBER(Q19),NOT(ISNUMBER(N19))),"ส่งมอบก่อนติดตั้ง, ","")&IF(AND(ISNUMBER(Q19),ISNUMBER(P19),N(Q19)<N(P19)),"ส่งมอบก่อน IEC, ","")&IF(AND(ISNUMBER(อัปเดตรายสัปดาห์!$AG19),ISNUMBER(TCRoof!$AC$19),ABS(N(อัปเดตรายสัปดาห์!$AG19)-N(TCRoof!$AC$19))>3),"IEC Excel≠แอป, ","")&IF(AND(ISNUMBER(อัปเดตรายสัปดาห์!$V19),ISNUMBER(TCRoof!$AD$19),ABS(N(อัปเดตรายสัปดาห์!$V19)-N(TCRoof!$AD$19))>3),"COD Excel≠แอป, ","")&IF(AND(ISNUMBER(อัปเดตรายสัปดาห์!$AF19),ISNUMBER(TCRoof!$AB$19),ABS(N(อัปเดตรายสัปดาห์!$AF19)-N(TCRoof!$AB$19))>3),"ติดตั้ง Excel≠แอป, ","")&IF(AND(ISNUMBER(N19),N(N19)>ASOF,OR(WEEKDAY(N(N19),2)>5,COUNTIF(HOLIDAYS,N(N19))>0)),"นัดดับไฟตรงวันหยุด, ","")&IF(AND(ISNUMBER(O19),N(O19)>ASOF,OR(WEEKDAY(N(O19),2)>5,COUNTIF(HOLIDAYS,N(O19))>0)),"นัด กฟภ.ตรงวันหยุด, ","")&IF(AND(ISNUMBER(P19),N(P19)>ASOF,OR(WEEKDAY(N(P19),2)>5,COUNTIF(HOLIDAYS,N(P19))>0)),"นัด IECตรงวันหยุด, ","")&IF(AND(ISNUMBER(X19),N(X19)>ASOF,OR(WEEKDAY(N(X19),2)>5,COUNTIF(HOLIDAYS,N(X19))>0)),"นัด Syncตรงวันหยุด, ","")) | AO19: =SUMIFS(CR_COD,CR_ST,A19,CR_STAT,"อนุมัติ")+SUMIFS(CR_COD,CR_ST,"ทั้งเฟส",CR_STAT,"อนุมัติ")+SUMIFS(CR_COD,CR_ST,"ผรม. "&L19,CR_STAT,"อนุมัติ")+SUMIFS(CR_COD,CR_ST,"เขต "&E19,CR_STAT,"อนุมัติ") -> 0 | AP19: =IF(NOT(ISNUMBER(AJ19)),"",MAX(0,AJ19-AO19)) -> 0 | AQ19: =COUNTIF(RW_ST,A19) -> 0 | AR19: =IF(ISNUMBER(TCRoof!$I$19),TCRoof!$I$19,"") | AS19: =IF(ISNUMBER(TCRoof!$H$19),TCRoof!$H$19,"") | AT19: =IF(N19<>"","",SUMIFS($F$8:$F$27,$L$8:$L$27,L19,$N$8:$N$27,"",$H$8:$H$27,"<"&H19)+SUMIFS($F$8:$F$27,$L$8:$L$27,L19,$N$8:$N$27,"",$H$8:$H$27,H19,$A$8:$A$27,"<="&A19)+SUMIFS($F$8:$F$27,$L$8:$L$27,L19,$N$8:$N$27,">"&ASOF)) -> 280.44 | AU19: =IFERROR(VLOOKUP(L19,TEAM_TBL,2,0)*VLOOKUP(L19,TEAM_TBL,3,0),150) -> 150 | AV19: =IF(O19<>"","",MAX(Y19+LAG_PEA,ASOF+LAG_PEA)) -> 46356 | AW19: =IF(O19<>"","",COUNTIFS($E$8:$E$27,E19,$AV$8:$AV$27,"<"&AV19)+COUNTIFS($E$8:$E$27,E19,$AV$8:$AV$27,AV19,$A$8:$A$27,"<"&A19)+COUNTIFS($E$8:$E$27,E19,$O$8:$O$27,">"&ASOF)+1) -> 1 | AX19: =IFERROR(VLOOKUP(E19,ZONE_TBL,2,0),CAP_PEA) -> 3 | AY19: =IF(O19<>"","",COUNTIFS($J$8:$J$27,J19,$AV$8:$AV$27,"<"&AV19)+COUNTIFS($J$8:$J$27,J19,$AV$8:$AV$27,AV19,$A$8:$A$27,"<"&A19)+COUNTIFS($J$8:$J$27,J19,$O$8:$O$27,">"&ASOF)+1) -> 1 | AZ19: =IFERROR(VLOOKUP(J19,ENG_TBL,2,0),ENG_CAP) -> 3 | BA19: =IF(P19<>"","",MAX(Z19+LAG_IEC,ASOF+1)) -> 46359 | BB19: =IF(P19<>"","",COUNTIFS($L$8:$L$27,L19,$BA$8:$BA$27,"<"&BA19)+COUNTIFS($L$8:$L$27,L19,$BA$8:$BA$27,BA19,$A$8:$A$27,"<"&A19)+COUNTIFS($L$8:$L$27,L19,$P$8:$P$27,">"&ASOF)+1) -> 1 | BC19: =IFERROR(VLOOKUP(L19,TEAM_TBL,4,0)*VLOOKUP(L19,TEAM_TBL,5,0),3) -> 3 | BD19: =IFERROR(VLOOKUP(L19,TEAM_TBL,6,0),LAG_HO) -> 7 | BE19: =IF(ISNUMBER(AW19),7*INT((AW19-1)/MAX(1,AX19)),"") -> 0 | BF19: =IF(ISNUMBER(AY19),7*INT((AY19-1)/MAX(1,AZ19)),"") -> 0 | BH19: =IF(AND($Y19<>"",$Y19>=BH$7,$Y19<BH$7+7),"I","")&IF(AND($Z19<>"",$Z19>=BH$7,$Z19<BH$7+7),"P","")&IF(AND($AA19<>"",$AA19>=BH$7,$AA19<BH$7+7),"T","")&IF(AND($AB19<>"",$AB19>=BH$7,$AB19<BH$7+7),"H","")&IF(AND($AC19<>"",$AC19>=BH$7,$AC19<BH$7+7),"G","")&IF(AND($AH19<>"",$AH19>=BH$7,$AH19<BH$7+7),"S","") | BI19: =IF(AND($Y19<>"",$Y19>=BI$7,$Y19<BI$7+7),"I","")&IF(AND($Z19<>"",$Z19>=BI$7,$Z19<BI$7+7),"P","")&IF(AND($AA19<>"",$AA19>=BI$7,$AA19<BI$7+7),"T","")&IF(AND($AB19<>"",$AB19>=BI$7,$AB19<BI$7+7),"H","")&IF(AND($AC19<>"",$AC19>=BI$7,$AC19<BI$7+7),"G","")&IF(AND($AH19<>"",$AH19>=BI$7,$AH19<BI$7+7),"S","") | BJ19: =IF(AND($Y19<>"",$Y19>=BJ$7,$Y19<BJ$7+7),"I","")&IF(AND($Z19<>"",$Z19>=BJ$7,$Z19<BJ$7+7),"P","")&IF(AND($AA19<>"",$AA19>=BJ$7,$AA19<BJ$7+7),"T","")&IF(AND($AB19<>"",$AB19>=BJ$7,$AB19<BJ$7+7),"H","")&IF(AND($AC19<>"",$AC19>=BJ$7,$AC19<BJ$7+7),"G","")&IF(AND($AH19<>"",$AH19>=BJ$7,$AH19<BJ$7+7),"S","") | BK19: =IF(AND($Y19<>"",$Y19>=BK$7,$Y19<BK$7+7),"I","")&IF(AND($Z19<>"",$Z19>=BK$7,$Z19<BK$7+7),"P","")&IF(AND($AA19<>"",$AA19>=BK$7,$AA19<BK$7+7),"T","")&IF(AND($AB19<>"",$AB19>=BK$7,$AB19<BK$7+7),"H","")&IF(AND($AC19<>"",$AC19>=BK$7,$AC19<BK$7+7),"G","")&IF(AND($AH19<>"",$AH19>=BK$7,$AH19<BK$7+7),"S","") | BL19: =IF(AND($Y19<>"",$Y19>=BL$7,$Y19<BL$7+7),"I","")&IF(AND($Z19<>"",$Z19>=BL$7,$Z19<BL$7+7),"P","")&IF(AND($AA19<>"",$AA19>=BL$7,$AA19<BL$7+7),"T","")&IF(AND($AB19<>"",$AB19>=BL$7,$AB19<BL$7+7),"H","")&IF(AND($AC19<>"",$AC19>=BL$7,$AC19<BL$7+7),"G","")&IF(AND($AH19<>"",$AH19>=BL$7,$AH19<BL$7+7),"S","") -> I | BM19: =IF(AND($Y19<>"",$Y19>=BM$7,$Y19<BM$7+7),"I","")&IF(AND($Z19<>"",$Z19>=BM$7,$Z19<BM$7+7),"P","")&IF(AND($AA19<>"",$AA19>=BM$7,$AA19<BM$7+7),"T","")&IF(AND($AB19<>"",$AB19>=BM$7,$AB19<BM$7+7),"H","")&IF(AND($AC19<>"",$AC19>=BM$7,$AC19<BM$7+7),"G","")&IF(AND($AH19<>"",$AH19>=BM$7,$AH19<BM$7+7),"S","") -> PTG | BN19: =IF(AND($Y19<>"",$Y19>=BN$7,$Y19<BN$7+7),"I","")&IF(AND($Z19<>"",$Z19>=BN$7,$Z19<BN$7+7),"P","")&IF(AND($AA19<>"",$AA19>=BN$7,$AA19<BN$7+7),"T","")&IF(AND($AB19<>"",$AB19>=BN$7,$AB19<BN$7+7),"H","")&IF(AND($AC19<>"",$AC19>=BN$7,$AC19<BN$7+7),"G","")&IF(AND($AH19<>"",$AH19>=BN$7,$AH19<BN$7+7),"S","") -> H | BO19: =IF(AND($Y19<>"",$Y19>=BO$7,$Y19<BO$7+7),"I","")&IF(AND($Z19<>"",$Z19>=BO$7,$Z19<BO$7+7),"P","")&IF(AND($AA19<>"",$AA19>=BO$7,$AA19<BO$7+7),"T","")&IF(AND($AB19<>"",$AB19>=BO$7,$AB19<BO$7+7),"H","")&IF(AND($AC19<>"",$AC19>=BO$7,$AC19<BO$7+7),"G","")&IF(AND($AH19<>"",$AH19>=BO$7,$AH19<BO$7+7),"S","") | ... DC19: =IF(AND($Y19<>"",$Y19>=DC$7,$Y19<DC$7+7),"I","")&IF(AND($Z19<>"",$Z19>=DC$7,$Z19<DC$7+7),"P","")&IF(AND($AA19<>"",$AA19>=DC$7,$AA19<DC$7+7),"T","")&IF(AND($AB19<>"",$AB19>=DC$7,$AB19<DC$7+7),"H","")&IF(AND($AC19<>"",$AC19>=DC$7,$AC19<DC$7+7),"G","")&IF(AND($AH19<>"",$AH19>=DC$7,$AH19<DC$7+7),"S","")
A20: P9-013 | B20: แม่แบบ ถังดินกลบ, กันย้อน HV, Inverter < 200 kVA | C20: (ตัวอย่าง) | D20: ตัวอย่าง | E20: ตย.13 | F20: 150.48 | G20: รอบ 9 | H20: =PROJ_START+RD_SPAN -> 46403 | I20: =H20+33 -> 46436 | J20: วศ.13 | K20: Admin | L20: 13 | M20: N | N20: =IF(ISNUMBER(อัปเดตรายสัปดาห์!$AF20),อัปเดตรายสัปดาห์!$AF20,"") | O20: =IF(ISNUMBER(อัปเดตรายสัปดาห์!$AH20),อัปเดตรายสัปดาห์!$AH20,"") | P20: =IF(ISNUMBER(อัปเดตรายสัปดาห์!$AG20),อัปเดตรายสัปดาห์!$AG20,IF(AND(ISNUMBER(TCRoof!$AC$20),N(TCRoof!$AC$20)<=ASOF),TCRoof!$AC$20,"")) | Q20: =IF(ISNUMBER(อัปเดตรายสัปดาห์!$AL20),อัปเดตรายสัปดาห์!$AL20,"") | R20: =IF(ISNUMBER(อัปเดตรายสัปดาห์!$Q20),อัปเดตรายสัปดาห์!$Q20,"") | S20: =IF(ISNUMBER(อัปเดตรายสัปดาห์!$R20),อัปเดตรายสัปดาห์!$R20,"") | T20: =IF(ISNUMBER(อัปเดตรายสัปดาห์!$S20),อัปเดตรายสัปดาห์!$S20,IF(อัปเดตรายสัปดาห์!$S20="Y",ASOF,"")) | U20: =IF(ISNUMBER(อัปเดตรายสัปดาห์!$T20),อัปเดตรายสัปดาห์!$T20,IF(อัปเดตรายสัปดาห์!$T20="Y",ASOF,"")) | V20: =IF(ISNUMBER(อัปเดตรายสัปดาห์!$U20),อัปเดตรายสัปดาห์!$U20,IF(อัปเดตรายสัปดาห์!$U20="Y",ASOF,"")) | W20: =IF(ISNUMBER(อัปเดตรายสัปดาห์!$N20),อัปเดตรายสัปดาห์!$N20,"") | X20: =IF(ISNUMBER(อัปเดตรายสัปดาห์!$V20),อัปเดตรายสัปดาห์!$V20,IF(AND(ISNUMBER(TCRoof!$AD$20),N(TCRoof!$AD$20)<=ASOF),TCRoof!$AD$20,"")) | Y20: =IF(N20<>"",N20,WORKDAY((ASOF+LEAD_INST+7*INT((AT20-0.01)/MAX(1,AU20)))-1,1,HOLIDAYS)) -> 46349 | Z20: =IF(O20<>"",O20,WORKDAY((MAX(AV20+7*INT((AW20-1)/MAX(1,AX20)),AV20+7*INT((AY20-1)/MAX(1,AZ20))))-1,1,HOLIDAYS)) -> 46356 | AA20: =IF(P20<>"",P20,WORKDAY((BA20+7*INT((BB20-1)/MAX(1,BC20)))-1,1,HOLIDAYS)) -> 46359 | AB20: =IF(Q20<>"",Q20,WORKDAY((MAX(AA20+BD20,ASOF+1))-1,1,HOLIDAYS)) -> 46367 | AC20: =IF(R20<>"",R20,WORKDAY((MAX(Y20,ASOF)+LAG_GRID)-1,1,HOLIDAYS)) -> 46356 | AD20: =IF(T20<>"",T20,WORKDAY((MAX(WORKDAY(MAX(AC20,N(S20)),REVIEW_WD,HOLIDAYS),ASOF+1))-1,1,HOLIDAYS)) -> 46379 | AE20: =IF(U20<>"",U20,WORKDAY((MAX(AD20,ASOF)+FEE_DAYS)-1,1,HOLIDAYS)) -> 46386 | AF20: =IF(V20<>"",V20,WORKDAY((MAX(AA20,Z20,AE20,IF(AG20="",0,AG20+REVIEW_PK2),ASOF)+LAG_INSREQ)-1,1,HOLIDAYS)) -> 46391 | AG20: =IF(M20<>"Y","",IF(W20<>"",W20,WORKDAY((MAX(Y20,ASOF)+LAG_GRID)-1,1,HOLIDAYS))) | AH20: =IF(X20<>"",X20,WORKDAY(AF20,INSPECT_WD,HOLIDAYS)) -> 46433 | AI20: =IF(H20="","",AB20-H20) -> -36 | AJ20: =IF(I20="","",AH20-I20) -> -3 | AK20: =IF(AND(ISNUMBER(N20),N(N20)<=ASOF),1,0)+IF(AND(ISNUMBER(O20),N(O20)<=ASOF),1,0)+IF(AND(ISNUMBER(P20),N(P20)<=ASOF),1,0)+IF(AND(ISNUMBER(Q20),N(Q20)<=ASOF),1,0)+IF(AND(ISNUMBER(R20),N(R20)<=ASOF),1,0)+IF(AND(ISNUMBER(U20),N(U20)<=ASOF),1,0)+IF(AND(ISNUMBER(X20),N(X20)<=ASOF),1,0) -> 0 | AL20: 7 | AM20: ='P9-013'!$J$4 -> 0 | AN20: =TRIM(IF(AND(ISNUMBER(O20),NOT(ISNUMBER(N20))),"กฟภ.ตรวจก่อนติดตั้ง, ","")&IF(AND(ISNUMBER(P20),NOT(ISNUMBER(N20))),"IEC ก่อนติดตั้ง, ","")&IF(AND(ISNUMBER(Q20),NOT(ISNUMBER(N20))),"ส่งมอบก่อนติดตั้ง, ","")&IF(AND(ISNUMBER(Q20),ISNUMBER(P20),N(Q20)<N(P20)),"ส่งมอบก่อน IEC, ","")&IF(AND(ISNUMBER(อัปเดตรายสัปดาห์!$AG20),ISNUMBER(TCRoof!$AC$20),ABS(N(อัปเดตรายสัปดาห์!$AG20)-N(TCRoof!$AC$20))>3),"IEC Excel≠แอป, ","")&IF(AND(ISNUMBER(อัปเดตรายสัปดาห์!$V20),ISNUMBER(TCRoof!$AD$20),ABS(N(อัปเดตรายสัปดาห์!$V20)-N(TCRoof!$AD$20))>3),"COD Excel≠แอป, ","")&IF(AND(ISNUMBER(อัปเดตรายสัปดาห์!$AF20),ISNUMBER(TCRoof!$AB$20),ABS(N(อัปเดตรายสัปดาห์!$AF20)-N(TCRoof!$AB$20))>3),"ติดตั้ง Excel≠แอป, ","")&IF(AND(ISNUMBER(N20),N(N20)>ASOF,OR(WEEKDAY(N(N20),2)>5,COUNTIF(HOLIDAYS,N(N20))>0)),"นัดดับไฟตรงวันหยุด, ","")&IF(AND(ISNUMBER(O20),N(O20)>ASOF,OR(WEEKDAY(N(O20),2)>5,COUNTIF(HOLIDAYS,N(O20))>0)),"นัด กฟภ.ตรงวันหยุด, ","")&IF(AND(ISNUMBER(P20),N(P20)>ASOF,OR(WEEKDAY(N(P20),2)>5,COUNTIF(HOLIDAYS,N(P20))>0)),"นัด IECตรงวันหยุด, ","")&IF(AND(ISNUMBER(X20),N(X20)>ASOF,OR(WEEKDAY(N(X20),2)>5,COUNTIF(HOLIDAYS,N(X20))>0)),"นัด Syncตรงวันหยุด, ","")) | AO20: =SUMIFS(CR_COD,CR_ST,A20,CR_STAT,"อนุมัติ")+SUMIFS(CR_COD,CR_ST,"ทั้งเฟส",CR_STAT,"อนุมัติ")+SUMIFS(CR_COD,CR_ST,"ผรม. "&L20,CR_STAT,"อนุมัติ")+SUMIFS(CR_COD,CR_ST,"เขต "&E20,CR_STAT,"อนุมัติ") -> 0 | AP20: =IF(NOT(ISNUMBER(AJ20)),"",MAX(0,AJ20-AO20)) -> 0 | AQ20: =COUNTIF(RW_ST,A20) -> 0 | AR20: =IF(ISNUMBER(TCRoof!$I$20),TCRoof!$I$20,"") | AS20: =IF(ISNUMBER(TCRoof!$H$20),TCRoof!$H$20,"") | AT20: =IF(N20<>"","",SUMIFS($F$8:$F$27,$L$8:$L$27,L20,$N$8:$N$27,"",$H$8:$H$27,"<"&H20)+SUMIFS($F$8:$F$27,$L$8:$L$27,L20,$N$8:$N$27,"",$H$8:$H$27,H20,$A$8:$A$27,"<="&A20)+SUMIFS($F$8:$F$27,$L$8:$L$27,L20,$N$8:$N$27,">"&ASOF)) -> 150.48 | AU20: =IFERROR(VLOOKUP(L20,TEAM_TBL,2,0)*VLOOKUP(L20,TEAM_TBL,3,0),150) -> 150 | AV20: =IF(O20<>"","",MAX(Y20+LAG_PEA,ASOF+LAG_PEA)) -> 46356 | AW20: =IF(O20<>"","",COUNTIFS($E$8:$E$27,E20,$AV$8:$AV$27,"<"&AV20)+COUNTIFS($E$8:$E$27,E20,$AV$8:$AV$27,AV20,$A$8:$A$27,"<"&A20)+COUNTIFS($E$8:$E$27,E20,$O$8:$O$27,">"&ASOF)+1) -> 1 | AX20: =IFERROR(VLOOKUP(E20,ZONE_TBL,2,0),CAP_PEA) -> 3 | AY20: =IF(O20<>"","",COUNTIFS($J$8:$J$27,J20,$AV$8:$AV$27,"<"&AV20)+COUNTIFS($J$8:$J$27,J20,$AV$8:$AV$27,AV20,$A$8:$A$27,"<"&A20)+COUNTIFS($J$8:$J$27,J20,$O$8:$O$27,">"&ASOF)+1) -> 1 | AZ20: =IFERROR(VLOOKUP(J20,ENG_TBL,2,0),ENG_CAP) -> 3 | BA20: =IF(P20<>"","",MAX(Z20+LAG_IEC,ASOF+1)) -> 46359 | BB20: =IF(P20<>"","",COUNTIFS($L$8:$L$27,L20,$BA$8:$BA$27,"<"&BA20)+COUNTIFS($L$8:$L$27,L20,$BA$8:$BA$27,BA20,$A$8:$A$27,"<"&A20)+COUNTIFS($L$8:$L$27,L20,$P$8:$P$27,">"&ASOF)+1) -> 1 | BC20: =IFERROR(VLOOKUP(L20,TEAM_TBL,4,0)*VLOOKUP(L20,TEAM_TBL,5,0),3) -> 3 | BD20: =IFERROR(VLOOKUP(L20,TEAM_TBL,6,0),LAG_HO) -> 7 | BE20: =IF(ISNUMBER(AW20),7*INT((AW20-1)/MAX(1,AX20)),"") -> 0 | BF20: =IF(ISNUMBER(AY20),7*INT((AY20-1)/MAX(1,AZ20)),"") -> 0 | BH20: =IF(AND($Y20<>"",$Y20>=BH$7,$Y20<BH$7+7),"I","")&IF(AND($Z20<>"",$Z20>=BH$7,$Z20<BH$7+7),"P","")&IF(AND($AA20<>"",$AA20>=BH$7,$AA20<BH$7+7),"T","")&IF(AND($AB20<>"",$AB20>=BH$7,$AB20<BH$7+7),"H","")&IF(AND($AC20<>"",$AC20>=BH$7,$AC20<BH$7+7),"G","")&IF(AND($AH20<>"",$AH20>=BH$7,$AH20<BH$7+7),"S","") | BI20: =IF(AND($Y20<>"",$Y20>=BI$7,$Y20<BI$7+7),"I","")&IF(AND($Z20<>"",$Z20>=BI$7,$Z20<BI$7+7),"P","")&IF(AND($AA20<>"",$AA20>=BI$7,$AA20<BI$7+7),"T","")&IF(AND($AB20<>"",$AB20>=BI$7,$AB20<BI$7+7),"H","")&IF(AND($AC20<>"",$AC20>=BI$7,$AC20<BI$7+7),"G","")&IF(AND($AH20<>"",$AH20>=BI$7,$AH20<BI$7+7),"S","") | BJ20: =IF(AND($Y20<>"",$Y20>=BJ$7,$Y20<BJ$7+7),"I","")&IF(AND($Z20<>"",$Z20>=BJ$7,$Z20<BJ$7+7),"P","")&IF(AND($AA20<>"",$AA20>=BJ$7,$AA20<BJ$7+7),"T","")&IF(AND($AB20<>"",$AB20>=BJ$7,$AB20<BJ$7+7),"H","")&IF(AND($AC20<>"",$AC20>=BJ$7,$AC20<BJ$7+7),"G","")&IF(AND($AH20<>"",$AH20>=BJ$7,$AH20<BJ$7+7),"S","") | BK20: =IF(AND($Y20<>"",$Y20>=BK$7,$Y20<BK$7+7),"I","")&IF(AND($Z20<>"",$Z20>=BK$7,$Z20<BK$7+7),"P","")&IF(AND($AA20<>"",$AA20>=BK$7,$AA20<BK$7+7),"T","")&IF(AND($AB20<>"",$AB20>=BK$7,$AB20<BK$7+7),"H","")&IF(AND($AC20<>"",$AC20>=BK$7,$AC20<BK$7+7),"G","")&IF(AND($AH20<>"",$AH20>=BK$7,$AH20<BK$7+7),"S","") | BL20: =IF(AND($Y20<>"",$Y20>=BL$7,$Y20<BL$7+7),"I","")&IF(AND($Z20<>"",$Z20>=BL$7,$Z20<BL$7+7),"P","")&IF(AND($AA20<>"",$AA20>=BL$7,$AA20<BL$7+7),"T","")&IF(AND($AB20<>"",$AB20>=BL$7,$AB20<BL$7+7),"H","")&IF(AND($AC20<>"",$AC20>=BL$7,$AC20<BL$7+7),"G","")&IF(AND($AH20<>"",$AH20>=BL$7,$AH20<BL$7+7),"S","") -> I | BM20: =IF(AND($Y20<>"",$Y20>=BM$7,$Y20<BM$7+7),"I","")&IF(AND($Z20<>"",$Z20>=BM$7,$Z20<BM$7+7),"P","")&IF(AND($AA20<>"",$AA20>=BM$7,$AA20<BM$7+7),"T","")&IF(AND($AB20<>"",$AB20>=BM$7,$AB20<BM$7+7),"H","")&IF(AND($AC20<>"",$AC20>=BM$7,$AC20<BM$7+7),"G","")&IF(AND($AH20<>"",$AH20>=BM$7,$AH20<BM$7+7),"S","") -> PTG | BN20: =IF(AND($Y20<>"",$Y20>=BN$7,$Y20<BN$7+7),"I","")&IF(AND($Z20<>"",$Z20>=BN$7,$Z20<BN$7+7),"P","")&IF(AND($AA20<>"",$AA20>=BN$7,$AA20<BN$7+7),"T","")&IF(AND($AB20<>"",$AB20>=BN$7,$AB20<BN$7+7),"H","")&IF(AND($AC20<>"",$AC20>=BN$7,$AC20<BN$7+7),"G","")&IF(AND($AH20<>"",$AH20>=BN$7,$AH20<BN$7+7),"S","") -> H | BO20: =IF(AND($Y20<>"",$Y20>=BO$7,$Y20<BO$7+7),"I","")&IF(AND($Z20<>"",$Z20>=BO$7,$Z20<BO$7+7),"P","")&IF(AND($AA20<>"",$AA20>=BO$7,$AA20<BO$7+7),"T","")&IF(AND($AB20<>"",$AB20>=BO$7,$AB20<BO$7+7),"H","")&IF(AND($AC20<>"",$AC20>=BO$7,$AC20<BO$7+7),"G","")&IF(AND($AH20<>"",$AH20>=BO$7,$AH20<BO$7+7),"S","") | ... DC20: =IF(AND($Y20<>"",$Y20>=DC$7,$Y20<DC$7+7),"I","")&IF(AND($Z20<>"",$Z20>=DC$7,$Z20<DC$7+7),"P","")&IF(AND($AA20<>"",$AA20>=DC$7,$AA20<DC$7+7),"T","")&IF(AND($AB20<>"",$AB20>=DC$7,$AB20<DC$7+7),"H","")&IF(AND($AC20<>"",$AC20>=DC$7,$AC20<DC$7+7),"G","")&IF(AND($AH20<>"",$AH20>=DC$7,$AH20<DC$7+7),"S","")
A21: P9-014 | B21: แม่แบบ ถังดินกลบ, กันย้อน HV, Inverter ≥ 200 kVA | C21: (ตัวอย่าง) | D21: ตัวอย่าง | E21: ตย.14 | F21: 280.44 | G21: รอบ 9 | H21: =PROJ_START+RD_SPAN -> 46403 | I21: =H21+33 -> 46436 | J21: วศ.14 | K21: Admin | L21: 14 | M21: Y | N21: =IF(ISNUMBER(อัปเดตรายสัปดาห์!$AF21),อัปเดตรายสัปดาห์!$AF21,"") | O21: =IF(ISNUMBER(อัปเดตรายสัปดาห์!$AH21),อัปเดตรายสัปดาห์!$AH21,"") | P21: =IF(ISNUMBER(อัปเดตรายสัปดาห์!$AG21),อัปเดตรายสัปดาห์!$AG21,IF(AND(ISNUMBER(TCRoof!$AC$21),N(TCRoof!$AC$21)<=ASOF),TCRoof!$AC$21,"")) | Q21: =IF(ISNUMBER(อัปเดตรายสัปดาห์!$AL21),อัปเดตรายสัปดาห์!$AL21,"") | R21: =IF(ISNUMBER(อัปเดตรายสัปดาห์!$Q21),อัปเดตรายสัปดาห์!$Q21,"") | S21: =IF(ISNUMBER(อัปเดตรายสัปดาห์!$R21),อัปเดตรายสัปดาห์!$R21,"") | T21: =IF(ISNUMBER(อัปเดตรายสัปดาห์!$S21),อัปเดตรายสัปดาห์!$S21,IF(อัปเดตรายสัปดาห์!$S21="Y",ASOF,"")) | U21: =IF(ISNUMBER(อัปเดตรายสัปดาห์!$T21),อัปเดตรายสัปดาห์!$T21,IF(อัปเดตรายสัปดาห์!$T21="Y",ASOF,"")) | V21: =IF(ISNUMBER(อัปเดตรายสัปดาห์!$U21),อัปเดตรายสัปดาห์!$U21,IF(อัปเดตรายสัปดาห์!$U21="Y",ASOF,"")) | W21: =IF(ISNUMBER(อัปเดตรายสัปดาห์!$N21),อัปเดตรายสัปดาห์!$N21,"") | X21: =IF(ISNUMBER(อัปเดตรายสัปดาห์!$V21),อัปเดตรายสัปดาห์!$V21,IF(AND(ISNUMBER(TCRoof!$AD$21),N(TCRoof!$AD$21)<=ASOF),TCRoof!$AD$21,"")) | Y21: =IF(N21<>"",N21,WORKDAY((ASOF+LEAD_INST+7*INT((AT21-0.01)/MAX(1,AU21)))-1,1,HOLIDAYS)) -> 46349 | Z21: =IF(O21<>"",O21,WORKDAY((MAX(AV21+7*INT((AW21-1)/MAX(1,AX21)),AV21+7*INT((AY21-1)/MAX(1,AZ21))))-1,1,HOLIDAYS)) -> 46356 | AA21: =IF(P21<>"",P21,WORKDAY((BA21+7*INT((BB21-1)/MAX(1,BC21)))-1,1,HOLIDAYS)) -> 46359 | AB21: =IF(Q21<>"",Q21,WORKDAY((MAX(AA21+BD21,ASOF+1))-1,1,HOLIDAYS)) -> 46367 | AC21: =IF(R21<>"",R21,WORKDAY((MAX(Y21,ASOF)+LAG_GRID)-1,1,HOLIDAYS)) -> 46356 | AD21: =IF(T21<>"",T21,WORKDAY((MAX(WORKDAY(MAX(AC21,N(S21)),REVIEW_WD,HOLIDAYS),ASOF+1))-1,1,HOLIDAYS)) -> 46379 | AE21: =IF(U21<>"",U21,WORKDAY((MAX(AD21,ASOF)+FEE_DAYS)-1,1,HOLIDAYS)) -> 46386 | AF21: =IF(V21<>"",V21,WORKDAY((MAX(AA21,Z21,AE21,IF(AG21="",0,AG21+REVIEW_PK2),ASOF)+LAG_INSREQ)-1,1,HOLIDAYS)) -> 46391 | AG21: =IF(M21<>"Y","",IF(W21<>"",W21,WORKDAY((MAX(Y21,ASOF)+LAG_GRID)-1,1,HOLIDAYS))) -> 46356 | AH21: =IF(X21<>"",X21,WORKDAY(AF21,INSPECT_WD,HOLIDAYS)) -> 46433 | AI21: =IF(H21="","",AB21-H21) -> -36 | AJ21: =IF(I21="","",AH21-I21) -> -3 | AK21: =IF(AND(ISNUMBER(N21),N(N21)<=ASOF),1,0)+IF(AND(ISNUMBER(O21),N(O21)<=ASOF),1,0)+IF(AND(ISNUMBER(P21),N(P21)<=ASOF),1,0)+IF(AND(ISNUMBER(Q21),N(Q21)<=ASOF),1,0)+IF(AND(ISNUMBER(R21),N(R21)<=ASOF),1,0)+IF(AND(ISNUMBER(U21),N(U21)<=ASOF),1,0)+IF(AND(ISNUMBER(X21),N(X21)<=ASOF),1,0)+IF(AND(ISNUMBER(W21),N(W21)<=ASOF),1,0) -> 0 | AL21: 8 | AM21: ='P9-014'!$J$4 -> 0 | AN21: =TRIM(IF(AND(ISNUMBER(O21),NOT(ISNUMBER(N21))),"กฟภ.ตรวจก่อนติดตั้ง, ","")&IF(AND(ISNUMBER(P21),NOT(ISNUMBER(N21))),"IEC ก่อนติดตั้ง, ","")&IF(AND(ISNUMBER(Q21),NOT(ISNUMBER(N21))),"ส่งมอบก่อนติดตั้ง, ","")&IF(AND(ISNUMBER(Q21),ISNUMBER(P21),N(Q21)<N(P21)),"ส่งมอบก่อน IEC, ","")&IF(AND(ISNUMBER(อัปเดตรายสัปดาห์!$AG21),ISNUMBER(TCRoof!$AC$21),ABS(N(อัปเดตรายสัปดาห์!$AG21)-N(TCRoof!$AC$21))>3),"IEC Excel≠แอป, ","")&IF(AND(ISNUMBER(อัปเดตรายสัปดาห์!$V21),ISNUMBER(TCRoof!$AD$21),ABS(N(อัปเดตรายสัปดาห์!$V21)-N(TCRoof!$AD$21))>3),"COD Excel≠แอป, ","")&IF(AND(ISNUMBER(อัปเดตรายสัปดาห์!$AF21),ISNUMBER(TCRoof!$AB$21),ABS(N(อัปเดตรายสัปดาห์!$AF21)-N(TCRoof!$AB$21))>3),"ติดตั้ง Excel≠แอป, ","")&IF(AND(ISNUMBER(N21),N(N21)>ASOF,OR(WEEKDAY(N(N21),2)>5,COUNTIF(HOLIDAYS,N(N21))>0)),"นัดดับไฟตรงวันหยุด, ","")&IF(AND(ISNUMBER(O21),N(O21)>ASOF,OR(WEEKDAY(N(O21),2)>5,COUNTIF(HOLIDAYS,N(O21))>0)),"นัด กฟภ.ตรงวันหยุด, ","")&IF(AND(ISNUMBER(P21),N(P21)>ASOF,OR(WEEKDAY(N(P21),2)>5,COUNTIF(HOLIDAYS,N(P21))>0)),"นัด IECตรงวันหยุด, ","")&IF(AND(ISNUMBER(X21),N(X21)>ASOF,OR(WEEKDAY(N(X21),2)>5,COUNTIF(HOLIDAYS,N(X21))>0)),"นัด Syncตรงวันหยุด, ","")) | AO21: =SUMIFS(CR_COD,CR_ST,A21,CR_STAT,"อนุมัติ")+SUMIFS(CR_COD,CR_ST,"ทั้งเฟส",CR_STAT,"อนุมัติ")+SUMIFS(CR_COD,CR_ST,"ผรม. "&L21,CR_STAT,"อนุมัติ")+SUMIFS(CR_COD,CR_ST,"เขต "&E21,CR_STAT,"อนุมัติ") -> 0 | AP21: =IF(NOT(ISNUMBER(AJ21)),"",MAX(0,AJ21-AO21)) -> 0 | AQ21: =COUNTIF(RW_ST,A21) -> 0 | AR21: =IF(ISNUMBER(TCRoof!$I$21),TCRoof!$I$21,"") | AS21: =IF(ISNUMBER(TCRoof!$H$21),TCRoof!$H$21,"") | AT21: =IF(N21<>"","",SUMIFS($F$8:$F$27,$L$8:$L$27,L21,$N$8:$N$27,"",$H$8:$H$27,"<"&H21)+SUMIFS($F$8:$F$27,$L$8:$L$27,L21,$N$8:$N$27,"",$H$8:$H$27,H21,$A$8:$A$27,"<="&A21)+SUMIFS($F$8:$F$27,$L$8:$L$27,L21,$N$8:$N$27,">"&ASOF)) -> 280.44 | AU21: =IFERROR(VLOOKUP(L21,TEAM_TBL,2,0)*VLOOKUP(L21,TEAM_TBL,3,0),150) -> 150 | AV21: =IF(O21<>"","",MAX(Y21+LAG_PEA,ASOF+LAG_PEA)) -> 46356 | AW21: =IF(O21<>"","",COUNTIFS($E$8:$E$27,E21,$AV$8:$AV$27,"<"&AV21)+COUNTIFS($E$8:$E$27,E21,$AV$8:$AV$27,AV21,$A$8:$A$27,"<"&A21)+COUNTIFS($E$8:$E$27,E21,$O$8:$O$27,">"&ASOF)+1) -> 1 | AX21: =IFERROR(VLOOKUP(E21,ZONE_TBL,2,0),CAP_PEA) -> 3 | AY21: =IF(O21<>"","",COUNTIFS($J$8:$J$27,J21,$AV$8:$AV$27,"<"&AV21)+COUNTIFS($J$8:$J$27,J21,$AV$8:$AV$27,AV21,$A$8:$A$27,"<"&A21)+COUNTIFS($J$8:$J$27,J21,$O$8:$O$27,">"&ASOF)+1) -> 1 | AZ21: =IFERROR(VLOOKUP(J21,ENG_TBL,2,0),ENG_CAP) -> 3 | BA21: =IF(P21<>"","",MAX(Z21+LAG_IEC,ASOF+1)) -> 46359 | BB21: =IF(P21<>"","",COUNTIFS($L$8:$L$27,L21,$BA$8:$BA$27,"<"&BA21)+COUNTIFS($L$8:$L$27,L21,$BA$8:$BA$27,BA21,$A$8:$A$27,"<"&A21)+COUNTIFS($L$8:$L$27,L21,$P$8:$P$27,">"&ASOF)+1) -> 1 | BC21: =IFERROR(VLOOKUP(L21,TEAM_TBL,4,0)*VLOOKUP(L21,TEAM_TBL,5,0),3) -> 3 | BD21: =IFERROR(VLOOKUP(L21,TEAM_TBL,6,0),LAG_HO) -> 7 | BE21: =IF(ISNUMBER(AW21),7*INT((AW21-1)/MAX(1,AX21)),"") -> 0 | BF21: =IF(ISNUMBER(AY21),7*INT((AY21-1)/MAX(1,AZ21)),"") -> 0 | BH21: =IF(AND($Y21<>"",$Y21>=BH$7,$Y21<BH$7+7),"I","")&IF(AND($Z21<>"",$Z21>=BH$7,$Z21<BH$7+7),"P","")&IF(AND($AA21<>"",$AA21>=BH$7,$AA21<BH$7+7),"T","")&IF(AND($AB21<>"",$AB21>=BH$7,$AB21<BH$7+7),"H","")&IF(AND($AC21<>"",$AC21>=BH$7,$AC21<BH$7+7),"G","")&IF(AND($AH21<>"",$AH21>=BH$7,$AH21<BH$7+7),"S","") | BI21: =IF(AND($Y21<>"",$Y21>=BI$7,$Y21<BI$7+7),"I","")&IF(AND($Z21<>"",$Z21>=BI$7,$Z21<BI$7+7),"P","")&IF(AND($AA21<>"",$AA21>=BI$7,$AA21<BI$7+7),"T","")&IF(AND($AB21<>"",$AB21>=BI$7,$AB21<BI$7+7),"H","")&IF(AND($AC21<>"",$AC21>=BI$7,$AC21<BI$7+7),"G","")&IF(AND($AH21<>"",$AH21>=BI$7,$AH21<BI$7+7),"S","") | BJ21: =IF(AND($Y21<>"",$Y21>=BJ$7,$Y21<BJ$7+7),"I","")&IF(AND($Z21<>"",$Z21>=BJ$7,$Z21<BJ$7+7),"P","")&IF(AND($AA21<>"",$AA21>=BJ$7,$AA21<BJ$7+7),"T","")&IF(AND($AB21<>"",$AB21>=BJ$7,$AB21<BJ$7+7),"H","")&IF(AND($AC21<>"",$AC21>=BJ$7,$AC21<BJ$7+7),"G","")&IF(AND($AH21<>"",$AH21>=BJ$7,$AH21<BJ$7+7),"S","") | BK21: =IF(AND($Y21<>"",$Y21>=BK$7,$Y21<BK$7+7),"I","")&IF(AND($Z21<>"",$Z21>=BK$7,$Z21<BK$7+7),"P","")&IF(AND($AA21<>"",$AA21>=BK$7,$AA21<BK$7+7),"T","")&IF(AND($AB21<>"",$AB21>=BK$7,$AB21<BK$7+7),"H","")&IF(AND($AC21<>"",$AC21>=BK$7,$AC21<BK$7+7),"G","")&IF(AND($AH21<>"",$AH21>=BK$7,$AH21<BK$7+7),"S","") | BL21: =IF(AND($Y21<>"",$Y21>=BL$7,$Y21<BL$7+7),"I","")&IF(AND($Z21<>"",$Z21>=BL$7,$Z21<BL$7+7),"P","")&IF(AND($AA21<>"",$AA21>=BL$7,$AA21<BL$7+7),"T","")&IF(AND($AB21<>"",$AB21>=BL$7,$AB21<BL$7+7),"H","")&IF(AND($AC21<>"",$AC21>=BL$7,$AC21<BL$7+7),"G","")&IF(AND($AH21<>"",$AH21>=BL$7,$AH21<BL$7+7),"S","") -> I | BM21: =IF(AND($Y21<>"",$Y21>=BM$7,$Y21<BM$7+7),"I","")&IF(AND($Z21<>"",$Z21>=BM$7,$Z21<BM$7+7),"P","")&IF(AND($AA21<>"",$AA21>=BM$7,$AA21<BM$7+7),"T","")&IF(AND($AB21<>"",$AB21>=BM$7,$AB21<BM$7+7),"H","")&IF(AND($AC21<>"",$AC21>=BM$7,$AC21<BM$7+7),"G","")&IF(AND($AH21<>"",$AH21>=BM$7,$AH21<BM$7+7),"S","") -> PTG | BN21: =IF(AND($Y21<>"",$Y21>=BN$7,$Y21<BN$7+7),"I","")&IF(AND($Z21<>"",$Z21>=BN$7,$Z21<BN$7+7),"P","")&IF(AND($AA21<>"",$AA21>=BN$7,$AA21<BN$7+7),"T","")&IF(AND($AB21<>"",$AB21>=BN$7,$AB21<BN$7+7),"H","")&IF(AND($AC21<>"",$AC21>=BN$7,$AC21<BN$7+7),"G","")&IF(AND($AH21<>"",$AH21>=BN$7,$AH21<BN$7+7),"S","") -> H | BO21: =IF(AND($Y21<>"",$Y21>=BO$7,$Y21<BO$7+7),"I","")&IF(AND($Z21<>"",$Z21>=BO$7,$Z21<BO$7+7),"P","")&IF(AND($AA21<>"",$AA21>=BO$7,$AA21<BO$7+7),"T","")&IF(AND($AB21<>"",$AB21>=BO$7,$AB21<BO$7+7),"H","")&IF(AND($AC21<>"",$AC21>=BO$7,$AC21<BO$7+7),"G","")&IF(AND($AH21<>"",$AH21>=BO$7,$AH21<BO$7+7),"S","") | ... DC21: =IF(AND($Y21<>"",$Y21>=DC$7,$Y21<DC$7+7),"I","")&IF(AND($Z21<>"",$Z21>=DC$7,$Z21<DC$7+7),"P","")&IF(AND($AA21<>"",$AA21>=DC$7,$AA21<DC$7+7),"T","")&IF(AND($AB21<>"",$AB21>=DC$7,$AB21<DC$7+7),"H","")&IF(AND($AC21<>"",$AC21>=DC$7,$AC21<DC$7+7),"G","")&IF(AND($AH21<>"",$AH21>=DC$7,$AH21<DC$7+7),"S","")
A22: P9-015 | B22: แม่แบบ ถังดินกลบ, กันย้อน LV, Inverter < 200 kVA | C22: (ตัวอย่าง) | D22: ตัวอย่าง | E22: ตย.15 | F22: 150.48 | G22: รอบ 9 | H22: =PROJ_START+RD_SPAN -> 46403 | I22: =H22+33 -> 46436 | J22: วศ.15 | K22: Admin | L22: 15 | M22: N | N22: =IF(ISNUMBER(อัปเดตรายสัปดาห์!$AF22),อัปเดตรายสัปดาห์!$AF22,"") | O22: =IF(ISNUMBER(อัปเดตรายสัปดาห์!$AH22),อัปเดตรายสัปดาห์!$AH22,"") | P22: =IF(ISNUMBER(อัปเดตรายสัปดาห์!$AG22),อัปเดตรายสัปดาห์!$AG22,IF(AND(ISNUMBER(TCRoof!$AC$22),N(TCRoof!$AC$22)<=ASOF),TCRoof!$AC$22,"")) | Q22: =IF(ISNUMBER(อัปเดตรายสัปดาห์!$AL22),อัปเดตรายสัปดาห์!$AL22,"") | R22: =IF(ISNUMBER(อัปเดตรายสัปดาห์!$Q22),อัปเดตรายสัปดาห์!$Q22,"") | S22: =IF(ISNUMBER(อัปเดตรายสัปดาห์!$R22),อัปเดตรายสัปดาห์!$R22,"") | T22: =IF(ISNUMBER(อัปเดตรายสัปดาห์!$S22),อัปเดตรายสัปดาห์!$S22,IF(อัปเดตรายสัปดาห์!$S22="Y",ASOF,"")) | U22: =IF(ISNUMBER(อัปเดตรายสัปดาห์!$T22),อัปเดตรายสัปดาห์!$T22,IF(อัปเดตรายสัปดาห์!$T22="Y",ASOF,"")) | V22: =IF(ISNUMBER(อัปเดตรายสัปดาห์!$U22),อัปเดตรายสัปดาห์!$U22,IF(อัปเดตรายสัปดาห์!$U22="Y",ASOF,"")) | W22: =IF(ISNUMBER(อัปเดตรายสัปดาห์!$N22),อัปเดตรายสัปดาห์!$N22,"") | X22: =IF(ISNUMBER(อัปเดตรายสัปดาห์!$V22),อัปเดตรายสัปดาห์!$V22,IF(AND(ISNUMBER(TCRoof!$AD$22),N(TCRoof!$AD$22)<=ASOF),TCRoof!$AD$22,"")) | Y22: =IF(N22<>"",N22,WORKDAY((ASOF+LEAD_INST+7*INT((AT22-0.01)/MAX(1,AU22)))-1,1,HOLIDAYS)) -> 46349 | Z22: =IF(O22<>"",O22,WORKDAY((MAX(AV22+7*INT((AW22-1)/MAX(1,AX22)),AV22+7*INT((AY22-1)/MAX(1,AZ22))))-1,1,HOLIDAYS)) -> 46356 | AA22: =IF(P22<>"",P22,WORKDAY((BA22+7*INT((BB22-1)/MAX(1,BC22)))-1,1,HOLIDAYS)) -> 46359 | AB22: =IF(Q22<>"",Q22,WORKDAY((MAX(AA22+BD22,ASOF+1))-1,1,HOLIDAYS)) -> 46367 | AC22: =IF(R22<>"",R22,WORKDAY((MAX(Y22,ASOF)+LAG_GRID)-1,1,HOLIDAYS)) -> 46356 | AD22: =IF(T22<>"",T22,WORKDAY((MAX(WORKDAY(MAX(AC22,N(S22)),REVIEW_WD,HOLIDAYS),ASOF+1))-1,1,HOLIDAYS)) -> 46379 | AE22: =IF(U22<>"",U22,WORKDAY((MAX(AD22,ASOF)+FEE_DAYS)-1,1,HOLIDAYS)) -> 46386 | AF22: =IF(V22<>"",V22,WORKDAY((MAX(AA22,Z22,AE22,IF(AG22="",0,AG22+REVIEW_PK2),ASOF)+LAG_INSREQ)-1,1,HOLIDAYS)) -> 46391 | AG22: =IF(M22<>"Y","",IF(W22<>"",W22,WORKDAY((MAX(Y22,ASOF)+LAG_GRID)-1,1,HOLIDAYS))) | AH22: =IF(X22<>"",X22,WORKDAY(AF22,INSPECT_WD,HOLIDAYS)) -> 46433 | AI22: =IF(H22="","",AB22-H22) -> -36 | AJ22: =IF(I22="","",AH22-I22) -> -3 | AK22: =IF(AND(ISNUMBER(N22),N(N22)<=ASOF),1,0)+IF(AND(ISNUMBER(O22),N(O22)<=ASOF),1,0)+IF(AND(ISNUMBER(P22),N(P22)<=ASOF),1,0)+IF(AND(ISNUMBER(Q22),N(Q22)<=ASOF),1,0)+IF(AND(ISNUMBER(R22),N(R22)<=ASOF),1,0)+IF(AND(ISNUMBER(U22),N(U22)<=ASOF),1,0)+IF(AND(ISNUMBER(X22),N(X22)<=ASOF),1,0) -> 0 | AL22: 7 | AM22: ='P9-015'!$J$4 -> 0 | AN22: =TRIM(IF(AND(ISNUMBER(O22),NOT(ISNUMBER(N22))),"กฟภ.ตรวจก่อนติดตั้ง, ","")&IF(AND(ISNUMBER(P22),NOT(ISNUMBER(N22))),"IEC ก่อนติดตั้ง, ","")&IF(AND(ISNUMBER(Q22),NOT(ISNUMBER(N22))),"ส่งมอบก่อนติดตั้ง, ","")&IF(AND(ISNUMBER(Q22),ISNUMBER(P22),N(Q22)<N(P22)),"ส่งมอบก่อน IEC, ","")&IF(AND(ISNUMBER(อัปเดตรายสัปดาห์!$AG22),ISNUMBER(TCRoof!$AC$22),ABS(N(อัปเดตรายสัปดาห์!$AG22)-N(TCRoof!$AC$22))>3),"IEC Excel≠แอป, ","")&IF(AND(ISNUMBER(อัปเดตรายสัปดาห์!$V22),ISNUMBER(TCRoof!$AD$22),ABS(N(อัปเดตรายสัปดาห์!$V22)-N(TCRoof!$AD$22))>3),"COD Excel≠แอป, ","")&IF(AND(ISNUMBER(อัปเดตรายสัปดาห์!$AF22),ISNUMBER(TCRoof!$AB$22),ABS(N(อัปเดตรายสัปดาห์!$AF22)-N(TCRoof!$AB$22))>3),"ติดตั้ง Excel≠แอป, ","")&IF(AND(ISNUMBER(N22),N(N22)>ASOF,OR(WEEKDAY(N(N22),2)>5,COUNTIF(HOLIDAYS,N(N22))>0)),"นัดดับไฟตรงวันหยุด, ","")&IF(AND(ISNUMBER(O22),N(O22)>ASOF,OR(WEEKDAY(N(O22),2)>5,COUNTIF(HOLIDAYS,N(O22))>0)),"นัด กฟภ.ตรงวันหยุด, ","")&IF(AND(ISNUMBER(P22),N(P22)>ASOF,OR(WEEKDAY(N(P22),2)>5,COUNTIF(HOLIDAYS,N(P22))>0)),"นัด IECตรงวันหยุด, ","")&IF(AND(ISNUMBER(X22),N(X22)>ASOF,OR(WEEKDAY(N(X22),2)>5,COUNTIF(HOLIDAYS,N(X22))>0)),"นัด Syncตรงวันหยุด, ","")) | AO22: =SUMIFS(CR_COD,CR_ST,A22,CR_STAT,"อนุมัติ")+SUMIFS(CR_COD,CR_ST,"ทั้งเฟส",CR_STAT,"อนุมัติ")+SUMIFS(CR_COD,CR_ST,"ผรม. "&L22,CR_STAT,"อนุมัติ")+SUMIFS(CR_COD,CR_ST,"เขต "&E22,CR_STAT,"อนุมัติ") -> 0 | AP22: =IF(NOT(ISNUMBER(AJ22)),"",MAX(0,AJ22-AO22)) -> 0 | AQ22: =COUNTIF(RW_ST,A22) -> 0 | AR22: =IF(ISNUMBER(TCRoof!$I$22),TCRoof!$I$22,"") | AS22: =IF(ISNUMBER(TCRoof!$H$22),TCRoof!$H$22,"") | AT22: =IF(N22<>"","",SUMIFS($F$8:$F$27,$L$8:$L$27,L22,$N$8:$N$27,"",$H$8:$H$27,"<"&H22)+SUMIFS($F$8:$F$27,$L$8:$L$27,L22,$N$8:$N$27,"",$H$8:$H$27,H22,$A$8:$A$27,"<="&A22)+SUMIFS($F$8:$F$27,$L$8:$L$27,L22,$N$8:$N$27,">"&ASOF)) -> 150.48 | AU22: =IFERROR(VLOOKUP(L22,TEAM_TBL,2,0)*VLOOKUP(L22,TEAM_TBL,3,0),150) -> 150 | AV22: =IF(O22<>"","",MAX(Y22+LAG_PEA,ASOF+LAG_PEA)) -> 46356 | AW22: =IF(O22<>"","",COUNTIFS($E$8:$E$27,E22,$AV$8:$AV$27,"<"&AV22)+COUNTIFS($E$8:$E$27,E22,$AV$8:$AV$27,AV22,$A$8:$A$27,"<"&A22)+COUNTIFS($E$8:$E$27,E22,$O$8:$O$27,">"&ASOF)+1) -> 1 | AX22: =IFERROR(VLOOKUP(E22,ZONE_TBL,2,0),CAP_PEA) -> 3 | AY22: =IF(O22<>"","",COUNTIFS($J$8:$J$27,J22,$AV$8:$AV$27,"<"&AV22)+COUNTIFS($J$8:$J$27,J22,$AV$8:$AV$27,AV22,$A$8:$A$27,"<"&A22)+COUNTIFS($J$8:$J$27,J22,$O$8:$O$27,">"&ASOF)+1) -> 1 | AZ22: =IFERROR(VLOOKUP(J22,ENG_TBL,2,0),ENG_CAP) -> 3 | BA22: =IF(P22<>"","",MAX(Z22+LAG_IEC,ASOF+1)) -> 46359 | BB22: =IF(P22<>"","",COUNTIFS($L$8:$L$27,L22,$BA$8:$BA$27,"<"&BA22)+COUNTIFS($L$8:$L$27,L22,$BA$8:$BA$27,BA22,$A$8:$A$27,"<"&A22)+COUNTIFS($L$8:$L$27,L22,$P$8:$P$27,">"&ASOF)+1) -> 1 | BC22: =IFERROR(VLOOKUP(L22,TEAM_TBL,4,0)*VLOOKUP(L22,TEAM_TBL,5,0),3) -> 3 | BD22: =IFERROR(VLOOKUP(L22,TEAM_TBL,6,0),LAG_HO) -> 7 | BE22: =IF(ISNUMBER(AW22),7*INT((AW22-1)/MAX(1,AX22)),"") -> 0 | BF22: =IF(ISNUMBER(AY22),7*INT((AY22-1)/MAX(1,AZ22)),"") -> 0 | BH22: =IF(AND($Y22<>"",$Y22>=BH$7,$Y22<BH$7+7),"I","")&IF(AND($Z22<>"",$Z22>=BH$7,$Z22<BH$7+7),"P","")&IF(AND($AA22<>"",$AA22>=BH$7,$AA22<BH$7+7),"T","")&IF(AND($AB22<>"",$AB22>=BH$7,$AB22<BH$7+7),"H","")&IF(AND($AC22<>"",$AC22>=BH$7,$AC22<BH$7+7),"G","")&IF(AND($AH22<>"",$AH22>=BH$7,$AH22<BH$7+7),"S","") | BI22: =IF(AND($Y22<>"",$Y22>=BI$7,$Y22<BI$7+7),"I","")&IF(AND($Z22<>"",$Z22>=BI$7,$Z22<BI$7+7),"P","")&IF(AND($AA22<>"",$AA22>=BI$7,$AA22<BI$7+7),"T","")&IF(AND($AB22<>"",$AB22>=BI$7,$AB22<BI$7+7),"H","")&IF(AND($AC22<>"",$AC22>=BI$7,$AC22<BI$7+7),"G","")&IF(AND($AH22<>"",$AH22>=BI$7,$AH22<BI$7+7),"S","") | BJ22: =IF(AND($Y22<>"",$Y22>=BJ$7,$Y22<BJ$7+7),"I","")&IF(AND($Z22<>"",$Z22>=BJ$7,$Z22<BJ$7+7),"P","")&IF(AND($AA22<>"",$AA22>=BJ$7,$AA22<BJ$7+7),"T","")&IF(AND($AB22<>"",$AB22>=BJ$7,$AB22<BJ$7+7),"H","")&IF(AND($AC22<>"",$AC22>=BJ$7,$AC22<BJ$7+7),"G","")&IF(AND($AH22<>"",$AH22>=BJ$7,$AH22<BJ$7+7),"S","") | BK22: =IF(AND($Y22<>"",$Y22>=BK$7,$Y22<BK$7+7),"I","")&IF(AND($Z22<>"",$Z22>=BK$7,$Z22<BK$7+7),"P","")&IF(AND($AA22<>"",$AA22>=BK$7,$AA22<BK$7+7),"T","")&IF(AND($AB22<>"",$AB22>=BK$7,$AB22<BK$7+7),"H","")&IF(AND($AC22<>"",$AC22>=BK$7,$AC22<BK$7+7),"G","")&IF(AND($AH22<>"",$AH22>=BK$7,$AH22<BK$7+7),"S","") | BL22: =IF(AND($Y22<>"",$Y22>=BL$7,$Y22<BL$7+7),"I","")&IF(AND($Z22<>"",$Z22>=BL$7,$Z22<BL$7+7),"P","")&IF(AND($AA22<>"",$AA22>=BL$7,$AA22<BL$7+7),"T","")&IF(AND($AB22<>"",$AB22>=BL$7,$AB22<BL$7+7),"H","")&IF(AND($AC22<>"",$AC22>=BL$7,$AC22<BL$7+7),"G","")&IF(AND($AH22<>"",$AH22>=BL$7,$AH22<BL$7+7),"S","") -> I | BM22: =IF(AND($Y22<>"",$Y22>=BM$7,$Y22<BM$7+7),"I","")&IF(AND($Z22<>"",$Z22>=BM$7,$Z22<BM$7+7),"P","")&IF(AND($AA22<>"",$AA22>=BM$7,$AA22<BM$7+7),"T","")&IF(AND($AB22<>"",$AB22>=BM$7,$AB22<BM$7+7),"H","")&IF(AND($AC22<>"",$AC22>=BM$7,$AC22<BM$7+7),"G","")&IF(AND($AH22<>"",$AH22>=BM$7,$AH22<BM$7+7),"S","") -> PTG | BN22: =IF(AND($Y22<>"",$Y22>=BN$7,$Y22<BN$7+7),"I","")&IF(AND($Z22<>"",$Z22>=BN$7,$Z22<BN$7+7),"P","")&IF(AND($AA22<>"",$AA22>=BN$7,$AA22<BN$7+7),"T","")&IF(AND($AB22<>"",$AB22>=BN$7,$AB22<BN$7+7),"H","")&IF(AND($AC22<>"",$AC22>=BN$7,$AC22<BN$7+7),"G","")&IF(AND($AH22<>"",$AH22>=BN$7,$AH22<BN$7+7),"S","") -> H | BO22: =IF(AND($Y22<>"",$Y22>=BO$7,$Y22<BO$7+7),"I","")&IF(AND($Z22<>"",$Z22>=BO$7,$Z22<BO$7+7),"P","")&IF(AND($AA22<>"",$AA22>=BO$7,$AA22<BO$7+7),"T","")&IF(AND($AB22<>"",$AB22>=BO$7,$AB22<BO$7+7),"H","")&IF(AND($AC22<>"",$AC22>=BO$7,$AC22<BO$7+7),"G","")&IF(AND($AH22<>"",$AH22>=BO$7,$AH22<BO$7+7),"S","") | ... DC22: =IF(AND($Y22<>"",$Y22>=DC$7,$Y22<DC$7+7),"I","")&IF(AND($Z22<>"",$Z22>=DC$7,$Z22<DC$7+7),"P","")&IF(AND($AA22<>"",$AA22>=DC$7,$AA22<DC$7+7),"T","")&IF(AND($AB22<>"",$AB22>=DC$7,$AB22<DC$7+7),"H","")&IF(AND($AC22<>"",$AC22>=DC$7,$AC22<DC$7+7),"G","")&IF(AND($AH22<>"",$AH22>=DC$7,$AH22<DC$7+7),"S","")
A23: P9-016 | B23: แม่แบบ ถังดินกลบ, กันย้อน LV, Inverter ≥ 200 kVA | C23: (ตัวอย่าง) | D23: ตัวอย่าง | E23: ตย.16 | F23: 280.44 | G23: รอบ 9 | H23: =PROJ_START+RD_SPAN -> 46403 | I23: =H23+33 -> 46436 | J23: วศ.16 | K23: Admin | L23: 16 | M23: Y | N23: =IF(ISNUMBER(อัปเดตรายสัปดาห์!$AF23),อัปเดตรายสัปดาห์!$AF23,"") | O23: =IF(ISNUMBER(อัปเดตรายสัปดาห์!$AH23),อัปเดตรายสัปดาห์!$AH23,"") | P23: =IF(ISNUMBER(อัปเดตรายสัปดาห์!$AG23),อัปเดตรายสัปดาห์!$AG23,IF(AND(ISNUMBER(TCRoof!$AC$23),N(TCRoof!$AC$23)<=ASOF),TCRoof!$AC$23,"")) | Q23: =IF(ISNUMBER(อัปเดตรายสัปดาห์!$AL23),อัปเดตรายสัปดาห์!$AL23,"") | R23: =IF(ISNUMBER(อัปเดตรายสัปดาห์!$Q23),อัปเดตรายสัปดาห์!$Q23,"") | S23: =IF(ISNUMBER(อัปเดตรายสัปดาห์!$R23),อัปเดตรายสัปดาห์!$R23,"") | T23: =IF(ISNUMBER(อัปเดตรายสัปดาห์!$S23),อัปเดตรายสัปดาห์!$S23,IF(อัปเดตรายสัปดาห์!$S23="Y",ASOF,"")) | U23: =IF(ISNUMBER(อัปเดตรายสัปดาห์!$T23),อัปเดตรายสัปดาห์!$T23,IF(อัปเดตรายสัปดาห์!$T23="Y",ASOF,"")) | V23: =IF(ISNUMBER(อัปเดตรายสัปดาห์!$U23),อัปเดตรายสัปดาห์!$U23,IF(อัปเดตรายสัปดาห์!$U23="Y",ASOF,"")) | W23: =IF(ISNUMBER(อัปเดตรายสัปดาห์!$N23),อัปเดตรายสัปดาห์!$N23,"") | X23: =IF(ISNUMBER(อัปเดตรายสัปดาห์!$V23),อัปเดตรายสัปดาห์!$V23,IF(AND(ISNUMBER(TCRoof!$AD$23),N(TCRoof!$AD$23)<=ASOF),TCRoof!$AD$23,"")) | Y23: =IF(N23<>"",N23,WORKDAY((ASOF+LEAD_INST+7*INT((AT23-0.01)/MAX(1,AU23)))-1,1,HOLIDAYS)) -> 46349 | Z23: =IF(O23<>"",O23,WORKDAY((MAX(AV23+7*INT((AW23-1)/MAX(1,AX23)),AV23+7*INT((AY23-1)/MAX(1,AZ23))))-1,1,HOLIDAYS)) -> 46356 | AA23: =IF(P23<>"",P23,WORKDAY((BA23+7*INT((BB23-1)/MAX(1,BC23)))-1,1,HOLIDAYS)) -> 46359 | AB23: =IF(Q23<>"",Q23,WORKDAY((MAX(AA23+BD23,ASOF+1))-1,1,HOLIDAYS)) -> 46367 | AC23: =IF(R23<>"",R23,WORKDAY((MAX(Y23,ASOF)+LAG_GRID)-1,1,HOLIDAYS)) -> 46356 | AD23: =IF(T23<>"",T23,WORKDAY((MAX(WORKDAY(MAX(AC23,N(S23)),REVIEW_WD,HOLIDAYS),ASOF+1))-1,1,HOLIDAYS)) -> 46379 | AE23: =IF(U23<>"",U23,WORKDAY((MAX(AD23,ASOF)+FEE_DAYS)-1,1,HOLIDAYS)) -> 46386 | AF23: =IF(V23<>"",V23,WORKDAY((MAX(AA23,Z23,AE23,IF(AG23="",0,AG23+REVIEW_PK2),ASOF)+LAG_INSREQ)-1,1,HOLIDAYS)) -> 46391 | AG23: =IF(M23<>"Y","",IF(W23<>"",W23,WORKDAY((MAX(Y23,ASOF)+LAG_GRID)-1,1,HOLIDAYS))) -> 46356 | AH23: =IF(X23<>"",X23,WORKDAY(AF23,INSPECT_WD,HOLIDAYS)) -> 46433 | AI23: =IF(H23="","",AB23-H23) -> -36 | AJ23: =IF(I23="","",AH23-I23) -> -3 | AK23: =IF(AND(ISNUMBER(N23),N(N23)<=ASOF),1,0)+IF(AND(ISNUMBER(O23),N(O23)<=ASOF),1,0)+IF(AND(ISNUMBER(P23),N(P23)<=ASOF),1,0)+IF(AND(ISNUMBER(Q23),N(Q23)<=ASOF),1,0)+IF(AND(ISNUMBER(R23),N(R23)<=ASOF),1,0)+IF(AND(ISNUMBER(U23),N(U23)<=ASOF),1,0)+IF(AND(ISNUMBER(X23),N(X23)<=ASOF),1,0)+IF(AND(ISNUMBER(W23),N(W23)<=ASOF),1,0) -> 0 | AL23: 8 | AM23: ='P9-016'!$J$4 -> 0 | AN23: =TRIM(IF(AND(ISNUMBER(O23),NOT(ISNUMBER(N23))),"กฟภ.ตรวจก่อนติดตั้ง, ","")&IF(AND(ISNUMBER(P23),NOT(ISNUMBER(N23))),"IEC ก่อนติดตั้ง, ","")&IF(AND(ISNUMBER(Q23),NOT(ISNUMBER(N23))),"ส่งมอบก่อนติดตั้ง, ","")&IF(AND(ISNUMBER(Q23),ISNUMBER(P23),N(Q23)<N(P23)),"ส่งมอบก่อน IEC, ","")&IF(AND(ISNUMBER(อัปเดตรายสัปดาห์!$AG23),ISNUMBER(TCRoof!$AC$23),ABS(N(อัปเดตรายสัปดาห์!$AG23)-N(TCRoof!$AC$23))>3),"IEC Excel≠แอป, ","")&IF(AND(ISNUMBER(อัปเดตรายสัปดาห์!$V23),ISNUMBER(TCRoof!$AD$23),ABS(N(อัปเดตรายสัปดาห์!$V23)-N(TCRoof!$AD$23))>3),"COD Excel≠แอป, ","")&IF(AND(ISNUMBER(อัปเดตรายสัปดาห์!$AF23),ISNUMBER(TCRoof!$AB$23),ABS(N(อัปเดตรายสัปดาห์!$AF23)-N(TCRoof!$AB$23))>3),"ติดตั้ง Excel≠แอป, ","")&IF(AND(ISNUMBER(N23),N(N23)>ASOF,OR(WEEKDAY(N(N23),2)>5,COUNTIF(HOLIDAYS,N(N23))>0)),"นัดดับไฟตรงวันหยุด, ","")&IF(AND(ISNUMBER(O23),N(O23)>ASOF,OR(WEEKDAY(N(O23),2)>5,COUNTIF(HOLIDAYS,N(O23))>0)),"นัด กฟภ.ตรงวันหยุด, ","")&IF(AND(ISNUMBER(P23),N(P23)>ASOF,OR(WEEKDAY(N(P23),2)>5,COUNTIF(HOLIDAYS,N(P23))>0)),"นัด IECตรงวันหยุด, ","")&IF(AND(ISNUMBER(X23),N(X23)>ASOF,OR(WEEKDAY(N(X23),2)>5,COUNTIF(HOLIDAYS,N(X23))>0)),"นัด Syncตรงวันหยุด, ","")) | AO23: =SUMIFS(CR_COD,CR_ST,A23,CR_STAT,"อนุมัติ")+SUMIFS(CR_COD,CR_ST,"ทั้งเฟส",CR_STAT,"อนุมัติ")+SUMIFS(CR_COD,CR_ST,"ผรม. "&L23,CR_STAT,"อนุมัติ")+SUMIFS(CR_COD,CR_ST,"เขต "&E23,CR_STAT,"อนุมัติ") -> 0 | AP23: =IF(NOT(ISNUMBER(AJ23)),"",MAX(0,AJ23-AO23)) -> 0 | AQ23: =COUNTIF(RW_ST,A23) -> 0 | AR23: =IF(ISNUMBER(TCRoof!$I$23),TCRoof!$I$23,"") | AS23: =IF(ISNUMBER(TCRoof!$H$23),TCRoof!$H$23,"") | AT23: =IF(N23<>"","",SUMIFS($F$8:$F$27,$L$8:$L$27,L23,$N$8:$N$27,"",$H$8:$H$27,"<"&H23)+SUMIFS($F$8:$F$27,$L$8:$L$27,L23,$N$8:$N$27,"",$H$8:$H$27,H23,$A$8:$A$27,"<="&A23)+SUMIFS($F$8:$F$27,$L$8:$L$27,L23,$N$8:$N$27,">"&ASOF)) -> 280.44 | AU23: =IFERROR(VLOOKUP(L23,TEAM_TBL,2,0)*VLOOKUP(L23,TEAM_TBL,3,0),150) -> 150 | AV23: =IF(O23<>"","",MAX(Y23+LAG_PEA,ASOF+LAG_PEA)) -> 46356 | AW23: =IF(O23<>"","",COUNTIFS($E$8:$E$27,E23,$AV$8:$AV$27,"<"&AV23)+COUNTIFS($E$8:$E$27,E23,$AV$8:$AV$27,AV23,$A$8:$A$27,"<"&A23)+COUNTIFS($E$8:$E$27,E23,$O$8:$O$27,">"&ASOF)+1) -> 1 | AX23: =IFERROR(VLOOKUP(E23,ZONE_TBL,2,0),CAP_PEA) -> 3 | AY23: =IF(O23<>"","",COUNTIFS($J$8:$J$27,J23,$AV$8:$AV$27,"<"&AV23)+COUNTIFS($J$8:$J$27,J23,$AV$8:$AV$27,AV23,$A$8:$A$27,"<"&A23)+COUNTIFS($J$8:$J$27,J23,$O$8:$O$27,">"&ASOF)+1) -> 1 | AZ23: =IFERROR(VLOOKUP(J23,ENG_TBL,2,0),ENG_CAP) -> 3 | BA23: =IF(P23<>"","",MAX(Z23+LAG_IEC,ASOF+1)) -> 46359 | BB23: =IF(P23<>"","",COUNTIFS($L$8:$L$27,L23,$BA$8:$BA$27,"<"&BA23)+COUNTIFS($L$8:$L$27,L23,$BA$8:$BA$27,BA23,$A$8:$A$27,"<"&A23)+COUNTIFS($L$8:$L$27,L23,$P$8:$P$27,">"&ASOF)+1) -> 1 | BC23: =IFERROR(VLOOKUP(L23,TEAM_TBL,4,0)*VLOOKUP(L23,TEAM_TBL,5,0),3) -> 3 | BD23: =IFERROR(VLOOKUP(L23,TEAM_TBL,6,0),LAG_HO) -> 7 | BE23: =IF(ISNUMBER(AW23),7*INT((AW23-1)/MAX(1,AX23)),"") -> 0 | BF23: =IF(ISNUMBER(AY23),7*INT((AY23-1)/MAX(1,AZ23)),"") -> 0 | BH23: =IF(AND($Y23<>"",$Y23>=BH$7,$Y23<BH$7+7),"I","")&IF(AND($Z23<>"",$Z23>=BH$7,$Z23<BH$7+7),"P","")&IF(AND($AA23<>"",$AA23>=BH$7,$AA23<BH$7+7),"T","")&IF(AND($AB23<>"",$AB23>=BH$7,$AB23<BH$7+7),"H","")&IF(AND($AC23<>"",$AC23>=BH$7,$AC23<BH$7+7),"G","")&IF(AND($AH23<>"",$AH23>=BH$7,$AH23<BH$7+7),"S","") | BI23: =IF(AND($Y23<>"",$Y23>=BI$7,$Y23<BI$7+7),"I","")&IF(AND($Z23<>"",$Z23>=BI$7,$Z23<BI$7+7),"P","")&IF(AND($AA23<>"",$AA23>=BI$7,$AA23<BI$7+7),"T","")&IF(AND($AB23<>"",$AB23>=BI$7,$AB23<BI$7+7),"H","")&IF(AND($AC23<>"",$AC23>=BI$7,$AC23<BI$7+7),"G","")&IF(AND($AH23<>"",$AH23>=BI$7,$AH23<BI$7+7),"S","") | BJ23: =IF(AND($Y23<>"",$Y23>=BJ$7,$Y23<BJ$7+7),"I","")&IF(AND($Z23<>"",$Z23>=BJ$7,$Z23<BJ$7+7),"P","")&IF(AND($AA23<>"",$AA23>=BJ$7,$AA23<BJ$7+7),"T","")&IF(AND($AB23<>"",$AB23>=BJ$7,$AB23<BJ$7+7),"H","")&IF(AND($AC23<>"",$AC23>=BJ$7,$AC23<BJ$7+7),"G","")&IF(AND($AH23<>"",$AH23>=BJ$7,$AH23<BJ$7+7),"S","") | BK23: =IF(AND($Y23<>"",$Y23>=BK$7,$Y23<BK$7+7),"I","")&IF(AND($Z23<>"",$Z23>=BK$7,$Z23<BK$7+7),"P","")&IF(AND($AA23<>"",$AA23>=BK$7,$AA23<BK$7+7),"T","")&IF(AND($AB23<>"",$AB23>=BK$7,$AB23<BK$7+7),"H","")&IF(AND($AC23<>"",$AC23>=BK$7,$AC23<BK$7+7),"G","")&IF(AND($AH23<>"",$AH23>=BK$7,$AH23<BK$7+7),"S","") | BL23: =IF(AND($Y23<>"",$Y23>=BL$7,$Y23<BL$7+7),"I","")&IF(AND($Z23<>"",$Z23>=BL$7,$Z23<BL$7+7),"P","")&IF(AND($AA23<>"",$AA23>=BL$7,$AA23<BL$7+7),"T","")&IF(AND($AB23<>"",$AB23>=BL$7,$AB23<BL$7+7),"H","")&IF(AND($AC23<>"",$AC23>=BL$7,$AC23<BL$7+7),"G","")&IF(AND($AH23<>"",$AH23>=BL$7,$AH23<BL$7+7),"S","") -> I | BM23: =IF(AND($Y23<>"",$Y23>=BM$7,$Y23<BM$7+7),"I","")&IF(AND($Z23<>"",$Z23>=BM$7,$Z23<BM$7+7),"P","")&IF(AND($AA23<>"",$AA23>=BM$7,$AA23<BM$7+7),"T","")&IF(AND($AB23<>"",$AB23>=BM$7,$AB23<BM$7+7),"H","")&IF(AND($AC23<>"",$AC23>=BM$7,$AC23<BM$7+7),"G","")&IF(AND($AH23<>"",$AH23>=BM$7,$AH23<BM$7+7),"S","") -> PTG | BN23: =IF(AND($Y23<>"",$Y23>=BN$7,$Y23<BN$7+7),"I","")&IF(AND($Z23<>"",$Z23>=BN$7,$Z23<BN$7+7),"P","")&IF(AND($AA23<>"",$AA23>=BN$7,$AA23<BN$7+7),"T","")&IF(AND($AB23<>"",$AB23>=BN$7,$AB23<BN$7+7),"H","")&IF(AND($AC23<>"",$AC23>=BN$7,$AC23<BN$7+7),"G","")&IF(AND($AH23<>"",$AH23>=BN$7,$AH23<BN$7+7),"S","") -> H | BO23: =IF(AND($Y23<>"",$Y23>=BO$7,$Y23<BO$7+7),"I","")&IF(AND($Z23<>"",$Z23>=BO$7,$Z23<BO$7+7),"P","")&IF(AND($AA23<>"",$AA23>=BO$7,$AA23<BO$7+7),"T","")&IF(AND($AB23<>"",$AB23>=BO$7,$AB23<BO$7+7),"H","")&IF(AND($AC23<>"",$AC23>=BO$7,$AC23<BO$7+7),"G","")&IF(AND($AH23<>"",$AH23>=BO$7,$AH23<BO$7+7),"S","") | ... DC23: =IF(AND($Y23<>"",$Y23>=DC$7,$Y23<DC$7+7),"I","")&IF(AND($Z23<>"",$Z23>=DC$7,$Z23<DC$7+7),"P","")&IF(AND($AA23<>"",$AA23>=DC$7,$AA23<DC$7+7),"T","")&IF(AND($AB23<>"",$AB23>=DC$7,$AB23<DC$7+7),"H","")&IF(AND($AC23<>"",$AC23>=DC$7,$AC23<DC$7+7),"G","")&IF(AND($AH23<>"",$AH23>=DC$7,$AH23<DC$7+7),"S","")
